fulladder/fulladder.v
module fulladder (input a,b,c_in,output sum,c_out);
wire s1,c1,c2;
xor(s1,a,b);
xor(sum,s1,c_in);
and(c1,a,b);
and(c2,s1,c_in);
xor(c_out,c1,c2);
endmodule

bnb_adder/my_addsub4/adder4.v
module adder4(input signed [3:0] a, input signed [3:0] b, input c_in, 
              output signed [3:0] sum, output c_out);
wire [3:0] c;

fulladder fa1(a[0],b[0], c_in, sum[0], c[1]) ;
fulladder fa2(a[1],b[1], c[1], sum[1], c[2]) ;
fulladder fa3(a[2],b[2], c[2], sum[2], c[3]) ;
fulladder fa4(a[3],b[3], c[3], sum[3], c_out) ;

endmodule

hw1and2/adder/my_addsub4/CB/adder16.v
module adder16(input signed [15:0] a, input signed [15:0] b, input c_in, 
              output signed [15:0] sum, output c_out);
wire [3:0] c;

adder4 a1(a[3:0],b[3:0],c_in,sum[3:0],c[0]);
  adder4 a2(a[7:4],b[7:4],c[0],sum[7:4],c[1]);
  adder4 a3(a[11:8],b[11:8],c[1],sum[11:8],c[2]);
  adder4 a4(a[15:12],b[15:12],c[2],sum[15:12],c_out);

endmodule

adder/my_addsub4/half_adder.v
module half_adder(input a, input b, 
              output s, output o);
and(o,a,b);//Cout
xor(s,a,b);//sum
endmodule

adder/my_addsub4/half_adder4.v
module half_adder4(input signed [3:0] a, input b, 
              output signed [3:0] s, output c);
  wire [2:0] o;
half_adder ha1 (a[0],b,s[0],o[0]);
  half_adder ha2 (a[1],b,s[0],o[1]);
  half_adder ha3 (a[2],b,s[1],o[2]);
  half_adder ha4 (a[3],b,s[2],c);
endmodule

adder/my_addsub4/half_adder16.v
module half_adder16(input [15:0] a, input b, 
              output [15:0] s,output c);
  wire [2:0] o;
half_adder4 ha1 (a[3:0],b,s[3:0],o[0]);
  half_adder4 ha2 (a[7:4],o[0],s[7:4],o[1]);
  half_adder4 ha3 (a[11:8],o[1],s[11:8],o[2]);
  half_adder4 ha4 (a[15:12],o[2],s[15:12],c);
endmodule

adder/my_addsub4/xor16.v
module xor16(input [15:0] a, input [15:0] b, output signed [15:0] y);
 // assign y = a ^ b;

	xor(y[0],a[0],b[0]);
	xor(y[1],a[1],b[1]);
	xor(y[2],a[2],b[2]);
	xor(y[3],a[3],b[3]);
	xor(y[4],a[4],b[4]);
	xor(y[5],a[5],b[5]);
	xor(y[6],a[6],b[6]);
	xor(y[7],a[7],b[7]);
	xor(y[8],a[8],b[8]);
	xor(y[9],a[9],b[9]);
	xor(y[10],a[10],b[10]);
	xor(y[11],a[11],b[11]);
	xor(y[12],a[12],b[12]);
	xor(y[13],a[13],b[13]);
	xor(y[14],a[14],b[14]);
	xor(y[15],a[15],b[15]);

endmodule

adder/my_addsub4/adder_s.v
//`include "half_adder4.v";
//`include "adder16.v";
module adder_16bit_s(A , B ,Add_ctrl , O , C_out , SUM);

input [15:0] A , B ;
input Add_ctrl;//1 for sub ,0 for add

output [15:0] SUM ;
output C_out ;
output O ;
  
  wire [15:0] contrast;
wire [15:0] comp2;

  /** your code **/
  xor16 x1(B,{Add_ctrl,Add_ctrl,Add_ctrl,Add_ctrl,Add_ctrl,Add_ctrl,Add_ctrl,Add_ctrl,Add_ctrl,Add_ctrl,Add_ctrl,Add_ctrl,Add_ctrl,Add_ctrl,Add_ctrl,Add_ctrl},contrast);
half_adder16 ha1(contrast,Add_ctrl,comp2,co);
adder16 a1(A,comp2,0,SUM,C_out);

endmodule

before_mounth10/hw1and2/adder/my_addsub4/CB/un_used_testbench/Tas16.v
//MUX_tb
`timescale 1ns/10ps
`include "adder16.v"
`include "adder4.v"
`include "fulladder.v"
`include "xor16.v"
`include "half_adder.v"
`include "half_adder4.v"
`include "half_adder16.v"

module Tas16;

reg [15:0] a,b;
reg m;

wire [15:0] s;
wire o,c;
wire [15:0]tf;

adder_16bit_s as(a,b,m,o,c,s);
assign tf=a+b;

initial begin
a=16'd0;
b=16'd0;
m=1'b0;

$monitor($time," || a=%d | b=%d | s=%d | c=%b | ref=%d",a,b,s,c,tf);
end

always #10 begin
a=a+1'b1;
end

always #50 begin
b=b+1'b1;
end

initial # 5 begin
//a=16'b1111111111111111;
//b=1'b1;
# 5000 $finish;
end
  initial begin
    //generate waveform
	$dumpfile("Wxor.vcd");
	$dumpvars;
  end
  
endmodule

adder/my_addsub4/garbage/Wxor.vcd
$date
    Oct 14, 2019  20:19:33
$end
$version
    TOOL:	ncsim	15.20-s039
$end
$timescale
    10 ps
$end

$scope module Tas16 $end
$var reg      16 !    a [15:0] $end
$var reg      16 "    b [15:0] $end
$var reg       1 #    m  $end
$var wire      1 $    s [15] $end
$var wire      1 %    s [14] $end
$var wire      1 &    s [13] $end
$var wire      1 '    s [12] $end
$var wire      1 (    s [11] $end
$var wire      1 )    s [10] $end
$var wire      1 *    s [9] $end
$var wire      1 +    s [8] $end
$var wire      1 ,    s [7] $end
$var wire      1 -    s [6] $end
$var wire      1 .    s [5] $end
$var wire      1 /    s [4] $end
$var wire      1 0    s [3] $end
$var wire      1 1    s [2] $end
$var wire      1 2    s [1] $end
$var wire      1 3    s [0] $end
$var wire      1 4    o  $end
$var wire      1 5    c  $end
$var wire     16 6    tf [15:0] $end

$scope module as $end
$var wire      1 7    A [15] $end
$var wire      1 8    A [14] $end
$var wire      1 9    A [13] $end
$var wire      1 :    A [12] $end
$var wire      1 ;    A [11] $end
$var wire      1 <    A [10] $end
$var wire      1 =    A [9] $end
$var wire      1 >    A [8] $end
$var wire      1 ?    A [7] $end
$var wire      1 @    A [6] $end
$var wire      1 A    A [5] $end
$var wire      1 B    A [4] $end
$var wire      1 C    A [3] $end
$var wire      1 D    A [2] $end
$var wire      1 E    A [1] $end
$var wire      1 F    A [0] $end
$var wire      1 G    B [15] $end
$var wire      1 H    B [14] $end
$var wire      1 I    B [13] $end
$var wire      1 J    B [12] $end
$var wire      1 K    B [11] $end
$var wire      1 L    B [10] $end
$var wire      1 M    B [9] $end
$var wire      1 N    B [8] $end
$var wire      1 O    B [7] $end
$var wire      1 P    B [6] $end
$var wire      1 Q    B [5] $end
$var wire      1 R    B [4] $end
$var wire      1 S    B [3] $end
$var wire      1 T    B [2] $end
$var wire      1 U    B [1] $end
$var wire      1 V    B [0] $end
$var wire      1 W    Add_ctrl  $end
$var wire      1 $    SUM [15] $end
$var wire      1 %    SUM [14] $end
$var wire      1 &    SUM [13] $end
$var wire      1 '    SUM [12] $end
$var wire      1 (    SUM [11] $end
$var wire      1 )    SUM [10] $end
$var wire      1 *    SUM [9] $end
$var wire      1 +    SUM [8] $end
$var wire      1 ,    SUM [7] $end
$var wire      1 -    SUM [6] $end
$var wire      1 .    SUM [5] $end
$var wire      1 /    SUM [4] $end
$var wire      1 0    SUM [3] $end
$var wire      1 1    SUM [2] $end
$var wire      1 2    SUM [1] $end
$var wire      1 3    SUM [0] $end
$var wire      1 5    C_out  $end
$var wire      1 4    O  $end
$var wire      1 X    contrast [15] $end
$var wire      1 Y    contrast [14] $end
$var wire      1 Z    contrast [13] $end
$var wire      1 [    contrast [12] $end
$var wire      1 \    contrast [11] $end
$var wire      1 ]    contrast [10] $end
$var wire      1 ^    contrast [9] $end
$var wire      1 _    contrast [8] $end
$var wire      1 `    contrast [7] $end
$var wire      1 a    contrast [6] $end
$var wire      1 b    contrast [5] $end
$var wire      1 c    contrast [4] $end
$var wire      1 d    contrast [3] $end
$var wire      1 e    contrast [2] $end
$var wire      1 f    contrast [1] $end
$var wire      1 g    contrast [0] $end
$var wire      1 h    comp2 [15] $end
$var wire      1 i    comp2 [14] $end
$var wire      1 j    comp2 [13] $end
$var wire      1 k    comp2 [12] $end
$var wire      1 l    comp2 [11] $end
$var wire      1 m    comp2 [10] $end
$var wire      1 n    comp2 [9] $end
$var wire      1 o    comp2 [8] $end
$var wire      1 p    comp2 [7] $end
$var wire      1 q    comp2 [6] $end
$var wire      1 r    comp2 [5] $end
$var wire      1 s    comp2 [4] $end
$var wire      1 t    comp2 [3] $end
$var wire      1 u    comp2 [2] $end
$var wire      1 v    comp2 [1] $end
$var wire      1 w    comp2 [0] $end
$var wire      1 x    co  $end

$scope module x1 $end
$var wire      1 G    a [15] $end
$var wire      1 H    a [14] $end
$var wire      1 I    a [13] $end
$var wire      1 J    a [12] $end
$var wire      1 K    a [11] $end
$var wire      1 L    a [10] $end
$var wire      1 M    a [9] $end
$var wire      1 N    a [8] $end
$var wire      1 O    a [7] $end
$var wire      1 P    a [6] $end
$var wire      1 Q    a [5] $end
$var wire      1 R    a [4] $end
$var wire      1 S    a [3] $end
$var wire      1 T    a [2] $end
$var wire      1 U    a [1] $end
$var wire      1 V    a [0] $end
$var wire      1 W    b [15] $end
$var wire      1 W    b [14] $end
$var wire      1 W    b [13] $end
$var wire      1 W    b [12] $end
$var wire      1 W    b [11] $end
$var wire      1 W    b [10] $end
$var wire      1 W    b [9] $end
$var wire      1 W    b [8] $end
$var wire      1 W    b [7] $end
$var wire      1 W    b [6] $end
$var wire      1 W    b [5] $end
$var wire      1 W    b [4] $end
$var wire      1 W    b [3] $end
$var wire      1 W    b [2] $end
$var wire      1 W    b [1] $end
$var wire      1 W    b [0] $end
$var wire      1 X    y [15] $end
$var wire      1 Y    y [14] $end
$var wire      1 Z    y [13] $end
$var wire      1 [    y [12] $end
$var wire      1 \    y [11] $end
$var wire      1 ]    y [10] $end
$var wire      1 ^    y [9] $end
$var wire      1 _    y [8] $end
$var wire      1 `    y [7] $end
$var wire      1 a    y [6] $end
$var wire      1 b    y [5] $end
$var wire      1 c    y [4] $end
$var wire      1 d    y [3] $end
$var wire      1 e    y [2] $end
$var wire      1 f    y [1] $end
$var wire      1 g    y [0] $end
$upscope $end


$scope module ha1 $end
$var wire      1 X    a [15] $end
$var wire      1 Y    a [14] $end
$var wire      1 Z    a [13] $end
$var wire      1 [    a [12] $end
$var wire      1 \    a [11] $end
$var wire      1 ]    a [10] $end
$var wire      1 ^    a [9] $end
$var wire      1 _    a [8] $end
$var wire      1 `    a [7] $end
$var wire      1 a    a [6] $end
$var wire      1 b    a [5] $end
$var wire      1 c    a [4] $end
$var wire      1 d    a [3] $end
$var wire      1 e    a [2] $end
$var wire      1 f    a [1] $end
$var wire      1 g    a [0] $end
$var wire      1 W    b  $end
$var wire      1 h    s [15] $end
$var wire      1 i    s [14] $end
$var wire      1 j    s [13] $end
$var wire      1 k    s [12] $end
$var wire      1 l    s [11] $end
$var wire      1 m    s [10] $end
$var wire      1 n    s [9] $end
$var wire      1 o    s [8] $end
$var wire      1 p    s [7] $end
$var wire      1 q    s [6] $end
$var wire      1 r    s [5] $end
$var wire      1 s    s [4] $end
$var wire      1 t    s [3] $end
$var wire      1 u    s [2] $end
$var wire      1 v    s [1] $end
$var wire      1 w    s [0] $end
$var wire      1 x    c  $end
$var wire      1 y    o [2] $end
$var wire      1 z    o [1] $end
$var wire      1 {    o [0] $end

$scope module ha1 $end
$var wire      1 d    a [3] $end
$var wire      1 e    a [2] $end
$var wire      1 f    a [1] $end
$var wire      1 g    a [0] $end
$var wire      1 W    b  $end
$var wire      1 t    s [3] $end
$var wire      1 u    s [2] $end
$var wire      1 v    s [1] $end
$var wire      1 w    s [0] $end
$var wire      1 {    c  $end
$var wire      1 |    o [2] $end
$var wire      1 }    o [1] $end
$var wire      1 ~    o [0] $end

$scope module ha1 $end
$var wire      1 g    a  $end
$var wire      1 W    b  $end
$var wire      1 w    s  $end
$var wire      1 ~    o  $end
$upscope $end


$scope module ha2 $end
$var wire      1 f    a  $end
$var wire      1 ~    b  $end
$var wire      1 v    s  $end
$var wire      1 }    o  $end
$upscope $end


$scope module ha3 $end
$var wire      1 e    a  $end
$var wire      1 }    b  $end
$var wire      1 u    s  $end
$var wire      1 |    o  $end
$upscope $end


$scope module ha4 $end
$var wire      1 d    a  $end
$var wire      1 |    b  $end
$var wire      1 t    s  $end
$var wire      1 {    o  $end
$upscope $end

$upscope $end


$scope module ha2 $end
$var wire      1 `    a [3] $end
$var wire      1 a    a [2] $end
$var wire      1 b    a [1] $end
$var wire      1 c    a [0] $end
$var wire      1 {    b  $end
$var wire      1 p    s [3] $end
$var wire      1 q    s [2] $end
$var wire      1 r    s [1] $end
$var wire      1 s    s [0] $end
$var wire      1 z    c  $end
$var wire      1 !!   o [2] $end
$var wire      1 "!   o [1] $end
$var wire      1 #!   o [0] $end

$scope module ha1 $end
$var wire      1 c    a  $end
$var wire      1 {    b  $end
$var wire      1 s    s  $end
$var wire      1 #!   o  $end
$upscope $end


$scope module ha2 $end
$var wire      1 b    a  $end
$var wire      1 #!   b  $end
$var wire      1 r    s  $end
$var wire      1 "!   o  $end
$upscope $end


$scope module ha3 $end
$var wire      1 a    a  $end
$var wire      1 "!   b  $end
$var wire      1 q    s  $end
$var wire      1 !!   o  $end
$upscope $end


$scope module ha4 $end
$var wire      1 `    a  $end
$var wire      1 !!   b  $end
$var wire      1 p    s  $end
$var wire      1 z    o  $end
$upscope $end

$upscope $end


$scope module ha3 $end
$var wire      1 \    a [3] $end
$var wire      1 ]    a [2] $end
$var wire      1 ^    a [1] $end
$var wire      1 _    a [0] $end
$var wire      1 z    b  $end
$var wire      1 l    s [3] $end
$var wire      1 m    s [2] $end
$var wire      1 n    s [1] $end
$var wire      1 o    s [0] $end
$var wire      1 y    c  $end
$var wire      1 $!   o [2] $end
$var wire      1 %!   o [1] $end
$var wire      1 &!   o [0] $end

$scope module ha1 $end
$var wire      1 _    a  $end
$var wire      1 z    b  $end
$var wire      1 o    s  $end
$var wire      1 &!   o  $end
$upscope $end


$scope module ha2 $end
$var wire      1 ^    a  $end
$var wire      1 &!   b  $end
$var wire      1 n    s  $end
$var wire      1 %!   o  $end
$upscope $end


$scope module ha3 $end
$var wire      1 ]    a  $end
$var wire      1 %!   b  $end
$var wire      1 m    s  $end
$var wire      1 $!   o  $end
$upscope $end


$scope module ha4 $end
$var wire      1 \    a  $end
$var wire      1 $!   b  $end
$var wire      1 l    s  $end
$var wire      1 y    o  $end
$upscope $end

$upscope $end


$scope module ha4 $end
$var wire      1 X    a [3] $end
$var wire      1 Y    a [2] $end
$var wire      1 Z    a [1] $end
$var wire      1 [    a [0] $end
$var wire      1 y    b  $end
$var wire      1 h    s [3] $end
$var wire      1 i    s [2] $end
$var wire      1 j    s [1] $end
$var wire      1 k    s [0] $end
$var wire      1 x    c  $end
$var wire      1 '!   o [2] $end
$var wire      1 (!   o [1] $end
$var wire      1 )!   o [0] $end

$scope module ha1 $end
$var wire      1 [    a  $end
$var wire      1 y    b  $end
$var wire      1 k    s  $end
$var wire      1 )!   o  $end
$upscope $end


$scope module ha2 $end
$var wire      1 Z    a  $end
$var wire      1 )!   b  $end
$var wire      1 j    s  $end
$var wire      1 (!   o  $end
$upscope $end


$scope module ha3 $end
$var wire      1 Y    a  $end
$var wire      1 (!   b  $end
$var wire      1 i    s  $end
$var wire      1 '!   o  $end
$upscope $end


$scope module ha4 $end
$var wire      1 X    a  $end
$var wire      1 '!   b  $end
$var wire      1 h    s  $end
$var wire      1 x    o  $end
$upscope $end

$upscope $end

$upscope $end


$scope module a1 $end
$var wire      1 7    a [15] $end
$var wire      1 8    a [14] $end
$var wire      1 9    a [13] $end
$var wire      1 :    a [12] $end
$var wire      1 ;    a [11] $end
$var wire      1 <    a [10] $end
$var wire      1 =    a [9] $end
$var wire      1 >    a [8] $end
$var wire      1 ?    a [7] $end
$var wire      1 @    a [6] $end
$var wire      1 A    a [5] $end
$var wire      1 B    a [4] $end
$var wire      1 C    a [3] $end
$var wire      1 D    a [2] $end
$var wire      1 E    a [1] $end
$var wire      1 F    a [0] $end
$var wire      1 h    b [15] $end
$var wire      1 i    b [14] $end
$var wire      1 j    b [13] $end
$var wire      1 k    b [12] $end
$var wire      1 l    b [11] $end
$var wire      1 m    b [10] $end
$var wire      1 n    b [9] $end
$var wire      1 o    b [8] $end
$var wire      1 p    b [7] $end
$var wire      1 q    b [6] $end
$var wire      1 r    b [5] $end
$var wire      1 s    b [4] $end
$var wire      1 t    b [3] $end
$var wire      1 u    b [2] $end
$var wire      1 v    b [1] $end
$var wire      1 w    b [0] $end
$var wire      1 *!   c_in  $end
$var wire      1 $    sum [15] $end
$var wire      1 %    sum [14] $end
$var wire      1 &    sum [13] $end
$var wire      1 '    sum [12] $end
$var wire      1 (    sum [11] $end
$var wire      1 )    sum [10] $end
$var wire      1 *    sum [9] $end
$var wire      1 +    sum [8] $end
$var wire      1 ,    sum [7] $end
$var wire      1 -    sum [6] $end
$var wire      1 .    sum [5] $end
$var wire      1 /    sum [4] $end
$var wire      1 0    sum [3] $end
$var wire      1 1    sum [2] $end
$var wire      1 2    sum [1] $end
$var wire      1 3    sum [0] $end
$var wire      1 5    c_out  $end
$var wire      1 +!   c [3] $end
$var wire      1 ,!   c [2] $end
$var wire      1 -!   c [1] $end
$var wire      1 .!   c [0] $end

$scope module a1 $end
$var wire      1 C    a [3] $end
$var wire      1 D    a [2] $end
$var wire      1 E    a [1] $end
$var wire      1 F    a [0] $end
$var wire      1 t    b [3] $end
$var wire      1 u    b [2] $end
$var wire      1 v    b [1] $end
$var wire      1 w    b [0] $end
$var wire      1 *!   c_in  $end
$var wire      1 0    sum [3] $end
$var wire      1 1    sum [2] $end
$var wire      1 2    sum [1] $end
$var wire      1 3    sum [0] $end
$var wire      1 .!   c_out  $end
$var wire      1 /!   c [3] $end
$var wire      1 0!   c [2] $end
$var wire      1 1!   c [1] $end
$var wire      1 2!   c [0] $end

$scope module fa1 $end
$var wire      1 F    a  $end
$var wire      1 w    b  $end
$var wire      1 *!   c_in  $end
$var wire      1 3    sum  $end
$var wire      1 1!   c_out  $end
$var wire      1 3!   s1  $end
$var wire      1 4!   c1  $end
$var wire      1 5!   c2  $end
$upscope $end


$scope module fa2 $end
$var wire      1 E    a  $end
$var wire      1 v    b  $end
$var wire      1 1!   c_in  $end
$var wire      1 2    sum  $end
$var wire      1 0!   c_out  $end
$var wire      1 6!   s1  $end
$var wire      1 7!   c1  $end
$var wire      1 8!   c2  $end
$upscope $end


$scope module fa3 $end
$var wire      1 D    a  $end
$var wire      1 u    b  $end
$var wire      1 0!   c_in  $end
$var wire      1 1    sum  $end
$var wire      1 /!   c_out  $end
$var wire      1 9!   s1  $end
$var wire      1 :!   c1  $end
$var wire      1 ;!   c2  $end
$upscope $end


$scope module fa4 $end
$var wire      1 C    a  $end
$var wire      1 t    b  $end
$var wire      1 /!   c_in  $end
$var wire      1 0    sum  $end
$var wire      1 .!   c_out  $end
$var wire      1 <!   s1  $end
$var wire      1 =!   c1  $end
$var wire      1 >!   c2  $end
$upscope $end

$upscope $end


$scope module a2 $end
$var wire      1 ?    a [3] $end
$var wire      1 @    a [2] $end
$var wire      1 A    a [1] $end
$var wire      1 B    a [0] $end
$var wire      1 p    b [3] $end
$var wire      1 q    b [2] $end
$var wire      1 r    b [1] $end
$var wire      1 s    b [0] $end
$var wire      1 .!   c_in  $end
$var wire      1 ,    sum [3] $end
$var wire      1 -    sum [2] $end
$var wire      1 .    sum [1] $end
$var wire      1 /    sum [0] $end
$var wire      1 -!   c_out  $end
$var wire      1 ?!   c [3] $end
$var wire      1 @!   c [2] $end
$var wire      1 A!   c [1] $end
$var wire      1 B!   c [0] $end

$scope module fa1 $end
$var wire      1 B    a  $end
$var wire      1 s    b  $end
$var wire      1 .!   c_in  $end
$var wire      1 /    sum  $end
$var wire      1 A!   c_out  $end
$var wire      1 C!   s1  $end
$var wire      1 D!   c1  $end
$var wire      1 E!   c2  $end
$upscope $end


$scope module fa2 $end
$var wire      1 A    a  $end
$var wire      1 r    b  $end
$var wire      1 A!   c_in  $end
$var wire      1 .    sum  $end
$var wire      1 @!   c_out  $end
$var wire      1 F!   s1  $end
$var wire      1 G!   c1  $end
$var wire      1 H!   c2  $end
$upscope $end


$scope module fa3 $end
$var wire      1 @    a  $end
$var wire      1 q    b  $end
$var wire      1 @!   c_in  $end
$var wire      1 -    sum  $end
$var wire      1 ?!   c_out  $end
$var wire      1 I!   s1  $end
$var wire      1 J!   c1  $end
$var wire      1 K!   c2  $end
$upscope $end


$scope module fa4 $end
$var wire      1 ?    a  $end
$var wire      1 p    b  $end
$var wire      1 ?!   c_in  $end
$var wire      1 ,    sum  $end
$var wire      1 -!   c_out  $end
$var wire      1 L!   s1  $end
$var wire      1 M!   c1  $end
$var wire      1 N!   c2  $end
$upscope $end

$upscope $end


$scope module a3 $end
$var wire      1 ;    a [3] $end
$var wire      1 <    a [2] $end
$var wire      1 =    a [1] $end
$var wire      1 >    a [0] $end
$var wire      1 l    b [3] $end
$var wire      1 m    b [2] $end
$var wire      1 n    b [1] $end
$var wire      1 o    b [0] $end
$var wire      1 -!   c_in  $end
$var wire      1 (    sum [3] $end
$var wire      1 )    sum [2] $end
$var wire      1 *    sum [1] $end
$var wire      1 +    sum [0] $end
$var wire      1 ,!   c_out  $end
$var wire      1 O!   c [3] $end
$var wire      1 P!   c [2] $end
$var wire      1 Q!   c [1] $end
$var wire      1 R!   c [0] $end

$scope module fa1 $end
$var wire      1 >    a  $end
$var wire      1 o    b  $end
$var wire      1 -!   c_in  $end
$var wire      1 +    sum  $end
$var wire      1 Q!   c_out  $end
$var wire      1 S!   s1  $end
$var wire      1 T!   c1  $end
$var wire      1 U!   c2  $end
$upscope $end


$scope module fa2 $end
$var wire      1 =    a  $end
$var wire      1 n    b  $end
$var wire      1 Q!   c_in  $end
$var wire      1 *    sum  $end
$var wire      1 P!   c_out  $end
$var wire      1 V!   s1  $end
$var wire      1 W!   c1  $end
$var wire      1 X!   c2  $end
$upscope $end


$scope module fa3 $end
$var wire      1 <    a  $end
$var wire      1 m    b  $end
$var wire      1 P!   c_in  $end
$var wire      1 )    sum  $end
$var wire      1 O!   c_out  $end
$var wire      1 Y!   s1  $end
$var wire      1 Z!   c1  $end
$var wire      1 [!   c2  $end
$upscope $end


$scope module fa4 $end
$var wire      1 ;    a  $end
$var wire      1 l    b  $end
$var wire      1 O!   c_in  $end
$var wire      1 (    sum  $end
$var wire      1 ,!   c_out  $end
$var wire      1 \!   s1  $end
$var wire      1 ]!   c1  $end
$var wire      1 ^!   c2  $end
$upscope $end

$upscope $end


$scope module a4 $end
$var wire      1 7    a [3] $end
$var wire      1 8    a [2] $end
$var wire      1 9    a [1] $end
$var wire      1 :    a [0] $end
$var wire      1 h    b [3] $end
$var wire      1 i    b [2] $end
$var wire      1 j    b [1] $end
$var wire      1 k    b [0] $end
$var wire      1 ,!   c_in  $end
$var wire      1 $    sum [3] $end
$var wire      1 %    sum [2] $end
$var wire      1 &    sum [1] $end
$var wire      1 '    sum [0] $end
$var wire      1 5    c_out  $end
$var wire      1 _!   c [3] $end
$var wire      1 `!   c [2] $end
$var wire      1 a!   c [1] $end
$var wire      1 b!   c [0] $end

$scope module fa1 $end
$var wire      1 :    a  $end
$var wire      1 k    b  $end
$var wire      1 ,!   c_in  $end
$var wire      1 '    sum  $end
$var wire      1 a!   c_out  $end
$var wire      1 c!   s1  $end
$var wire      1 d!   c1  $end
$var wire      1 e!   c2  $end
$upscope $end


$scope module fa2 $end
$var wire      1 9    a  $end
$var wire      1 j    b  $end
$var wire      1 a!   c_in  $end
$var wire      1 &    sum  $end
$var wire      1 `!   c_out  $end
$var wire      1 f!   s1  $end
$var wire      1 g!   c1  $end
$var wire      1 h!   c2  $end
$upscope $end


$scope module fa3 $end
$var wire      1 8    a  $end
$var wire      1 i    b  $end
$var wire      1 `!   c_in  $end
$var wire      1 %    sum  $end
$var wire      1 _!   c_out  $end
$var wire      1 i!   s1  $end
$var wire      1 j!   c1  $end
$var wire      1 k!   c2  $end
$upscope $end


$scope module fa4 $end
$var wire      1 7    a  $end
$var wire      1 h    b  $end
$var wire      1 _!   c_in  $end
$var wire      1 $    sum  $end
$var wire      1 5    c_out  $end
$var wire      1 l!   s1  $end
$var wire      1 m!   c1  $end
$var wire      1 n!   c2  $end
$upscope $end

$upscope $end

$upscope $end

$upscope $end

$upscope $end

$enddefinitions $end
$dumpvars
b0 !
b0 "
0#
0$
0%
0&
0'
0(
0)
0*
0+
0,
0-
0.
0/
00
01
02
03
z4
05
b0 6
07
08
09
0:
0;
0<
0=
0>
0?
0@
0A
0B
0C
0D
0E
0F
0G
0H
0I
0J
0K
0L
0M
0N
0O
0P
0Q
0R
0S
0T
0U
0V
0W
0X
0Y
0Z
0[
0\
0]
0^
0_
0`
0a
0b
0c
0d
0e
0f
0g
0h
0i
0j
0k
0l
0m
0n
0o
0p
0q
0r
0s
0t
0u
0v
0w
0x
0y
0z
0{
0|
0}
0~
0!!
0"!
0#!
0$!
0%!
0&!
0'!
0(!
0)!
0*!
z+!
0,!
0-!
0.!
0/!
00!
01!
z2!
03!
04!
05!
06!
07!
08!
09!
0:!
0;!
0<!
0=!
0>!
0?!
0@!
0A!
zB!
0C!
0D!
0E!
0F!
0G!
0H!
0I!
0J!
0K!
0L!
0M!
0N!
0O!
0P!
0Q!
zR!
0S!
0T!
0U!
0V!
0W!
0X!
0Y!
0Z!
0[!
0\!
0]!
0^!
0_!
0`!
0a!
zb!
0c!
0d!
0e!
0f!
0g!
0h!
0i!
0j!
0k!
0l!
0m!
0n!
$end
#1000
b1 !
1F
b1 6
13!
13
#2000
b10 !
1E
0F
b10 6
03!
16!
12
03
#3000
b11 !
1F
b11 6
13!
13
#4000
b100 !
1D
0E
0F
b100 6
03!
06!
19!
11
02
03
#5000
b1 "
b101 !
1F
1V
b110 6
1g
03!
03
1w
14!
11!
12
#6000
b110 !
1E
0F
b111 6
13!
04!
01!
16!
13
#7000
b111 !
1F
b1000 6
03!
14!
11!
02
18!
10!
03
01
1;!
1/!
10
#8000
b1000 !
1C
0D
0E
0F
b1001 6
13!
04!
01!
06!
08!
00!
09!
0;!
0/!
1<!
13
#9000
b1001 !
1F
b1010 6
03!
14!
11!
12
03
#10000
b10 "
b1010 !
1E
0F
1U
0V
b1100 6
0g
1f
03!
04!
01!
06!
03
1v
0w
17!
10!
11
02
#11000
b1011 !
1F
b1101 6
13!
13
#12000
b1100 !
1D
0E
0F
b1110 6
03!
16!
07!
00!
19!
12
03
#13000
b1101 !
1F
b1111 6
13!
13
#14000
b1110 !
1E
0F
b10000 6
03!
06!
17!
10!
01
1;!
1/!
02
03
00
1>!
1.!
1/
#15000
b11 "
b1111 !
1F
1V
b10010 6
1g
03!
03
1w
14!
11!
12
#16000
b10000 !
1B
0C
0D
0E
0F
b10011 6
13!
04!
01!
16!
07!
00!
09!
0;!
0/!
0<!
0>!
0.!
1C!
13
#17000
b10001 !
1F
b10100 6
03!
14!
11!
02
18!
10!
03
11
#18000
b10010 !
1E
0F
b10101 6
13!
04!
01!
06!
17!
08!
13
#19000
b10011 !
1F
b10110 6
03!
14!
11!
12
03
#20000
b100 "
b10100 !
1D
0E
0F
1T
0U
0V
b11000 6
0g
0f
1e
03!
04!
01!
06!
07!
00!
09!
03
1u
0v
0w
1:!
1/!
10
01
02
#21000
b10101 !
1F
b11001 6
13!
13
#22000
b10110 !
1E
0F
b11010 6
03!
16!
12
03
#23000
b10111 !
1F
b11011 6
13!
13
#24000
b11000 !
1C
0D
0E
0F
b11100 6
03!
06!
19!
0:!
0/!
1<!
11
02
03
#25000
b101 "
b11001 !
1F
1V
b11110 6
1g
03!
03
1w
14!
11!
12
#26000
b11010 !
1E
0F
b11111 6
13!
04!
01!
16!
13
#27000
b11011 !
1F
b100000 6
03!
14!
11!
02
18!
10!
03
01
1;!
1/!
00
1>!
1.!
0/
1E!
1A!
1.
#28000
b11100 !
1D
0E
0F
b100001 6
13!
04!
01!
06!
08!
00!
09!
1:!
0;!
13
#29000
b11101 !
1F
b100010 6
03!
14!
11!
12
03
#30000
b110 "
b11110 !
1E
0F
1U
0V
b100100 6
0g
1f
03!
04!
01!
06!
03
1v
0w
17!
10!
11
02
#31000
b11111 !
1F
b100101 6
13!
13
#32000
b100000 !
1A
0B
0C
0D
0E
0F
b100110 6
03!
16!
07!
00!
19!
0:!
0/!
0<!
0>!
0.!
0C!
0E!
0A!
1F!
12
03
#33000
b100001 !
1F
b100111 6
13!
13
#34000
b100010 !
1E
0F
b101000 6
03!
06!
17!
10!
01
1;!
1/!
02
03
10
#35000
b111 "
b100011 !
1F
1V
b101010 6
1g
03!
03
1w
14!
11!
12
#36000
b100100 !
1D
0E
0F
b101011 6
13!
04!
01!
16!
07!
00!
09!
1:!
0;!
13
#37000
b100101 !
1F
b101100 6
03!
14!
11!
02
18!
10!
03
11
#38000
b100110 !
1E
0F
b101101 6
13!
04!
01!
06!
17!
08!
13
#39000
b100111 !
1F
b101110 6
03!
14!
11!
12
03
#40000
b1000 "
b101000 !
1C
0D
0E
0F
1S
0T
0U
0V
b110000 6
0g
0f
0e
1d
03!
04!
01!
06!
07!
00!
09!
0:!
0/!
0<!
03
1t
0u
0v
0w
1=!
1.!
1/
00
01
02
#41000
b101001 !
1F
b110001 6
13!
13
#42000
b101010 !
1E
0F
b110010 6
03!
16!
12
03
#43000
b101011 !
1F
b110011 6
13!
13
#44000
b101100 !
1D
0E
0F
b110100 6
03!
06!
19!
11
02
03
#45000
b1001 "
b101101 !
1F
1V
b110110 6
1g
03!
03
1w
14!
11!
12
#46000
b101110 !
1E
0F
b110111 6
13!
04!
01!
16!
13
#47000
b101111 !
1F
b111000 6
03!
14!
11!
02
18!
10!
03
01
1;!
1/!
10
#48000
b110000 !
1B
0C
0D
0E
0F
b111001 6
13!
04!
01!
06!
08!
00!
09!
0;!
0/!
1<!
0=!
0.!
1C!
13
#49000
b110001 !
1F
b111010 6
03!
14!
11!
12
03
#50000
b1010 "
b110010 !
1E
0F
1U
0V
b111100 6
0g
1f
03!
04!
01!
06!
03
1v
0w
17!
10!
11
02
