synchronous_ctr/structural/MUX.v
module MUX(Din1,Din2,Sel,Dout);
input  [4:0] Din1;
input  [4:0] Din2;
input  Sel ;
output [4:0] Dout;

wire Sel_;
wire [4:0] w1 ,w2;

not (Sel_ ,Sel  );

and (w1[0]   ,Din1[0] ,Sel  );
and (w2[0]   ,Din2[0] ,Sel_ );
or  (Dout[0] ,w1[0]   ,w2[0]   );

and (w1[1]   ,Din1[1] ,Sel  );
and (w2[1]   ,Din2[1] ,Sel_ );
or  (Dout[1] ,w1[1]   ,w2[1]   );

and (w1[2]   ,Din1[2] ,Sel  );
and (w2[2]   ,Din2[2] ,Sel_ );
or  (Dout[2] ,w1[2]   ,w2[2]   );

and (w1[3]   ,Din1[3] ,Sel  );
and (w2[3]   ,Din2[3] ,Sel_ );
or  (Dout[3] ,w1[3]   ,w2[3]   );

and (w1[4]   ,Din1[4] ,Sel  );
and (w2[4]   ,Din2[4] ,Sel_ );
or  (Dout[4] ,w1[4]   ,w2[4]   );
endmodule

adder/my_addsub4/half_adder.v
module half_adder(input a, input b, 
              output s, output o);
and(o,a,b);//Cout
xor(s,a,b);//sum
endmodule

synchronous_ctr/structural/half_adder5.v
module half_adder5(input [4:0] a, input b, 
              output [4:0] s,output c);
  wire [3:0] o;
half_adder ha1 (a[0],b,s[0],o[0]);
  half_adder ha2 (a[1],o[0],s[1],o[1]);
  half_adder ha3 (a[2],o[1],s[2],o[2]);
  half_adder ha4 (a[3],o[2],s[3],o[3]);
half_adder ha5 (a[4],o[3],s[4],c);
endmodule

before_mounth10/hw1and2/synchronous_ctr/structural/eq5.v
module eq5(input [4:0] a,input [4:0] b,output s);
//=====================
//output = 1 if occurs a != b
//else s = o
//====================
wire [4:0] c;
wire [2:0] d;
xor(c[0],a[0],b[0]);
xor(c[1],a[1],b[1]);
xor(c[2],a[2],b[2]);
xor(c[3],a[3],b[3]);
xor(c[4],a[4],b[4]);
or(d[0],c[0],c[1]);
or(d[1],d[0],c[2]);
or(d[2],d[1],c[3]);
or(s,d[2],c[4]);
endmodule

before_mounth10/hw1and2/synchronous_ctr/structural/subtractor_borrow.v
module subtractor_borrow(input targ,input sub,output out,output bor);
xor(out,targ,sub);
and (bor,sub,out);
endmodule

synchronous_ctr/structural/sub_bor5.v
module sub_bor5(input [4:0] inp,input s/*for subtractor*/,output [4:0] a/*for ans*/,output c/*borrow*/);
wire [3:0] tmp;
subtractor_borrow sb1(inp[0],s,a[0],tmp[0]);
subtractor_borrow sb2(inp[1],tmp[0],a[1],tmp[1]);
subtractor_borrow sb3(inp[2],tmp[1],a[2],tmp[2]);
subtractor_borrow sb4(inp[3],tmp[2],a[3],tmp[3]);
subtractor_borrow sb5(inp[4],tmp[3],a[4],c);
endmodule

synchronous_ctr/structural/SR_latch_gate.v
module SR_latch_gate (input R, input S, output Q,output Qbar);
nor (Q , R,Qbar);
nor(Qbar,S,Q);
endmodule

hw1and2/synchronous_ctr/structural/enable_sr.v
module enable_sr(
input d,/*data*/
input e,/*enable*/
output q,
output p/*q bar*/);

//=======================
//use "nor" to do latch
//the thing that lay out with q is r
//and p is with s
//=======================


wire od,s,r;

not(od,d);
and(r,od,e);
and(s,e,d);
SR_latch_gate sr1(r,s,q,p);

endmodule

before_mounth10/hw1and2/synchronous_ctr/structural/rising_edge_trigger_ff.v
module rising_edge_trigger_ff(input d,input clk ,output q);
wire p,n,un,uc;
not(n,clk);
enable_sr sr1(d,n,p,nu);
enable_sr sr2(p,clk,q,nc);
endmodule

synchronous_ctr/structural/ff5.v
module ff5(input clk,input [4:0] d, output [4:0] q);
rising_edge_trigger_ff r1 (d[0],clk,q[0]);
rising_edge_trigger_ff r2 (d[1],clk,q[1]);
rising_edge_trigger_ff r3 (d[2],clk,q[2]);
rising_edge_trigger_ff r4 (d[3],clk,q[3]);
rising_edge_trigger_ff r5 (d[4],clk,q[4]);
endmodule

synchronous_ctr/structural/synchronous_ctr_s.v
module synchronous_ctr_s(
input clk,
input ct,/*control | '0' -> '+' |  '1' -> '-'*/
input cn,/*count*/
input rst,
output [4:0] op
);
wire [4:0] iop;
ff5 f1(clk,iop,op);
wire p0;
eq5 e1(op,5'd0,p0);
wire [4:0] p1;
wire nc1;
sub_bor5 s1(op,cn,p1,nc1);
wire [4:0] p2;
MUX m1(p1,5'd0,p0,p2);
wire p3;
eq5 e2(op,5'd20,p3);
wire [4:0] p4;
wire nc2;
half_adder5 h5(op,cn,p4,nc2);
wire [4:0] p5;
MUX m2(p2,p4,p3,p5);
wire [4:0] p6;
MUX m3(p5,op,cn,p6);
MUX m4(5'd0,p6,rst,iop);
endmodule

hw1and2/synchronous_ctr/structural/testbench.v
`timescale 1ns/1ps
`include "synchronous_ctr_s.v"
`include "half_adder.v"
`include "half_adder5.v"
`include "ff5.v"
`include "eq5.v"
`include "enable_sr.v"
`include "rising_edge_trigger_ff.v"
`include "SR_latch_gate.v"
`include "sub_bor5.v"
`include "subtractor_borrow.v"
`include "MUX.v"

module testbench;

reg ct,clk,cn,rst;
wire [4:0] op;

synchronous_ctr_s scs(clk,ct,cn,rst,op);

integer i,j;

initial begin
rst = 0;
clk = 0;
cn = 1;
ct = 0;
end

initial begin
$monitor("Time= %d | op= %d",$time,op);
end

always #10 begin
clk=~clk;
end

//raw test
/*
initial #5 begin
rst = 1;
#10 rst =0;
#10 cn=1;
#10 cn=0;
#10 cn=1;
#10 cn=0;
#10 $finish;
end
*/

initial begin
# 5 rst=1;
#10 rst =0;
for(j=0;j<2;j=j+1)
begin
	for(i=0;i<42;i=i+1)
	begin
		#10 cn=~cn;
	end
	ct=1;
	for(i=0;i<42;i=i+1)
	begin
		#10 cn=~cn;
	end
	ct=~ct;
end
//#10 $finish;
end

initial begin
#1000 rst=1;
#10 rst = 0;
#190 rst = 1;
#10 rst =0;
end

initial #1985 begin
for(j=0;j<50;j=j+1)
begin
//+4
#15 ct=0;
#15 for(i=0;i<8;i=i+1)
begin
#10 cn=~cn;
end
//-2
#10 ct=1;
#10 for(i=0;i<4;i=i+1)
begin
#10 cn=~cn;
end
//+8
#10 ct=0;
#10 for(i=0;i<16;i=i+1)
begin
#10 cn=~cn;
end
//-6
#10 ct=1;
#10 for(i=0;i<11;i=i+1)
begin
#10 cn=~cn;
end
end
#10 $finish;
end

initial begin
$dumpfile("scb.vcd");
$dumpvars;
end

endmodule

synchronous_ctr/structural/scb.vcd
$date
    Oct 16, 2019  05:18:58
$end
$version
    TOOL:	ncsim	15.20-s039
$end
$timescale
    1 ps
$end

$scope module testbench $end
$var reg       1 !    ct  $end
$var reg       1 "    clk  $end
$var reg       1 #    cn  $end
$var reg       1 $    rst  $end
$var wire      1 %    op [4] $end
$var wire      1 &    op [3] $end
$var wire      1 '    op [2] $end
$var wire      1 (    op [1] $end
$var wire      1 )    op [0] $end
$var integer  32 *    i  $end
$var integer  32 +    j  $end

$scope module scs $end
$var wire      1 ,    clk  $end
$var wire      1 -    ct  $end
$var wire      1 .    cn  $end
$var wire      1 /    rst  $end
$var wire      1 %    op [4] $end
$var wire      1 &    op [3] $end
$var wire      1 '    op [2] $end
$var wire      1 (    op [1] $end
$var wire      1 )    op [0] $end
$var wire      1 0    iop [4] $end
$var wire      1 1    iop [3] $end
$var wire      1 2    iop [2] $end
$var wire      1 3    iop [1] $end
$var wire      1 4    iop [0] $end
$var wire      1 5    p0  $end
$var wire      1 6    p1 [4] $end
$var wire      1 7    p1 [3] $end
$var wire      1 8    p1 [2] $end
$var wire      1 9    p1 [1] $end
$var wire      1 :    p1 [0] $end
$var wire      1 ;    nc1  $end
$var wire      1 <    p2 [4] $end
$var wire      1 =    p2 [3] $end
$var wire      1 >    p2 [2] $end
$var wire      1 ?    p2 [1] $end
$var wire      1 @    p2 [0] $end
$var wire      1 A    p3  $end
$var wire      1 B    p4 [4] $end
$var wire      1 C    p4 [3] $end
$var wire      1 D    p4 [2] $end
$var wire      1 E    p4 [1] $end
$var wire      1 F    p4 [0] $end
$var wire      1 G    nc2  $end
$var wire      1 H    p5 [4] $end
$var wire      1 I    p5 [3] $end
$var wire      1 J    p5 [2] $end
$var wire      1 K    p5 [1] $end
$var wire      1 L    p5 [0] $end
$var wire      1 M    p6 [4] $end
$var wire      1 N    p6 [3] $end
$var wire      1 O    p6 [2] $end
$var wire      1 P    p6 [1] $end
$var wire      1 Q    p6 [0] $end

$scope module f1 $end
$var wire      1 ,    clk  $end
$var wire      1 0    d [4] $end
$var wire      1 1    d [3] $end
$var wire      1 2    d [2] $end
$var wire      1 3    d [1] $end
$var wire      1 4    d [0] $end
$var wire      1 %    q [4] $end
$var wire      1 &    q [3] $end
$var wire      1 '    q [2] $end
$var wire      1 (    q [1] $end
$var wire      1 )    q [0] $end

$scope module r1 $end
$var wire      1 4    d  $end
$var wire      1 ,    clk  $end
$var wire      1 )    q  $end
$var wire      1 R    p  $end
$var wire      1 S    n  $end
$var wire      1 T    un  $end
$var wire      1 U    uc  $end
$var wire      1 V    nu  $end
$var wire      1 W    nc  $end

$scope module sr1 $end
$var wire      1 4    d  $end
$var wire      1 S    e  $end
$var wire      1 R    q  $end
$var wire      1 V    p  $end
$var wire      1 X    od  $end
$var wire      1 Y    s  $end
$var wire      1 Z    r  $end

$scope module sr1 $end
$var wire      1 Z    R  $end
$var wire      1 Y    S  $end
$var wire      1 R    Q  $end
$var wire      1 V    Qbar  $end
$upscope $end

$upscope $end


$scope module sr2 $end
$var wire      1 R    d  $end
$var wire      1 ,    e  $end
$var wire      1 )    q  $end
$var wire      1 W    p  $end
$var wire      1 [    od  $end
$var wire      1 \    s  $end
$var wire      1 ]    r  $end

$scope module sr1 $end
$var wire      1 ]    R  $end
$var wire      1 \    S  $end
$var wire      1 )    Q  $end
$var wire      1 W    Qbar  $end
$upscope $end

$upscope $end

$upscope $end


$scope module r2 $end
$var wire      1 3    d  $end
$var wire      1 ,    clk  $end
$var wire      1 (    q  $end
$var wire      1 ^    p  $end
$var wire      1 _    n  $end
$var wire      1 `    un  $end
$var wire      1 a    uc  $end
$var wire      1 b    nu  $end
$var wire      1 c    nc  $end

$scope module sr1 $end
$var wire      1 3    d  $end
$var wire      1 _    e  $end
$var wire      1 ^    q  $end
$var wire      1 b    p  $end
$var wire      1 d    od  $end
$var wire      1 e    s  $end
$var wire      1 f    r  $end

$scope module sr1 $end
$var wire      1 f    R  $end
$var wire      1 e    S  $end
$var wire      1 ^    Q  $end
$var wire      1 b    Qbar  $end
$upscope $end

$upscope $end


$scope module sr2 $end
$var wire      1 ^    d  $end
$var wire      1 ,    e  $end
$var wire      1 (    q  $end
$var wire      1 c    p  $end
$var wire      1 g    od  $end
$var wire      1 h    s  $end
$var wire      1 i    r  $end

$scope module sr1 $end
$var wire      1 i    R  $end
$var wire      1 h    S  $end
$var wire      1 (    Q  $end
$var wire      1 c    Qbar  $end
$upscope $end

$upscope $end

$upscope $end


$scope module r3 $end
$var wire      1 2    d  $end
$var wire      1 ,    clk  $end
$var wire      1 '    q  $end
$var wire      1 j    p  $end
$var wire      1 k    n  $end
$var wire      1 l    un  $end
$var wire      1 m    uc  $end
$var wire      1 n    nu  $end
$var wire      1 o    nc  $end

$scope module sr1 $end
$var wire      1 2    d  $end
$var wire      1 k    e  $end
$var wire      1 j    q  $end
$var wire      1 n    p  $end
$var wire      1 p    od  $end
$var wire      1 q    s  $end
$var wire      1 r    r  $end

$scope module sr1 $end
$var wire      1 r    R  $end
$var wire      1 q    S  $end
$var wire      1 j    Q  $end
$var wire      1 n    Qbar  $end
$upscope $end

$upscope $end


$scope module sr2 $end
$var wire      1 j    d  $end
$var wire      1 ,    e  $end
$var wire      1 '    q  $end
$var wire      1 o    p  $end
$var wire      1 s    od  $end
$var wire      1 t    s  $end
$var wire      1 u    r  $end

$scope module sr1 $end
$var wire      1 u    R  $end
$var wire      1 t    S  $end
$var wire      1 '    Q  $end
$var wire      1 o    Qbar  $end
$upscope $end

$upscope $end

$upscope $end


$scope module r4 $end
$var wire      1 1    d  $end
$var wire      1 ,    clk  $end
$var wire      1 &    q  $end
$var wire      1 v    p  $end
$var wire      1 w    n  $end
$var wire      1 x    un  $end
$var wire      1 y    uc  $end
$var wire      1 z    nu  $end
$var wire      1 {    nc  $end

$scope module sr1 $end
$var wire      1 1    d  $end
$var wire      1 w    e  $end
$var wire      1 v    q  $end
$var wire      1 z    p  $end
$var wire      1 |    od  $end
$var wire      1 }    s  $end
$var wire      1 ~    r  $end

$scope module sr1 $end
$var wire      1 ~    R  $end
$var wire      1 }    S  $end
$var wire      1 v    Q  $end
$var wire      1 z    Qbar  $end
$upscope $end

$upscope $end


$scope module sr2 $end
$var wire      1 v    d  $end
$var wire      1 ,    e  $end
$var wire      1 &    q  $end
$var wire      1 {    p  $end
$var wire      1 !!   od  $end
$var wire      1 "!   s  $end
$var wire      1 #!   r  $end

$scope module sr1 $end
$var wire      1 #!   R  $end
$var wire      1 "!   S  $end
$var wire      1 &    Q  $end
$var wire      1 {    Qbar  $end
$upscope $end

$upscope $end

$upscope $end


$scope module r5 $end
$var wire      1 0    d  $end
$var wire      1 ,    clk  $end
$var wire      1 %    q  $end
$var wire      1 $!   p  $end
$var wire      1 %!   n  $end
$var wire      1 &!   un  $end
$var wire      1 '!   uc  $end
$var wire      1 (!   nu  $end
$var wire      1 )!   nc  $end

$scope module sr1 $end
$var wire      1 0    d  $end
$var wire      1 %!   e  $end
$var wire      1 $!   q  $end
$var wire      1 (!   p  $end
$var wire      1 *!   od  $end
$var wire      1 +!   s  $end
$var wire      1 ,!   r  $end

$scope module sr1 $end
$var wire      1 ,!   R  $end
$var wire      1 +!   S  $end
$var wire      1 $!   Q  $end
$var wire      1 (!   Qbar  $end
$upscope $end

$upscope $end


$scope module sr2 $end
$var wire      1 $!   d  $end
$var wire      1 ,    e  $end
$var wire      1 %    q  $end
$var wire      1 )!   p  $end
$var wire      1 -!   od  $end
$var wire      1 .!   s  $end
$var wire      1 /!   r  $end

$scope module sr1 $end
$var wire      1 /!   R  $end
$var wire      1 .!   S  $end
$var wire      1 %    Q  $end
$var wire      1 )!   Qbar  $end
$upscope $end

$upscope $end

$upscope $end

$upscope $end


$scope module e1 $end
$var wire      1 %    a [4] $end
$var wire      1 &    a [3] $end
$var wire      1 '    a [2] $end
$var wire      1 (    a [1] $end
$var wire      1 )    a [0] $end
$var wire      1 0!   b [4] $end
$var wire      1 1!   b [3] $end
$var wire      1 2!   b [2] $end
$var wire      1 3!   b [1] $end
$var wire      1 4!   b [0] $end
$var wire      1 5    s  $end
$var wire      1 5!   c [4] $end
$var wire      1 6!   c [3] $end
$var wire      1 7!   c [2] $end
$var wire      1 8!   c [1] $end
$var wire      1 9!   c [0] $end
$var wire      1 :!   d [2] $end
$var wire      1 ;!   d [1] $end
$var wire      1 <!   d [0] $end
$upscope $end


$scope module s1 $end
$var wire      1 %    inp [4] $end
$var wire      1 &    inp [3] $end
$var wire      1 '    inp [2] $end
$var wire      1 (    inp [1] $end
$var wire      1 )    inp [0] $end
$var wire      1 .    s  $end
$var wire      1 6    a [4] $end
$var wire      1 7    a [3] $end
$var wire      1 8    a [2] $end
$var wire      1 9    a [1] $end
$var wire      1 :    a [0] $end
$var wire      1 ;    c  $end
$var wire      1 =!   tmp [3] $end
$var wire      1 >!   tmp [2] $end
$var wire      1 ?!   tmp [1] $end
$var wire      1 @!   tmp [0] $end

$scope module sb1 $end
$var wire      1 )    targ  $end
$var wire      1 .    sub  $end
$var wire      1 :    out  $end
$var wire      1 @!   bor  $end
$upscope $end


$scope module sb2 $end
$var wire      1 (    targ  $end
$var wire      1 @!   sub  $end
$var wire      1 9    out  $end
$var wire      1 ?!   bor  $end
$upscope $end


$scope module sb3 $end
$var wire      1 '    targ  $end
$var wire      1 ?!   sub  $end
$var wire      1 8    out  $end
$var wire      1 >!   bor  $end
$upscope $end


$scope module sb4 $end
$var wire      1 &    targ  $end
$var wire      1 >!   sub  $end
$var wire      1 7    out  $end
$var wire      1 =!   bor  $end
$upscope $end


$scope module sb5 $end
$var wire      1 %    targ  $end
$var wire      1 =!   sub  $end
$var wire      1 6    out  $end
$var wire      1 ;    bor  $end
$upscope $end

$upscope $end


$scope module m1 $end
$var wire      1 6    Din1 [4] $end
$var wire      1 7    Din1 [3] $end
$var wire      1 8    Din1 [2] $end
$var wire      1 9    Din1 [1] $end
$var wire      1 :    Din1 [0] $end
$var wire      1 A!   Din2 [4] $end
$var wire      1 B!   Din2 [3] $end
$var wire      1 C!   Din2 [2] $end
$var wire      1 D!   Din2 [1] $end
$var wire      1 E!   Din2 [0] $end
$var wire      1 5    Sel  $end
$var wire      1 <    Dout [4] $end
$var wire      1 =    Dout [3] $end
$var wire      1 >    Dout [2] $end
$var wire      1 ?    Dout [1] $end
$var wire      1 @    Dout [0] $end
$var wire      1 F!   Sel_  $end
$var wire      1 G!   w1 [4] $end
$var wire      1 H!   w1 [3] $end
$var wire      1 I!   w1 [2] $end
$var wire      1 J!   w1 [1] $end
$var wire      1 K!   w1 [0] $end
$var wire      1 L!   w2 [4] $end
$var wire      1 M!   w2 [3] $end
$var wire      1 N!   w2 [2] $end
$var wire      1 O!   w2 [1] $end
$var wire      1 P!   w2 [0] $end
$upscope $end


$scope module e2 $end
$var wire      1 %    a [4] $end
$var wire      1 &    a [3] $end
$var wire      1 '    a [2] $end
$var wire      1 (    a [1] $end
$var wire      1 )    a [0] $end
$var wire      1 Q!   b [4] $end
$var wire      1 R!   b [3] $end
$var wire      1 S!   b [2] $end
$var wire      1 T!   b [1] $end
$var wire      1 U!   b [0] $end
$var wire      1 A    s  $end
$var wire      1 V!   c [4] $end
$var wire      1 W!   c [3] $end
$var wire      1 X!   c [2] $end
$var wire      1 Y!   c [1] $end
$var wire      1 Z!   c [0] $end
$var wire      1 [!   d [2] $end
$var wire      1 \!   d [1] $end
$var wire      1 ]!   d [0] $end
$upscope $end


$scope module h5 $end
$var wire      1 %    a [4] $end
$var wire      1 &    a [3] $end
$var wire      1 '    a [2] $end
$var wire      1 (    a [1] $end
$var wire      1 )    a [0] $end
$var wire      1 .    b  $end
$var wire      1 B    s [4] $end
$var wire      1 C    s [3] $end
$var wire      1 D    s [2] $end
$var wire      1 E    s [1] $end
$var wire      1 F    s [0] $end
$var wire      1 G    c  $end
$var wire      1 ^!   o [3] $end
$var wire      1 _!   o [2] $end
$var wire      1 `!   o [1] $end
$var wire      1 a!   o [0] $end

$scope module ha1 $end
$var wire      1 )    a  $end
$var wire      1 .    b  $end
$var wire      1 F    s  $end
$var wire      1 a!   o  $end
$upscope $end


$scope module ha2 $end
$var wire      1 (    a  $end
$var wire      1 a!   b  $end
$var wire      1 E    s  $end
$var wire      1 `!   o  $end
$upscope $end


$scope module ha3 $end
$var wire      1 '    a  $end
$var wire      1 `!   b  $end
$var wire      1 D    s  $end
$var wire      1 _!   o  $end
$upscope $end


$scope module ha4 $end
$var wire      1 &    a  $end
$var wire      1 _!   b  $end
$var wire      1 C    s  $end
$var wire      1 ^!   o  $end
$upscope $end


$scope module ha5 $end
$var wire      1 %    a  $end
$var wire      1 ^!   b  $end
$var wire      1 B    s  $end
$var wire      1 G    o  $end
$upscope $end

$upscope $end


$scope module m2 $end
$var wire      1 <    Din1 [4] $end
$var wire      1 =    Din1 [3] $end
$var wire      1 >    Din1 [2] $end
$var wire      1 ?    Din1 [1] $end
$var wire      1 @    Din1 [0] $end
$var wire      1 B    Din2 [4] $end
$var wire      1 C    Din2 [3] $end
$var wire      1 D    Din2 [2] $end
$var wire      1 E    Din2 [1] $end
$var wire      1 F    Din2 [0] $end
$var wire      1 A    Sel  $end
$var wire      1 H    Dout [4] $end
$var wire      1 I    Dout [3] $end
$var wire      1 J    Dout [2] $end
$var wire      1 K    Dout [1] $end
$var wire      1 L    Dout [0] $end
$var wire      1 b!   Sel_  $end
$var wire      1 c!   w1 [4] $end
$var wire      1 d!   w1 [3] $end
$var wire      1 e!   w1 [2] $end
$var wire      1 f!   w1 [1] $end
$var wire      1 g!   w1 [0] $end
$var wire      1 h!   w2 [4] $end
$var wire      1 i!   w2 [3] $end
$var wire      1 j!   w2 [2] $end
$var wire      1 k!   w2 [1] $end
$var wire      1 l!   w2 [0] $end
$upscope $end


$scope module m3 $end
$var wire      1 H    Din1 [4] $end
$var wire      1 I    Din1 [3] $end
$var wire      1 J    Din1 [2] $end
$var wire      1 K    Din1 [1] $end
$var wire      1 L    Din1 [0] $end
$var wire      1 %    Din2 [4] $end
$var wire      1 &    Din2 [3] $end
$var wire      1 '    Din2 [2] $end
$var wire      1 (    Din2 [1] $end
$var wire      1 )    Din2 [0] $end
$var wire      1 .    Sel  $end
$var wire      1 M    Dout [4] $end
$var wire      1 N    Dout [3] $end
$var wire      1 O    Dout [2] $end
$var wire      1 P    Dout [1] $end
$var wire      1 Q    Dout [0] $end
$var wire      1 m!   Sel_  $end
$var wire      1 n!   w1 [4] $end
$var wire      1 o!   w1 [3] $end
$var wire      1 p!   w1 [2] $end
$var wire      1 q!   w1 [1] $end
$var wire      1 r!   w1 [0] $end
$var wire      1 s!   w2 [4] $end
$var wire      1 t!   w2 [3] $end
$var wire      1 u!   w2 [2] $end
$var wire      1 v!   w2 [1] $end
$var wire      1 w!   w2 [0] $end
$upscope $end


$scope module m4 $end
$var wire      1 x!   Din1 [4] $end
$var wire      1 y!   Din1 [3] $end
$var wire      1 z!   Din1 [2] $end
$var wire      1 {!   Din1 [1] $end
$var wire      1 |!   Din1 [0] $end
$var wire      1 M    Din2 [4] $end
$var wire      1 N    Din2 [3] $end
$var wire      1 O    Din2 [2] $end
$var wire      1 P    Din2 [1] $end
$var wire      1 Q    Din2 [0] $end
$var wire      1 /    Sel  $end
$var wire      1 0    Dout [4] $end
$var wire      1 1    Dout [3] $end
$var wire      1 2    Dout [2] $end
$var wire      1 3    Dout [1] $end
$var wire      1 4    Dout [0] $end
$var wire      1 }!   Sel_  $end
$var wire      1 ~!   w1 [4] $end
$var wire      1 !"   w1 [3] $end
$var wire      1 ""   w1 [2] $end
$var wire      1 #"   w1 [1] $end
$var wire      1 $"   w1 [0] $end
$var wire      1 %"   w2 [4] $end
$var wire      1 &"   w2 [3] $end
$var wire      1 '"   w2 [2] $end
$var wire      1 ("   w2 [1] $end
$var wire      1 )"   w2 [0] $end
$upscope $end

$upscope $end

$upscope $end

$enddefinitions $end
$dumpvars
0!
0"
1#
0$
x%
x&
x'
x(
x)
bx *
bx +
0,
0-
1.
0/
x0
x1
x2
x3
x4
x5
x6
x7
x8
x9
x:
x;
x<
x=
x>
x?
x@
xA
xB
xC
xD
xE
xF
xG
xH
xI
xJ
xK
xL
xM
xN
xO
xP
xQ
xR
1S
zT
zU
xV
xW
xX
xY
xZ
x[
0\
0]
x^
1_
z`
za
xb
xc
xd
xe
xf
xg
0h
0i
xj
1k
zl
zm
xn
xo
xp
xq
xr
xs
0t
0u
xv
1w
zx
zy
xz
x{
x|
x}
x~
x!!
0"!
0#!
x$!
1%!
z&!
z'!
x(!
x)!
x*!
x+!
x,!
x-!
0.!
0/!
00!
01!
02!
03!
04!
x5!
x6!
x7!
x8!
x9!
x:!
x;!
x<!
x=!
x>!
x?!
x@!
0A!
0B!
0C!
0D!
0E!
xF!
xG!
xH!
xI!
xJ!
xK!
0L!
0M!
0N!
0O!
0P!
1Q!
0R!
1S!
0T!
0U!
xV!
xW!
xX!
xY!
xZ!
x[!
x\!
x]!
x^!
x_!
x`!
xa!
xb!
xc!
xd!
xe!
xf!
xg!
xh!
xi!
xj!
xk!
xl!
0m!
xn!
xo!
xp!
xq!
xr!
0s!
0t!
0u!
0v!
0w!
0x!
0y!
0z!
0{!
0|!
1}!
0~!
0!"
0""
0#"
0$"
x%"
x&"
x'"
x("
x)"
$end
#5000
1$
1/
0%"
0&"
0'"
0("
0}!
0)"
04
03
02
01
00
0+!
1*!
1,!
0}
1|
1~
0q
1p
1r
0e
1d
1f
0Y
1X
1Z
0R
0^
0j
0v
0$!
1(!
1-!
1z
1!!
1n
1s
1b
1g
1V
1[
#10000
1"
1,
0S
0_
0k
0w
0%!
1/!
1#!
1u
1i
1]
0)
0(
0'
0&
0%
0,!
0~
0r
0f
0Z
1V!
05!
1)!
0G
0W!
06!
1{
0^!
1X!
07!
1o
0_!
0Y!
08!
1c
0`!
0Z!
1:
1F
09!
1W
0a!
0E
0<!
1@!
0]!
0D
0C
1\!
0B
1A
0b!
0l!
0h!
1[!
0i!
0j!
19
0;!
0k!
0:!
1?!
18
05
0G!
0H!
0I!
0J!
0K!
1F!
1>!
17
0@
0?
0>
0=
0<
0c!
0d!
0e!
0f!
0g!
1=!
16
0L
0K
0J
0I
0H
0n!
0o!
0p!
0q!
0r!
1;
0Q
0P
0O
0N
0M
#15000
0$
b0 +
b0 *
0/
1}!
#20000
0"
0,
1S
1_
1k
1w
1%!
0/!
0#!
0u
0i
0]
1,!
1~
1r
1f
1Z
#25000
0#
b1 *
0.
0:
0F
0@!
1m!
09
0?!
08
0>!
07
0=!
06
0;
#30000
1"
1,
0S
0_
0k
0w
0%!
1/!
1#!
1u
1i
1]
0,!
0~
0r
0f
0Z
#35000
1#
b10 *
1.
1:
1F
0m!
1@!
19
1?!
18
1>!
17
1=!
16
1;
#40000
0"
0,
1S
1_
1k
1w
1%!
0/!
0#!
0u
0i
0]
1,!
1~
1r
1f
1Z
#45000
0#
b11 *
0.
0:
0F
0@!
1m!
09
0?!
08
0>!
07
0=!
06
0;
#50000
1"
1,
0S
0_
0k
0w
0%!
1/!
1#!
1u
1i
1]
0,!
0~
0r
0f
0Z
#55000
1#
b100 *
1.
1:
1F
0m!
1@!
19
1?!
18
1>!
17
1=!
16
1;
#60000
0"
0,
1S
1_
1k
1w
1%!
0/!
0#!
0u
0i
0]
1,!
1~
1r
1f
1Z
#65000
0#
b101 *
0.
0:
0F
0@!
1m!
09
0?!
08
0>!
07
0=!
06
0;
#70000
1"
1,
0S
0_
0k
0w
0%!
1/!
1#!
1u
1i
1]
0,!
0~
0r
0f
0Z
#75000
1#
b110 *
1.
1:
1F
0m!
1@!
19
1?!
18
1>!
17
1=!
16
1;
#80000
0"
0,
1S
1_
1k
1w
1%!
0/!
0#!
0u
0i
0]
1,!
1~
1r
1f
1Z
#85000
0#
b111 *
0.
0:
0F
0@!
1m!
09
0?!
08
0>!
07
0=!
06
0;
#90000
1"
1,
0S
0_
0k
0w
0%!
1/!
1#!
1u
1i
1]
0,!
0~
0r
0f
0Z
#95000
1#
b1000 *
1.
1:
1F
0m!
1@!
19
1?!
18
1>!
17
1=!
16
1;
#100000
0"
0,
1S
1_
1k
1w
1%!
0/!
0#!
0u
0i
0]
1,!
1~
1r
1f
1Z
#105000
0#
b1001 *
0.
0:
0F
0@!
1m!
09
0?!
08
0>!
07
0=!
06
0;
#110000
1"
1,
0S
0_
0k
0w
0%!
1/!
1#!
1u
1i
1]
0,!
0~
0r
0f
0Z
#115000
1#
b1010 *
1.
1:
1F
0m!
1@!
19
1?!
18
1>!
17
1=!
16
1;
#120000
0"
0,
1S
1_
1k
1w
1%!
0/!
0#!
0u
0i
0]
1,!
1~
1r
1f
1Z
#125000
0#
b1011 *
0.
0:
0F
0@!
1m!
09
0?!
08
0>!
07
0=!
06
0;
#130000
1"
1,
0S
0_
0k
0w
0%!
1/!
1#!
1u
1i
1]
0,!
0~
0r
0f
0Z
#135000
1#
b1100 *
1.
1:
1F
0m!
1@!
19
1?!
18
1>!
17
1=!
16
1;
#140000
0"
0,
1S
1_
1k
1w
1%!
0/!
0#!
0u
0i
0]
1,!
1~
1r
1f
1Z
#145000
0#
b1101 *
0.
0:
0F
0@!
1m!
09
0?!
08
0>!
07
0=!
06
0;
#150000
1"
1,
0S
0_
0k
0w
0%!
1/!
1#!
1u
1i
1]
0,!
0~
0r
0f
0Z
#155000
1#
b1110 *
1.
1:
1F
0m!
1@!
19
1?!
18
1>!
17
1=!
16
1;
#160000
0"
0,
1S
1_
1k
1w
1%!
0/!
0#!
0u
0i
0]
1,!
1~
1r
1f
1Z
#165000
0#
b1111 *
0.
0:
0F
0@!
1m!
09
0?!
08
0>!
07
0=!
06
0;
#170000
1"
1,
0S
0_
0k
0w
0%!
1/!
1#!
1u
1i
1]
0,!
0~
0r
0f
0Z
#175000
1#
b10000 *
1.
1:
1F
0m!
1@!
19
1?!
18
1>!
17
1=!
16
1;
#180000
0"
0,
1S
1_
1k
1w
1%!
0/!
0#!
0u
0i
0]
1,!
1~
1r
1f
1Z
#185000
0#
b10001 *
0.
0:
0F
0@!
1m!
09
0?!
08
0>!
07
0=!
06
0;
#190000
1"
1,
0S
0_
0k
0w
0%!
1/!
1#!
1u
1i
1]
0,!
0~
0r
0f
0Z
#195000
1#
b10010 *
1.
1:
1F
0m!
1@!
19
1?!
18
1>!
17
1=!
16
1;
#200000
0"
0,
1S
1_
1k
1w
1%!
0/!
0#!
0u
0i
0]
1,!
1~
1r
1f
1Z
#205000
0#
b10011 *
0.
0:
0F
0@!
1m!
09
0?!
08
0>!
07
0=!
06
0;
#210000
1"
1,
0S
0_
0k
0w
0%!
1/!
1#!
1u
1i
1]
0,!
0~
0r
0f
0Z
#215000
1#
b10100 *
1.
1:
1F
0m!
1@!
19
1?!
18
1>!
17
1=!
16
1;
#220000
0"
0,
1S
1_
1k
1w
1%!
0/!
0#!
0u
0i
0]
1,!
1~
1r
1f
1Z
#225000
0#
b10101 *
0.
0:
0F
0@!
1m!
09
0?!
08
0>!
07
0=!
06
0;
#230000
1"
1,
0S
0_
0k
0w
0%!
1/!
1#!
1u
1i
1]
0,!
0~
0r
0f
0Z
#235000
1#
b10110 *
1.
1:
1F
0m!
1@!
19
1?!
18
1>!
17
1=!
16
1;
