before_mounth10/hw1and2/synchronous_ctr/structural/subtractor_borrow.v
module subtractor_borrow(input targ,input sub,output out,output bor);
xor(out,targ,sub);
and (bor,sub,out);
endmodule

synchronous_ctr/structural/sub_bor5.v
module sub_bor5(input [4:0] inp,input s/*for subtractor*/,output [4:0] a/*for ans*/,output c/*borrow*/);
wire [3:0] tmp;
subtractor_borrow sb1(inp[0],s,a[0],tmp[0]);
subtractor_borrow sb2(inp[1],tmp[0],a[1],tmp[1]);
subtractor_borrow sb3(inp[2],tmp[1],a[2],tmp[2]);
subtractor_borrow sb4(inp[3],tmp[2],a[3],tmp[3]);
subtractor_borrow sb5(inp[4],tmp[3],a[4],c);
endmodule

hw1and2/synchronous_ctr/structural/Tsb5.v
`timescale 1ns/1ps
`include "sub_bor5.v"
module Tsb5;

reg [4:0] inp;
reg s;
wire [4:0] a;
wire c;

sub_bor5 sb51(inp,s,a,c);

initial begin
inp = 5'd0;
s = 1'b0;
end

initial begin
$monitor("Time= %d | inp= %d | oup= %d",$time,inp,a);
end

always #10 begin
inp=inp+5'd1;
end

initial begin
#204 s=1;
#406 $finish;
end

initial begin
$dumpfile("scb.vcd");
$dumpvars;
end

endmodule

synchronous_ctr/structural/scb.vcd
$date
    Oct 16, 2019  00:18:06
$end
$version
    TOOL:	ncsim	15.20-s039
$end
$timescale
    1 ps
$end

$scope module Tsb5 $end
$var reg       5 !    inp [4:0] $end
$var reg       1 "    s  $end
$var wire      1 #    a [4] $end
$var wire      1 $    a [3] $end
$var wire      1 %    a [2] $end
$var wire      1 &    a [1] $end
$var wire      1 '    a [0] $end
$var wire      1 (    c  $end

$scope module sb51 $end
$var wire      1 )    inp [4] $end
$var wire      1 *    inp [3] $end
$var wire      1 +    inp [2] $end
$var wire      1 ,    inp [1] $end
$var wire      1 -    inp [0] $end
$var wire      1 .    s  $end
$var wire      1 #    a [4] $end
$var wire      1 $    a [3] $end
$var wire      1 %    a [2] $end
$var wire      1 &    a [1] $end
$var wire      1 '    a [0] $end
$var wire      1 (    c  $end
$var wire      1 /    tmp [3] $end
$var wire      1 0    tmp [2] $end
$var wire      1 1    tmp [1] $end
$var wire      1 2    tmp [0] $end

$scope module sb1 $end
$var wire      1 -    targ  $end
$var wire      1 .    sub  $end
$var wire      1 '    out  $end
$var wire      1 2    bor  $end
$upscope $end


$scope module sb2 $end
$var wire      1 ,    targ  $end
$var wire      1 2    sub  $end
$var wire      1 &    out  $end
$var wire      1 1    bor  $end
$upscope $end


$scope module sb3 $end
$var wire      1 +    targ  $end
$var wire      1 1    sub  $end
$var wire      1 %    out  $end
$var wire      1 0    bor  $end
$upscope $end


$scope module sb4 $end
$var wire      1 *    targ  $end
$var wire      1 0    sub  $end
$var wire      1 $    out  $end
$var wire      1 /    bor  $end
$upscope $end


$scope module sb5 $end
$var wire      1 )    targ  $end
$var wire      1 /    sub  $end
$var wire      1 #    out  $end
$var wire      1 (    bor  $end
$upscope $end

$upscope $end

$upscope $end

$enddefinitions $end
$dumpvars
b0 !
0"
0#
0$
0%
0&
0'
0(
0)
0*
0+
0,
0-
0.
0/
00
01
02
$end
#10000
b1 !
1-
1'
#20000
b10 !
1,
0-
0'
1&
#30000
b11 !
1-
1'
#40000
b100 !
1+
0,
0-
0'
0&
1%
#50000
b101 !
1-
1'
#60000
b110 !
1,
0-
0'
1&
#70000
b111 !
1-
1'
#80000
b1000 !
1*
0+
0,
0-
0'
0&
0%
1$
#90000
b1001 !
1-
1'
#100000
b1010 !
1,
0-
0'
1&
#110000
b1011 !
1-
1'
#120000
b1100 !
1+
0,
0-
0'
0&
1%
#130000
b1101 !
1-
1'
#140000
b1110 !
1,
0-
0'
1&
#150000
b1111 !
1-
1'
#160000
b10000 !
1)
0*
0+
0,
0-
0'
0&
0%
0$
1#
#170000
b10001 !
1-
1'
#180000
b10010 !
1,
0-
0'
1&
#190000
b10011 !
1-
1'
#200000
b10100 !
1+
0,
0-
0'
0&
1%
#204000
1"
1.
1'
12
1&
11
0%
#210000
b10101 !
1-
0'
02
0&
01
1%
#220000
b10110 !
1,
0-
1'
0&
12
#230000
b10111 !
1-
0'
02
1&
#240000
b11000 !
1*
0+
0,
0-
1'
1&
1%
0$
12
11
10
#250000
b11001 !
1-
0'
02
0&
01
0%
00
1$
#260000
b11010 !
1,
0-
1'
0&
12
#270000
b11011 !
1-
0'
02
1&
#280000
b11100 !
1+
0,
0-
1'
1&
0%
12
11
#290000
b11101 !
1-
0'
02
0&
01
1%
#300000
b11110 !
1,
0-
1'
0&
12
#310000
b11111 !
1-
0'
02
1&
#320000
b0 !
0)
0*
0+
0,
0-
1'
1&
1%
1$
1#
12
11
10
1/
1(
#330000
b1 !
1-
0'
02
0&
01
0%
00
0$
0/
0#
0(
#340000
b10 !
1,
0-
1'
0&
12
#350000
b11 !
1-
0'
02
1&
#360000
b100 !
1+
0,
0-
1'
1&
0%
12
11
#370000
b101 !
1-
0'
02
0&
01
1%
#380000
b110 !
1,
0-
1'
0&
12
#390000
b111 !
1-
0'
02
1&
#400000
b1000 !
1*
0+
0,
0-
1'
1&
1%
0$
12
11
10
#410000
b1001 !
1-
0'
02
0&
01
0%
00
1$
#420000
b1010 !
1,
0-
1'
0&
12
#430000
b1011 !
1-
0'
02
1&
#440000
b1100 !
1+
0,
0-
1'
1&
0%
12
11
#450000
b1101 !
1-
0'
02
0&
01
1%
#460000
b1110 !
1,
0-
1'
0&
12
#470000
b1111 !
1-
0'
02
1&
#480000
b10000 !
1)
0*
0+
0,
0-
1'
1&
1%
1$
0#
12
11
10
1/
#490000
b10001 !
1-
0'
02
0&
01
0%
00
0$
0/
1#
#500000
b10010 !
1,
0-
1'
0&
12
#510000
b10011 !
1-
0'
02
1&
#520000
b10100 !
1+
0,
0-
1'
1&
0%
12
11
#530000
b10101 !
1-
0'
02
0&
01
1%
#540000
b10110 !
1,
0-
1'
0&
12
#550000
b10111 !
1-
0'
02
1&
#560000
b11000 !
1*
0+
0,
0-
1'
1&
1%
0$
12
11
10
#570000
b11001 !
1-
0'
02
0&
01
0%
00
1$
#580000
b11010 !
1,
0-
1'
0&
12
#590000
b11011 !
1-
0'
02
1&
#600000
b11100 !
1+
0,
0-
1'
1&
0%
12
11
