synchronous_ctr/structural/SR_latch_gate.v
module SR_latch_gate (input R, input S, output Q,output Qbar);
nor (Q , R,Qbar);
nor(Qbar,S,Q);
endmodule

hw1and2/synchronous_ctr/structural/enable_sr.v
module enable_sr(
input d,/*data*/
input e,/*enable*/
output q,
output p/*q bar*/);

//=======================
//use "nor" to do latch
//the thing that lay out with q is r
//and p is with s
//=======================


wire od,s,r;

not(od,d);
and(r,od,e);
and(s,e,d);
SR_latch_gate sr1(r,s,q,p);

endmodule

hw1and2/synchronous_ctr/structural/Tes.v
`timescale 1ns/1ps
`include "enable_sr.v"
`include "SR_latch_gate.v"
module Tes;

reg d,e;
wire q,p;

enable_sr es1(d,e,q,p);

initial begin
d=1'b0;
e=1'b0;
#10 d=1'b1;
#10 d=1'b0;
#10 e=1'b1;
#10 d=1'b1;
#10 e=1'b0;
#10 d=1'b0;
#10 e=1'b1;
#10 d=1'b1;
#10 $finish;
end

initial begin
$monitor("Time= %d | d= %b | e= %b | q= %b | p= %b",$time,d,e,q,p);
end

initial begin
$dumpfile("Tes.vcd");
$dumpvars;
end

endmodule

synchronous_ctr/structural/Tes.vcd
$date
    Oct 16, 2019  02:42:31
$end
$version
    TOOL:	ncsim	15.20-s039
$end
$timescale
    1 ps
$end

$scope module Tes $end
$var reg       1 !    d  $end
$var reg       1 "    e  $end
$var wire      1 #    q  $end
$var wire      1 $    p  $end

$scope module es1 $end
$var wire      1 %    d  $end
$var wire      1 &    e  $end
$var wire      1 #    q  $end
$var wire      1 $    p  $end
$var wire      1 '    od  $end
$var wire      1 (    s  $end
$var wire      1 )    r  $end

$scope module sr1 $end
$var wire      1 )    R  $end
$var wire      1 (    S  $end
$var wire      1 #    Q  $end
$var wire      1 $    Qbar  $end
$upscope $end

$upscope $end

$upscope $end

$enddefinitions $end
$dumpvars
0!
0"
x#
x$
0%
0&
1'
0(
0)
$end
#10000
1!
1%
0'
#20000
0!
0%
1'
#30000
1"
1&
1)
0#
1$
#40000
1!
1%
1(
0'
0)
0$
1#
#50000
0"
0&
0(
#60000
0!
0%
1'
#70000
1"
1&
1)
0#
1$
#80000
1!
1%
1(
0'
0)
0$
1#
