synchronous_ctr/structural/dff_R_asyn.v
module dff_R_asyn(input d,input clk,input clear,output q);
wire pc,ao,an;
rising_edge_trigger_ff retf(d,clk,pc);
or(ao,pc,clear);
not(an,clear);
and(q,an,ao);
endmodule

synchronous_ctr/structural/SR_latch_gate.v
module SR_latch_gate (input R, input S, output Q,output Qbar);
nor (Q , R,Qbar);
nor(Qbar,S,Q);
endmodule

hw1and2/synchronous_ctr/structural/enable_sr.v
module enable_sr(
input d,/*data*/
input e,/*enable*/
output q,
output p/*q bar*/);

//=======================
//use "nor" to do latch
//the thing that lay out with q is r
//and p is with s
//=======================


wire od,s,r;

not(od,d);
and(r,od,e);
and(s,e,d);
SR_latch_gate sr1(r,s,q,p);

endmodule

before_mounth10/hw1and2/synchronous_ctr/structural/rising_edge_trigger_ff.v
module rising_edge_trigger_ff(input d,input clk ,output q);
wire p,n,un,uc;
not(n,clk);
enable_sr sr1(d,n,p,nu);
enable_sr sr2(p,clk,q,nc);
endmodule

synchronous_ctr/structural/Tretf.v
`timescale 1ns/1ps
`include "SR_latch_gate.v"
`include "enable_sr.v"
`include "rising_edge_trigger_ff.v"
//`include "dff_R_asyn.v"
module Tretf;

reg d,clk;
wire q;

rising_edge_trigger_ff retf1(d,clk,q);

always #10 begin
clk=~clk;
end

initial begin
clk=0;
d=1'b0;
//clear=1'b0;
#15 d=1'b1;
#16 d=1'b0;
#20 d=1'b1;
#3 d=1'b0;
//#10 clear=1'b1;
//#10 clear=1'b0;
#10 $finish;
end

initial begin
$monitor("Time= %d | d= %b | q= %b",$time,d,q);
end

initial begin
$dumpfile("Tretf.vcd");
$dumpvars;
end

endmodule

synchronous_ctr/structural/Tretf.vcd
$date
    Oct 16, 2019  03:58:32
$end
$version
    TOOL:	ncsim	15.20-s039
$end
$timescale
    1 ps
$end

$scope module Tretf $end
$var reg       1 !    d  $end
$var reg       1 "    clk  $end
$var wire      1 #    q  $end

$scope module retf1 $end
$var wire      1 $    d  $end
$var wire      1 %    clk  $end
$var wire      1 #    q  $end
$var wire      1 &    p  $end
$var wire      1 '    n  $end
$var wire      1 (    un  $end
$var wire      1 )    uc  $end
$var wire      1 *    nu  $end
$var wire      1 +    nc  $end

$scope module sr1 $end
$var wire      1 $    d  $end
$var wire      1 '    e  $end
$var wire      1 &    q  $end
$var wire      1 *    p  $end
$var wire      1 ,    od  $end
$var wire      1 -    s  $end
$var wire      1 .    r  $end

$scope module sr1 $end
$var wire      1 .    R  $end
$var wire      1 -    S  $end
$var wire      1 &    Q  $end
$var wire      1 *    Qbar  $end
$upscope $end

$upscope $end


$scope module sr2 $end
$var wire      1 &    d  $end
$var wire      1 %    e  $end
$var wire      1 #    q  $end
$var wire      1 +    p  $end
$var wire      1 /    od  $end
$var wire      1 0    s  $end
$var wire      1 1    r  $end

$scope module sr1 $end
$var wire      1 1    R  $end
$var wire      1 0    S  $end
$var wire      1 #    Q  $end
$var wire      1 +    Qbar  $end
$upscope $end

$upscope $end

$upscope $end

$upscope $end

$enddefinitions $end
$dumpvars
0!
0"
x#
0$
0%
0&
1'
z(
z)
1*
x+
1,
0-
1.
1/
00
01
$end
#10000
1"
1%
0'
11
0#
0.
1+
#15000
1!
1$
0,
#20000
0"
0%
1'
01
1-
0*
1&
0/
#30000
1"
1%
0'
10
0+
0-
1#
#31000
0!
0$
1,
#40000
0"
0%
1'
00
1.
0&
1*
1/
#50000
1"
1%
0'
11
0#
0.
1+
#51000
1!
1$
0,
#54000
0!
0$
1,
#60000
0"
0%
1'
01
1.
