Behavior/adder_b.v
module adder_16bit_b(A , B ,Add_ctrl , O , C_out , SUM);

input [15:0] A , B ;
input Add_ctrl;//1 for sub ,0 for add

output [15:00] SUM ;
output C_out ;
output O ;
reg aC_out;
reg aO;
reg [15:0] aSUM;
assign e=A[15];
assign r=B[15];
assign O=aO;
assign C_out=aC_out;
assign SUM=aSUM;

/** your code **/

always@(A or B or Add_ctrl)
begin

{aC_out,aSUM}=(Add_ctrl==0)?(A+B):(A-B);
//{aC_out,aSUM}=(((Add_ctrl==1)?~B:B)+Add_ctrl)+A;
end

reg pn;
always@(A or B or Add_ctrl)
begin
pn=(Add_ctrl==1)?(((e==0)&&(r==1))||((e==1)&&(r==0)))?1:0:(((e==0)&&(r==0))||((e==1)&&(r==1)))?1:0;
aO=(pn==1)?(C_out==SUM[15])?0:1:0;
end  

endmodule

Behavior/testbench.v
`timescale 1ns/10ps

`include        "adder_b.v"

module tb_adder ;
reg [15:0] A , B ;
reg Add_ctrl ;

wire [15:0] SUM;
wire C_out ;
wire O ;


reg [15:0] mem_A [9999:0] ;
reg [15:0] mem_B [9999:0] ;
reg mem_add_ctrl [9999:0] ;
reg [17:0] expect [9999:0] ;

reg    [16:0] error = 0;
integer i ;

initial 
begin
	$readmemh("A.txt", mem_A);
	$readmemh("B.txt", mem_B);
	$readmemh("Add_ctrl.txt", mem_add_ctrl);
	$readmemh("Result.txt", expect);
end


adder_16bit_b u_adder(        .A            (A        ),
                .B            (B        ),
                .Add_ctrl     (Add_ctrl ),
                .O            (O        ),
                .C_out        (C_out    ),
                .SUM          (SUM      )
);

initial 
begin

	for (i =0 ; i <= 9999; i = i + 1 )          
  begin
    A = mem_A[i] ;
	B = mem_B[i] ;
	Add_ctrl = mem_add_ctrl[i] ;
    
    #10;
    if (SUM !== expect[i][15:0])
        begin
           $display ("ERROR at time=%d(pattern%d): SUM(%h)!= expect(%h)",
                      $time, i+1, SUM, expect[i][15:0]);
           error = error + 1;
	end
		
    if (C_out !== expect[i][16])
	begin
           $display ("ERROR at time=%d(pattern%d): C_out(%b)!= expect(%b)", 
                      $time,  i+1, C_out, expect[i][16]);
           error = error + 1;
	end

    if ( O !== expect[i][17])
	begin
           $display ("ERROR at time=%d(pattern%d): O(%b)!= expect(%b)",
                      $time, i+1, O , expect[i][17]);
	    error = error + 1;
	end
    end

     if(error == 17'b0)
     begin
      $display ("=============================================================");
      $display ("Congratulation!, Your design PASSed all the test patterns ");
	  $display ("^     ^");
	  $display (" +++++");
      $display ("=============================================================");
      end
      else
      begin
      $display ("=================================================");
      $display ("There're %d errors in your design", error); 
      $display ("=================================================");
      end

	$finish ;
end

initial
begin
	$dumpfile("addS16_new.vcd");
	$dumpvars;
end
	
endmodule

Behavior/addS16_new.vcd
$date
    Oct 14, 2019  23:23:13
$end
$version
    TOOL:	ncsim	15.20-s039
$end
$timescale
    10 ps
$end

$scope module tb_adder $end
$var reg      16 !    A [15:0] $end
$var reg      16 "    B [15:0] $end
$var reg       1 #    Add_ctrl  $end
$var wire     16 $    SUM [15:0] $end
$var wire      1 %    C_out  $end
$var wire      1 &    O  $end
$var reg      17 '    error [16:0] $end
$var integer  32 (    i  $end

$scope module u_adder $end
$var wire     16 )    A [15:0] $end
$var wire     16 *    B [15:0] $end
$var wire      1 +    Add_ctrl  $end
$var wire     16 $    SUM [15:0] $end
$var wire      1 %    C_out  $end
$var wire      1 &    O  $end
$var reg       1 ,    aC_out  $end
$var reg       1 -    aO  $end
$var reg      16 .    aSUM [15:0] $end
$var wire      1 /    e  $end
$var wire      1 0    r  $end
$var reg       1 1    pn  $end
$upscope $end

$upscope $end

$enddefinitions $end
$dumpvars
b1111101001011110 !
b1010000110001000 "
0#
b1001101111100110 $
1%
x&
b0 '
b0 (
b1111101001011110 )
b1010000110001000 *
0+
1,
x-
b1001101111100110 .
1/
10
x1
$end
#1000
b1 '
b1 (
b111000111010110 !
b110001011011100 "
1#
1+
b110001011011100 *
b111000111010110 )
01
0-
b111011111010 .
0,
0/
00
0%
b111011111010 $
0&
#2000
b10 '
b10 (
b110001011111101 !
b1001110010101000 "
0#
0+
b1001110010101000 *
b110001011111101 )
11
b1111111110100101 .
10
b1111111110100101 $
#3000
b11 (
b1111001111110011 !
b1001010100111100 "
b1001010100111100 *
b1111001111110011 )
01
b1000100100101111 .
1,
1/
1%
b1000100100101111 $
#4000
b100 (
b1001111111111110 !
b1101001101011011 "
1#
1+
b1101001101011011 *
b1001111111111110 )
b1100110010100011 .
b1100110010100011 $
#5000
b11 '
b101 (
b1001001101000100 !
b101111000011000 "
0#
0+
b101111000011000 *
b1001001101000100 )
11
b1111000101011100 .
0,
00
0%
b1111000101011100 $
#6000
b110 (
b11001010110 !
b11000101011 "
1#
1+
b11000101011 *
b11001010110 )
1-
b101011 .
0/
b101011 $
1&
#7000
b100 '
b101 '
b111 (
b11010000111 !
b110001101000000 "
b110001101000000 *
b11010000111 )
01
0-
b1010001101000111 .
1,
1%
b1010001101000111 $
0&
#8000
b110 '
b1000 (
b100011000010110 !
b101110100101110 "
b101110100101110 *
b100011000010110 )
b1110100011101000 .
b1110100011101000 $
#9000
b111 '
b1001 (
b1101011101010100 !
b10010011111101 "
0#
0+
b10010011111101 *
b1101011101010100 )
11
b1111110001010001 .
0,
1/
0%
b1111110001010001 $
#10000
b1010 (
b1101010111101001 !
b100100001101011 "
b100100001101011 *
b1101010111101001 )
01
b1111001010100 .
1,
1%
b1111001010100 $
#11000
b1011 (
b110001000011010 !
b1111001011010001 "
b1111001011010001 *
b110001000011010 )
b101010011101011 .
0/
10
b101010011101011 $
#12000
b1100 (
b11010011111 !
b1100110111101100 "
1#
1+
b1100110111101100 *
b11010011111 )
11
1-
b11100010110011 .
b11100010110011 $
1&
#13000
b1000 '
b1001 '
b1101 (
b1000100101000 !
b1100011111011011 "
b1100011111011011 *
b1000100101000 )
b100100101001101 .
b100100101001101 $
#14000
b1010 '
b1011 '
b1110 (
b101110111100101 !
b1110101110000 "
0#
0+
b1110101110000 *
b101110111100101 )
01
0-
b111101101010101 .
0,
00
0%
b111101101010101 $
0&
#15000
b1111 (
b10111000 !
b10100100100111 "
b10100100100111 *
b10111000 )
11
b10100111011111 .
b10100111011111 $
#16000
b10000 (
b100001111001011 !
b1010111100001110 "
b1010111100001110 *
b100001111001011 )
b1111001011011001 .
10
b1111001011011001 $
#17000
b10001 (
b100110111 !
b1011110111011010 "
1#
1+
b1011110111011010 *
b100110111 )
1-
b100001101011101 .
1,
1%
b100001101011101 $
1&
#18000
b1100 '
b1101 '
b10010 (
b1100111001010011 !
b110010101001011 "
0#
0+
b110010101001011 *
b1100111001010011 )
01
0-
b11001110011110 .
1/
00
b11001110011110 $
0&
#19000
b10011 (
b1010001010101001 !
b111010101111 "
1#
1+
b111010101111 *
b1010001010101001 )
11
1-
b1001001111111010 .
0,
0%
b1001001111111010 $
1&
#20000
b1110 '
b1111 '
b10100 (
b1011001010100011 !
b1010111100010101 "
0#
0+
b1010111100010101 *
b1011001010100011 )
01
0-
b110000110111000 .
1,
10
1%
b110000110111000 $
0&
#21000
b10000 '
b10101 (
b1010111100000101 !
b1111000011001000 "
1#
1+
b1111000011001000 *
b1010111100000101 )
b1011111000111101 .
b1011111000111101 $
#22000
b10001 '
b10110 (
b1010100111101100 !
b1111011111001011 "
0#
0+
b1111011111001011 *
b1010100111101100 )
11
b1010000110110111 .
b1010000110110111 $
#23000
b10111 (
b1111100111111101 !
b1100010011111101 "
1#
1+
b1100010011111101 *
b1111100111111101 )
01
b11010100000000 .
0,
0%
b11010100000000 $
#24000
b10010 '
b11000 (
b1000000000001111 !
b1010010100011011 "
b1010010100011011 *
b1000000000001111 )
b1101101011110100 .
1,
1%
b1101101011110100 $
#25000
b10011 '
b11001 (
b1111011110010011 !
b110000010011001 "
b110000010011001 *
b1111011110010011 )
b1001011011111010 .
0,
00
0%
b1001011011111010 $
#26000
b10100 '
b11010 (
b100100110110011 !
b1110010011011110 "
b1110010011011110 *
b100100110110011 )
11
1-
b110010011010101 .
1,
0/
10
1%
b110010011010101 $
1&
#27000
b10101 '
b10110 '
b11011 (
b111001110100010 !
b1000011111001111 "
b1000011111001111 *
b111001110100010 )
b1110101111010011 .
b1110101111010011 $
#28000
b10111 '
b11100 (
b10011111011100 !
b111001001111101 "
0#
0+
b111001001111101 *
b10011111011100 )
01
0-
b1001101001011001 .
0,
00
0%
b1001101001011001 $
0&
#29000
b11000 '
b11101 (
b101110001010000 !
b1000111000100 "
b1000111000100 *
b101110001010000 )
11
1-
b110111000010100 .
b110111000010100 $
1&
#30000
b11001 '
b11110 (
b111000011111000 !
b1000110000111110 "
1#
1+
b1000110000111110 *
b111000011111000 )
01
0-
b1110010010111010 .
1,
10
1%
b1110010010111010 $
0&
#31000
b11010 '
b11011 '
b11111 (
b1001001101101110 !
b111001000110111 "
0#
0+
b111001000110111 *
b1001001101101110 )
b10110100101 .
1/
00
b10110100101 $
#32000
b100000 (
b1111100010111110 !
b101001111001001 "
1#
1+
b101001111001001 *
b1111100010111110 )
11
1-
b1010010011110101 .
0,
0%
b1010010011110101 $
1&
#33000
b11100 '
b11101 '
b100001 (
b110000001000001 !
b1000010111001010 "
0#
0+
b1000010111001010 *
b110000001000001 )
01
0-
b1110011000001011 .
0/
10
b1110011000001011 $
0&
#34000
b100010 (
b111011100101000 !
b101101101100111 "
b101101101100111 *
b111011100101000 )
b1101001010001111 .
00
b1101001010001111 $
#35000
b11110 '
b100011 (
b11010001101000 !
b1100010010001001 "
b1100010010001001 *
b11010001101000 )
11
1-
b1111100011110001 .
10
b1111100011110001 $
1&
#36000
b11111 '
b100100 (
b1000101011111110 !
b1011010101010010 "
b1011010101010010 *
b1000101011111110 )
01
0-
b100000001010000 .
1,
1/
1%
b100000001010000 $
0&
#37000
b100000 '
b100101 (
b1100100100111111 !
b1101101110110110 "
1#
1+
b1101101110110110 *
b1100100100111111 )
b1110110110001001 .
b1110110110001001 $
#38000
b100001 '
b100110 (
b1100101110000000 !
b1101010011100011 "
0#
0+
b1101010011100011 *
b1100101110000000 )
11
b1010000001100011 .
b1010000001100011 $
#39000
b100111 (
b1001100011100001 !
b1001001111101001 "
b1001001111101001 *
b1001100011100001 )
b10110011001010 .
b10110011001010 $
#40000
b100010 '
b101000 (
b1110110010101101 !
b1101110011101011 "
b1101110011101011 *
b1110110010101101 )
1-
b1100100110011000 .
b1100100110011000 $
1&
#41000
b100011 '
b101001 (
b1011010011010001 !
b101111111111000 "
b101111111111000 *
b1011010011010001 )
0-
b1010011001001 .
00
b1010011001001 $
0&
#42000
b101010 (
b100101100111011 !
b1010111010001000 "
1#
1+
b1010111010001000 *
b100101100111011 )
1-
b1001110010110011 .
0/
10
b1001110010110011 $
1&
#43000
b100100 '
b101011 (
b1000010101101110 !
b111110000001001 "
b111110000001001 *
b1000010101101110 )
0-
b100101100101 .
0,
1/
00
0%
b100101100101 $
0&
#44000
b100101 '
b100110 '
b101100 (
b111101000101001 !
b100010111000 "
b100010111000 *
b111101000101001 )
b111000101110001 .
0/
b111000101110001 $
#45000
b100111 '
b101101 (
b110110101000000 !
b110101010110111 "
0#
0+
b110101010110111 *
b110110101000000 )
b1101011111110111 .
b1101011111110111 $
#46000
b101000 '
b101110 (
b100100011110011 !
b101100101101011 "
b101100101101011 *
b100100011110011 )
1-
b1010001001011110 .
b1010001001011110 $
1&
#47000
b101111 (
b1101010111101010 !
b1011001000110010 "
b1011001000110010 *
b1101010111101010 )
b1000100000011100 .
1,
1/
10
1%
b1000100000011100 $
#48000
b101001 '
b110000 (
b101000101010000 !
b1011010001101101 "
b1011010001101101 *
b101000101010000 )
0-
b10110111101 .
0/
b10110111101 $
0&
#49000
b110001 (
b1100110001111110 !
b110011011100110 "
b110011011100110 *
b1100110001111110 )
01
b11001101100100 .
1/
00
b11001101100100 $
#50000
b110010 (
b11110111111010 !
b11100000011 "
b11100000011 *
b11110111111010 )
b100010011111101 .
0,
0/
0%
b100010011111101 $
#51000
b110011 (
b1101000001011001 !
b11011001111010 "
b11011001111010 *
b1101000001011001 )
11
b11011010011 .
1,
1/
1%
b11011010011 $
#52000
b110100 (
b1010011100100111 !
b1110110111111101 "
1#
1+
b1110110111111101 *
b1010011100100111 )
1-
b1011100100101010 .
10
b1011100100101010 $
1&
#53000
b101010 '
b101011 '
b110101 (
b110011010011010 !
b101000000110101 "
b101000000110101 *
b110011010011010 )
01
0-
b1011001100101 .
0,
0/
00
0%
b1011001100101 $
0&
#54000
b101100 '
b110110 (
b1000000011000011 !
b1111101100101001 "
0#
0+
b1111101100101001 *
b1000000011000011 )
11
b111101111101100 .
1,
1/
10
1%
b111101111101100 $
#55000
b101101 '
b110111 (
b10000111001110 !
b1000001000001111 "
1#
1+
b1000001000001111 *
b10000111001110 )
01
b1001111110111111 .
0/
b1001111110111111 $
#56000
b101110 '
b101111 '
b111000 (
b11010101000000 !
b100110010000011 "
b100110010000011 *
b11010101000000 )
11
b1110100010111101 .
00
b1110100010111101 $
#57000
b110000 '
b111001 (
b1101000011111111 !
b1111110111010100 "
0#
0+
b1111110111010100 *
b1101000011111111 )
b1100111011010011 .
1/
10
b1100111011010011 $
#58000
b111010 (
b10000000000110 !
b1010001110111110 "
b1010001110111110 *
b10000000000110 )
b1100001111000100 .
0,
0/
0%
b1100001111000100 $
#59000
b111011 (
b1001101011010001 !
b101000000100101 "
1#
1+
b101000000100101 *
b1001101011010001 )
1-
b100101010101100 .
1/
00
b100101010101100 $
1&
#60000
b110001 '
b111100 (
b1010100100110001 !
b1100011101100101 "
b1100011101100101 *
b1010100100110001 )
0-
b1110000111001100 .
1,
10
1%
b1110000111001100 $
0&
#61000
b110010 '
b111101 (
b1001000001010100 !
b100001111010 "
0#
0+
b100001111010 *
b1001000001010100 )
b1001100011001110 .
0,
00
0%
b1001100011001110 $
#62000
b111110 (
b1101101111011 !
b1011000101101 "
1#
1+
b1011000101101 *
b1101101111011 )
1-
b10101001110 .
0/
b10101001110 $
1&
#63000
b110011 '
b110100 '
b111111 (
b1100000010101 !
b101000000000 "
0#
0+
b101000000000 *
b1100000010101 )
0-
b10001000010101 .
b10001000010101 $
0&
#64000
b1000000 (
b111011010101001 !
b1001100111100 "
b1001100111100 *
b111011010101001 )
b1000100111100101 .
b1000100111100101 $
#65000
b110101 '
b1000001 (
b10111010110110 !
b1010110101101101 "
b1010110101101101 *
b10111010110110 )
1-
b1101110000100011 .
10
b1101110000100011 $
1&
#66000
b110110 '
b1000010 (
b1111001111000110 !
b11110100110 "
1#
1+
b11110100110 *
b1111001111000110 )
b1110110000100000 .
1/
00
b1110110000100000 $
#67000
b110111 '
b111000 '
b1000011 (
b101111110100 !
b1110111100101001 "
b1110111100101001 *
b101111110100 )
b1110011001011 .
1,
0/
10
1%
b1110011001011 $
#68000
b111001 '
b111010 '
b1000100 (
b1111010101111 !
b101111001011110 "
b101111001011110 *
b1111010101111 )
b1100000001010001 .
00
b1100000001010001 $
#69000
b111011 '
b111100 '
b1000101 (
b10001010001000 !
b1000010110101010 "
b1000010110101010 *
b10001010001000 )
01
0-
b1001110011011110 .
10
b1001110011011110 $
0&
#70000
b111101 '
b111110 '
b1000110 (
b10000011111010 !
b111001101001110 "
b111001101001110 *
b10000011111010 )
11
b1010110110101100 .
00
b1010110110101100 $
#71000
b111111 '
b1000111 (
b10010000010110 !
b110010100101 "
b110010100101 *
b10010000010110 )
01
b1011101110001 .
0,
0%
b1011101110001 $
#72000
b1000000 '
b1001000 (
b1000001010000110 !
b1010000100111101 "
b1010000100111101 *
b1000001010000110 )
b1110000101001001 .
1,
1/
10
1%
b1110000101001001 $
#73000
b1000001 '
b1001001 (
b110001000011100 !
b1100001111000011 "
0#
0+
b1100001111000011 *
b110001000011100 )
11
b10010111011111 .
0/
b10010111011111 $
#74000
b1001010 (
b1000000100001110 !
b11101110101111 "
b11101110101111 *
b1000000100001110 )
01
b1011110010111101 .
0,
1/
00
0%
b1011110010111101 $
#75000
b1001011 (
b1110100101000010 !
b11100110001000 "
1#
1+
b11100110001000 *
b1110100101000010 )
11
1-
b1010111110111010 .
b1010111110111010 $
1&
#76000
b1000010 '
b1000011 '
b1001100 (
b1011101000110001 !
b10001111000100 "
b10001111000100 *
b1011101000110001 )
b1001011001101101 .
b1001011001101101 $
#77000
b1000100 '
b1000101 '
b1001101 (
b1111011101001011 !
b1101001101111001 "
b1101001101111001 *
b1111011101001011 )
b10001111010010 .
10
b10001111010010 $
#78000
b1000110 '
b1000111 '
b1001110 (
b11100010001101 !
b1001110100000110 "
b1001110100000110 *
b11100010001101 )
01
0-
b1001101110000111 .
1,
0/
1%
b1001101110000111 $
0&
#79000
b1001000 '
b1001001 '
b1001111 (
b100001010001010 !
b1101101110110 "
b1101101110110 *
b100001010001010 )
11
b10011100010100 .
0,
00
0%
b10011100010100 $
#80000
b1001010 '
b1010000 (
b1010111011010001 !
b1011111000011011 "
0#
0+
b1011111000011011 *
b1010111011010001 )
b110110011101100 .
1,
1/
10
1%
b110110011101100 $
#81000
b1001011 '
b1010001 (
b10111000011 !
b111101000101000 "
b111101000101000 *
b10111000011 )
1-
b111111111101011 .
0,
0/
00
0%
b111111111101011 $
1&
#82000
b1001100 '
b1010010 (
b100101100000 !
b1011111100110001 "
1#
1+
b1011111100110001 *
b100101100000 )
01
0-
b100101000101111 .
1,
10
1%
b100101000101111 $
0&
#83000
b1001101 '
b1010011 (
b10111000111101 !
b111010110001011 "
b111010110001011 *
b10111000111101 )
11
1-
b1011100010110010 .
00
b1011100010110010 $
1&
#84000
b1001110 '
b1001111 '
b1010100 (
b1011000001101100 !
b1100110100100001 "
b1100110100100001 *
b1011000001101100 )
01
0-
b1110001101001011 .
1/
10
b1110001101001011 $
0&
#85000
b1010000 '
b1010101 (
b110000010101111 !
b110001010001111 "
0#
0+
b110001010001111 *
b110000010101111 )
11
b1100001100111110 .
0,
0/
00
0%
b1100001100111110 $
#86000
b1010001 '
b1010110 (
b10000000110101 !
b101100011011000 "
1#
1+
b101100011011000 *
b10000000110101 )
01
b1100011101011101 .
1,
1%
b1100011101011101 $
#87000
b1010010 '
b1010111 (
b101001011111 !
b1011010101 "
b1011010101 *
b101001011111 )
b11110001010 .
0,
0%
b11110001010 $
#88000
b1010011 '
b1011000 (
b1011011000001011 !
b1101110001101111 "
b1101110001101111 *
b1011011000001011 )
b1101100110011100 .
1,
1/
10
1%
b1101100110011100 $
#89000
b1010100 '
b1011001 (
b1100110011101100 !
b1011110000001 "
b1011110000001 *
b1100110011101100 )
b1011010101101011 .
0,
00
0%
b1011010101101011 $
#90000
b1010101 '
b1011010 (
b1011110010110011 !
b1011110011001010 "
b1011110011001010 *
b1011110010110011 )
11
1-
b1111111111101001 .
1,
10
1%
b1111111111101001 $
1&
#91000
b1010110 '
b1010111 '
b1011011 (
b101100001001001 !
b10011111011011 "
b10011111011011 *
b101100001001001 )
01
0-
b11000001101110 .
0,
0/
00
0%
b11000001101110 $
0&
#92000
b1011000 '
b1011100 (
b11011011011000 !
b1111110000001001 "
0#
0+
b1111110000001001 *
b11011011011000 )
11
b11001011100001 .
1,
10
1%
b11001011100001 $
#93000
b1011101 (
b11110000001000 !
b10001100010010 "
b10001100010010 *
b11110000001000 )
01
b101111100011010 .
0,
00
0%
b101111100011010 $
#94000
b1011110 (
b1011010011000001 !
b111000111111100 "
1#
1+
b111000111111100 *
b1011010011000001 )
b100001011000101 .
1/
b100001011000101 $
#95000
b1011001 '
b1011010 '
b1011111 (
b1010110100100101 !
b1100011111011111 "
b1100011111011111 *
b1010110100100101 )
11
b1110010101000110 .
1,
10
1%
b1110010101000110 $
#96000
b1011011 '
b1100000 (
b11001011000 !
b1100001110001110 "
0#
0+
b1100001110001110 *
b11001011000 )
b1100100111100110 .
0,
0/
0%
b1100100111100110 $
#97000
b1100001 (
b11110011001010 !
b1100010001100000 "
1#
1+
b1100010001100000 *
b11110011001010 )
1-
b111100001101010 .
1,
1%
b111100001101010 $
1&
#98000
b1011100 '
b1011101 '
b1100010 (
b1100000101011010 !
b101110110011010 "
0#
0+
b101110110011010 *
b1100000101011010 )
01
0-
b1111011110100 .
1/
00
b1111011110100 $
0&
#99000
b1100011 (
b100011100001101 !
b101101110000000 "
b101101110000000 *
b100011100001101 )
b1010001010001101 .
0,
0/
0%
b1010001010001101 $
#100000
b1011110 '
b1100100 (
b101100001001 !
b111100011100110 "
1#
1+
b111100011100110 *
b101100001001 )
b1001001000100011 .
1,
1%
b1001001000100011 $
#101000
b1011111 '
b1100101 (
b1011101011001111 !
b1100000100111001 "
0#
0+
b1100000100111001 *
b1011101011001111 )
11
b111110000001000 .
1/
10
b111110000001000 $
#102000
b1100000 '
b1100110 (
b111101000101011 !
b111010111100100 "
b111010111100100 *
b111101000101011 )
1-
b1111000000001111 .
0,
0/
00
0%
b1111000000001111 $
1&
#103000
b1100111 (
b100010101110 !
b1011011010111111 "
b1011011010111111 *
b100010101110 )
b1011111101101101 .
10
b1011111101101101 $
#104000
b1100001 '
b1101000 (
b1101011011010 !
b110000101001110 "
1#
1+
b110000101001110 *
b1101011011010 )
b1011100110001100 .
1,
00
1%
b1011100110001100 $
#105000
b1100010 '
b1100011 '
b1101001 (
b1101100011110100 !
b101101010111000 "
0#
0+
b101101010111000 *
b1101100011110100 )
0-
b11001110101100 .
1/
b11001110101100 $
0&
#106000
b1101010 (
b10111110001100 !
b110100001011001 "
1#
1+
b110100001011001 *
b10111110001100 )
1-
b1100011100110011 .
0/
b1100011100110011 $
1&
#107000
b1100100 '
b1100101 '
b1101011 (
b1010111110101101 !
b11011001001001 "
b11011001001001 *
b1010111110101101 )
01
0-
b111100101100100 .
0,
1/
0%
b111100101100100 $
0&
#108000
b1100110 '
b1100111 '
b1101100 (
b11000000110000 !
b110110001010011 "
0#
0+
b110110001010011 *
b11000000110000 )
b1001110010000011 .
0/
b1001110010000011 $
#109000
b1101000 '
b1101101 (
b1011011101011001 !
b1101010011111010 "
b1101010011111010 *
b1011011101011001 )
11
1-
b1000110001010011 .
1,
1/
10
1%
b1000110001010011 $
1&
#110000
b1101001 '
b1101110 (
b1001100010010011 !
b100110000110010 "
b100110000110010 *
b1001100010010011 )
0-
b1110010011000101 .
0,
00
0%
b1110010011000101 $
0&
#111000
b1101111 (
b1001100000011010 !
b1101000000001010 "
1#
1+
b1101000000001010 *
b1001100000011010 )
1-
b1100100000010000 .
1,
10
1%
b1100100000010000 $
1&
#112000
b1101010 '
b1101011 '
b1110000 (
b1001000110 !
b101110001011111 "
0#
0+
b101110001011111 *
b1001000110 )
0-
b101111010100101 .
0,
0/
00
0%
b101111010100101 $
0&
#113000
b1110001 (
b10011000000110 !
b1000111111110110 "
b1000111111110110 *
b10011000000110 )
b1011010111111100 .
10
b1011010111111100 $
#114000
b1110010 (
b1111011011110100 !
b1100000111001000 "
b1100000111001000 *
b1111011011110100 )
01
b1011100010111100 .
1,
1/
1%
b1011100010111100 $
#115000
b1110011 (
b101111000101100 !
b1101100000010111 "
1#
1+
b1101100000010111 *
b101111000101100 )
b1000011000010101 .
0/
b1000011000010101 $
#116000
b1101100 '
b1101101 '
b1110100 (
b1100011000000 !
b1110000100110 "
b1110000100110 *
b1100011000000 )
11
b1111110010011010 .
00
b1111110010011010 $
#117000
b1101110 '
b1110101 (
b110100111001010 !
b1000010110001110 "
0#
0+
b1000010110001110 *
b110100111001010 )
b1110111101011000 .
0,
10
0%
b1110111101011000 $
#118000
b1110110 (
b1010101100101001 !
b101011110001010 "
1#
1+
b101011110001010 *
b1010101100101001 )
1-
b101001110011111 .
1/
00
b101001110011111 $
1&
#119000
b1101111 '
b1110111 (
b10111011111111 !
b1100100010001 "
b1100100010001 *
b10111011111111 )
0-
b1010111101110 .
0/
b1010111101110 $
0&
#120000
b1110000 '
b1111000 (
b1001011001110010 !
b111010011101000 "
0#
0+
b111010011101000 *
b1001011001110010 )
b101101011010 .
1,
1/
1%
b101101011010 $
#121000
b1111001 (
b101001011001001 !
b1011111100100000 "
1#
1+
b1011111100100000 *
b101001011001001 )
1-
b1001001110101001 .
0/
10
b1001001110101001 $
1&
#122000
b1110001 '
b1111010 (
b1101011111101001 !
b1001101101000000 "
0#
0+
b1001101101000000 *
b1101011111101001 )
01
0-
b111001100101001 .
1/
b111001100101001 $
0&
#123000
b1110010 '
b1111011 (
b101010110000011 !
b10010110100111 "
b10010110100111 *
b101010110000011 )
11
1-
b111101100101010 .
0,
0/
00
0%
b111101100101010 $
1&
#124000
b1110011 '
b1111100 (
b1011000010011011 !
b1110100111010101 "
b1110100111010101 *
b1011000010011011 )
0-
b1001101001110000 .
1,
1/
10
1%
b1001101001110000 $
0&
#125000
b1111101 (
b1001010010011011 !
b101011110001001 "
b101011110001001 *
b1001010010011011 )
b1110110000100100 .
0,
00
0%
b1110110000100100 $
#126000
b1111110 (
b1111010000011111 !
b1101000101111 "
1#
1+
b1101000101111 *
b1111010000011111 )
1-
b1101100111110000 .
b1101100111110000 $
1&
#127000
b1110100 '
b1110101 '
b1111111 (
b1010000011100110 !
b101010010 "
b101010010 *
b1010000011100110 )
b1001111110010100 .
b1001111110010100 $
#128000
b1110110 '
b1110111 '
b10000000 (
b1001100011000111 !
b1001110110111 "
b1001110110111 *
b1001100011000111 )
b1000010100010000 .
b1000010100010000 $
#129000
b1111000 '
b1111001 '
b10000001 (
b1101000101001001 !
b100000101111111 "
b100000101111111 *
b1101000101001001 )
b1000111111001010 .
b1000111111001010 $
#130000
b1111010 '
b1111011 '
b10000010 (
b1111000000101111 !
b1000111101010101 "
0#
0+
b1000111101010101 *
b1111000000101111 )
01
0-
b111111110000100 .
1,
10
1%
b111111110000100 $
0&
#131000
b1111100 '
b10000011 (
b1001100001110101 !
b110000101100 "
1#
1+
b110000101100 *
b1001100001110101 )
b1000110001001001 .
0,
00
0%
b1000110001001001 $
#132000
b1111101 '
b10000100 (
b1001101100011 !
b1101010011011111 "
b1101010011011111 *
b1001101100011 )
11
1-
b11111010000100 .
1,
0/
10
1%
b11111010000100 $
1&
#133000
b1111110 '
b1111111 '
b10000101 (
b1000111010110011 !
b1001011111100 "
0#
0+
b1001011111100 *
b1000111010110011 )
01
0-
b1010000110101111 .
0,
1/
00
0%
b1010000110101111 $
0&
#134000
b10000110 (
b1100100000100000 !
b1000000101111010 "
b1000000101111010 *
b1100100000100000 )
b100100110011010 .
1,
10
1%
b100100110011010 $
#135000
b10000000 '
b10000111 (
b110000011110011 !
b11001111110011 "
b11001111110011 *
b110000011110011 )
11
1-
b1001010011100110 .
0,
0/
00
0%
b1001010011100110 $
1&
#136000
b10001000 (
b11110101001110 !
b1111001110000011 "
1#
1+
b1111001110000011 *
b11110101001110 )
01
0-
b100100111001011 .
1,
10
1%
b100100111001011 $
0&
#137000
b10000001 '
b10001001 (
b1011000110000111 !
b10110101101101 "
b10110101101101 *
b1011000110000111 )
11
1-
b1000010000011010 .
0,
1/
00
0%
b1000010000011010 $
1&
#138000
b10000010 '
b10000011 '
b10001010 (
b1100010110110001 !
b110110110101010 "
b110110110101010 *
b1100010110110001 )
b101100000000111 .
b101100000000111 $
#139000
b10000100 '
b10001011 (
b1001110111110111 !
b1010000000010111 "
b1010000000010111 *
b1001110111110111 )
0-
b1111110111100000 .
1,
10
1%
b1111110111100000 $
0&
#140000
b10000101 '
b10001100 (
b1000000110001111 !
b1110010110100101 "
0#
0+
b1110010110100101 *
b1000000110001111 )
b110011100110100 .
b110011100110100 $
#141000
b10000110 '
b10001101 (
b110111001110000 !
b11111000000010 "
1#
1+
b11111000000010 *
b110111001110000 )
01
b11000001101110 .
0,
0/
00
0%
b11000001101110 $
#142000
b10000111 '
b10001110 (
b101110010000011 !
b1100000101011001 "
0#
0+
b1100000101011001 *
b101110010000011 )
11
b1110111011100 .
1,
10
1%
b1110111011100 $
#143000
b10001111 (
b1011101001111101 !
b1000001111101110 "
b1000001111101110 *
b1011101001111101 )
01
b11111001101011 .
1/
b11111001101011 $
#144000
b10001000 '
b10010000 (
b111101000011010 !
b110001111111010 "
b110001111111010 *
b111101000011010 )
11
1-
b1101111000010100 .
0,
0/
00
0%
b1101111000010100 $
1&
#145000
b10010001 (
b111110010100001 !
b1001101110111011 "
b1001101110111011 *
b111110010100001 )
b1100001011100 .
1,
10
1%
b1100001011100 $
#146000
b10001001 '
b10010010 (
b110001000010000 !
b11001011010101 "
1#
1+
b11001011010101 *
b110001000010000 )
b10111100111011 .
0,
00
0%
b10111100111011 $
#147000
b10001010 '
b10001011 '
b10010011 (
b1011111001001 !
b11110000101111 "
b11110000101111 *
b1011111001001 )
01
0-
b1101101110011010 .
1,
1%
b1101101110011010 $
0&
#148000
b10001100 '
b10010100 (
b1010001001111001 !
b1001010111001011 "
b1001010111001011 *
b1010001001111001 )
b110010101110 .
0,
1/
10
0%
b110010101110 $
#149000
b10001101 '
b10010101 (
b1001110110110101 !
b101101010100111 "
b101101010100111 *
b1001110110110101 )
b100001100001110 .
00
b100001100001110 $
#150000
b10001110 '
b10001111 '
b10010110 (
b1011110010110100 !
b111101101010110 "
b111101101010110 *
b1011110010110100 )
11
b100000101011110 .
b100000101011110 $
#151000
b10010000 '
b10010001 '
b10010111 (
b101000100100101 !
b1010111101010010 "
0#
0+
b1010111101010010 *
b101000100100101 )
01
b1110111 .
1,
0/
10
1%
b1110111 $
#152000
b10011000 (
b1000101 !
b101110101001110 "
b101110101001110 *
b1000101 )
b101110110010011 .
0,
00
0%
b101110110010011 $
#153000
b10011001 (
b1010110001010110 !
b1101000011011000 "
b1101000011011000 *
b1010110001010110 )
11
b111110100101110 .
1,
1/
10
1%
b111110100101110 $
