Behavior/adder_b.v
module adder_16bit_b(A , B ,Add_ctrl , O , C_out , SUM);

input [15:0] A , B ;
input Add_ctrl;//1 for sub ,0 for add

output [15:00] SUM ;
output C_out ;
output O ;
reg aC_out;
reg aO;
reg [16:0] idx;
reg ws;
reg [15:0] bp;
reg [15:0] aSUM;
assign e=A[15];
assign r=B[15];
assign O=aO;
assign C_out=aC_out;
assign SUM=aSUM;

/** your code **/

always@(A or B or Add_ctrl)
begin

aSUM=(Add_ctrl==0)?(A+B):(A-B);
bp=(((Add_ctrl==1)?~B:B)+Add_ctrl);
aC_out=1'b0;
for(idx=0;idx<16;idx=idx+1)begin
{aC_out,ws}={1'b0,bp[idx]}+{1'b0,A[idx]}+{1'b0,aC_out};
//$display("this is test : idx= %d | aO= %b",idx,aO);
end

end



reg pn;
always@(A or B or Add_ctrl)
#1 begin
pn=(Add_ctrl==1)?(((e==0)&&(r==1))||((e==1)&&(r==0)))?1:0:(((e==0)&&(r==0))||((e==1)&&(r==1)))?1:0;
aO=(pn==1)?(C_out==SUM[15])?0:1:0;
end  

endmodule

Behavior/testbench.v
`timescale 1ns/10ps

`include        "adder_b.v"

module tb_adder ;
reg [15:0] A , B ;
reg Add_ctrl ;

wire [15:0] SUM;
wire C_out ;
wire O ;


reg [15:0] mem_A [9999:0] ;
reg [15:0] mem_B [9999:0] ;
reg mem_add_ctrl [9999:0] ;
reg [17:0] expect [9999:0] ;

reg    [16:0] error = 0;
integer i ;

initial 
begin
	$readmemh("A.txt", mem_A);
	$readmemh("B.txt", mem_B);
	$readmemh("Add_ctrl.txt", mem_add_ctrl);
	$readmemh("Result.txt", expect);
end


adder_16bit_b u_adder(        .A            (A        ),
                .B            (B        ),
                .Add_ctrl     (Add_ctrl ),
                .O            (O        ),
                .C_out        (C_out    ),
                .SUM          (SUM      )
);

initial 
begin

	for (i =0 ; i <= 9999; i = i + 1 )          
  begin
    A = mem_A[i] ;
	B = mem_B[i] ;
	Add_ctrl = mem_add_ctrl[i] ;
    
    #10;
    if (SUM !== expect[i][15:0])
        begin
           $display ("ERROR at time=%d(pattern%d): SUM(%h)!= expect(%h)",
                      $time, i+1, SUM, expect[i][15:0]);
           error = error + 1;
	end
		
    if (C_out !== expect[i][16])
	begin
           $display ("ERROR at time=%d(pattern%d): C_out(%b)!= expect(%b)", 
                      $time,  i+1, C_out, expect[i][16]);
           error = error + 1;
	end

    if ( O !== expect[i][17])
	begin
           $display ("ERROR at time=%d(pattern%d): O(%b)!= expect(%b)",
                      $time, i+1, O , expect[i][17]);
	    error = error + 1;
	end
    end

     if(error == 17'b0)
     begin
      $display ("=============================================================");
      $display ("Congratulation!, Your design PASSed all the test patterns ");
	  $display ("^     ^");
	  $display (" +++++");
      $display ("=============================================================");
      end
      else
      begin
      $display ("=================================================");
      $display ("There're %d errors in your design", error); 
      $display ("=================================================");
      end

	$finish ;
end

initial
begin
	$dumpfile("addS16_new.vcd");
	$dumpvars;
end
	
endmodule

Behavior/addS16_new.vcd
$date
    Oct 15, 2019  19:33:24
$end
$version
    TOOL:	ncsim	15.20-s039
$end
$timescale
    10 ps
$end

$scope module tb_adder $end
$var reg      16 !    A [15:0] $end
$var reg      16 "    B [15:0] $end
$var reg       1 #    Add_ctrl  $end
$var wire     16 $    SUM [15:0] $end
$var wire      1 %    C_out  $end
$var wire      1 &    O  $end
$var reg      17 '    error [16:0] $end
$var integer  32 (    i  $end

$scope module u_adder $end
$var wire     16 )    A [15:0] $end
$var wire     16 *    B [15:0] $end
$var wire      1 +    Add_ctrl  $end
$var wire     16 $    SUM [15:0] $end
$var wire      1 %    C_out  $end
$var wire      1 &    O  $end
$var reg       1 ,    aC_out  $end
$var reg       1 -    aO  $end
$var reg      17 .    idx [16:0] $end
$var reg       1 /    ws  $end
$var reg      16 0    bp [15:0] $end
$var reg      16 1    aSUM [15:0] $end
$var wire      1 2    e  $end
$var wire      1 3    r  $end
$var reg       1 4    pn  $end
$upscope $end

$upscope $end

$enddefinitions $end
$dumpvars
b1111101001011110 !
b1010000110001000 "
0#
b1001101111100110 $
1%
x&
b0 '
b0 (
b1111101001011110 )
b1010000110001000 *
0+
1,
x-
b10000 .
1/
b1010000110001000 0
b1001101111100110 1
12
13
x4
$end
#100
14
0-
0&
#1000
b1 (
b111000111010110 !
b110001011011100 "
1#
1+
b110001011011100 *
b111000111010110 )
b111011111010 1
b1001110100100100 0
0,
b0 .
0/
b1 .
1/
b10 .
0/
1,
b11 .
1/
0,
b100 .
b101 .
b110 .
b111 .
b1000 .
0/
1,
b1001 .
1/
0,
b1010 .
b1011 .
b1100 .
0/
1,
b1101 .
b1110 .
b1111 .
b10000 .
02
03
b111011111010 $
#1100
04
#2000
b10 (
b110001011111101 !
b1001110010101000 "
0#
0+
b1001110010101000 *
b110001011111101 )
b1111111110100101 1
b1001110010101000 0
0,
b0 .
1/
b1 .
0/
b10 .
1/
b11 .
0/
1,
b100 .
b101 .
1/
b110 .
0/
b111 .
1/
b1000 .
0,
b1001 .
b1010 .
b1011 .
b1100 .
b1101 .
b1110 .
b1111 .
b10000 .
13
0%
b1111111110100101 $
#3000
b11 (
b1111001111110011 !
b1001010100111100 "
b1001010100111100 *
b1111001111110011 )
b1000100100101111 1
b1001010100111100 0
b0 .
b1 .
b10 .
b11 .
b100 .
0/
1,
b101 .
1/
b110 .
0/
b111 .
b1000 .
1/
b1001 .
0/
b1010 .
b1011 .
1/
0,
b1100 .
0/
1,
b1101 .
b1110 .
b1111 .
1/
b10000 .
12
1%
b1000100100101111 $
#3100
14
#4000
b100 (
b1001111111111110 !
b1101001101011011 "
1#
1+
b1101001101011011 *
b1001111111111110 )
b1100110010100011 1
b10110010100101 0
0,
b0 .
b1 .
b10 .
0/
1,
b11 .
b100 .
b101 .
1/
b110 .
0/
b111 .
1/
b1000 .
0/
b1001 .
b1010 .
1/
b1011 .
b1100 .
0/
b1101 .
b1110 .
1/
0,
b1111 .
b10000 .
0%
b1100110010100011 $
#4100
04
#5000
b101 (
b1001001101000100 !
b101111000011000 "
0#
0+
b101111000011000 *
b1001001101000100 )
b1111000101011100 1
b101111000011000 0
b0 .
0/
b1 .
b10 .
1/
b11 .
b100 .
b101 .
0/
b110 .
1/
b111 .
0/
b1000 .
1/
b1001 .
0/
1,
b1010 .
b1011 .
b1100 .
1/
b1101 .
0,
b1110 .
b1111 .
b10000 .
03
b1111000101011100 $
#6000
b110 (
b11001010110 !
b11000101011 "
1#
1+
b11000101011 *
b11001010110 )
b101011 1
b1111100111010101 0
b0 .
b1 .
b10 .
0/
1,
b11 .
1/
0,
b100 .
0/
1,
b101 .
1/
0,
b110 .
0/
1,
b111 .
b1000 .
b1001 .
b1010 .
b1011 .
b1100 .
b1101 .
b1110 .
b1111 .
b10000 .
02
1%
b101011 $
#7000
b111 (
b11010000111 !
b110001101000000 "
b110001101000000 *
b11010000111 )
b1010001101000111 1
b1001110011000000 0
0,
b0 .
1/
b1 .
b10 .
b11 .
0/
b100 .
b101 .
b110 .
1/
b111 .
0/
1,
b1000 .
1/
0,
b1001 .
b1010 .
0/
1,
b1011 .
b1100 .
b1101 .
1/
0,
b1110 .
0/
b1111 .
1/
b10000 .
0%
b1010001101000111 $
#8000
b1000 (
b100011000010110 !
b101110100101110 "
b101110100101110 *
b100011000010110 )
b1110100011101000 1
b1010001011010010 0
b0 .
0/
b1 .
1,
b10 .
b11 .
1/
0,
b100 .
0/
1,
b101 .
1/
0,
b110 .
b111 .
b1000 .
0/
b1001 .
1,
b1010 .
b1011 .
1/
0,
b1100 .
0/
b1101 .
1/
b1110 .
b1111 .
b10000 .
b1110100011101000 $
#9000
b1001 (
b1101011101010100 !
b10010011111101 "
0#
0+
b10010011111101 *
b1101011101010100 )
b1111110001010001 1
b10010011111101 0
b0 .
b1 .
0/
b10 .
1,
b11 .
b100 .
1/
b101 .
0/
b110 .
1/
b111 .
0/
b1000 .
b1001 .
b1010 .
1/
b1011 .
0,
b1100 .
b1101 .
b1110 .
b1111 .
b10000 .
12
b1111110001010001 $
#10000
b1010 (
b1101010111101001 !
b100100001101011 "
b100100001101011 *
b1101010111101001 )
b1111001010100 1
b100100001101011 0
b0 .
0/
1,
b1 .
b10 .
1/
0,
b11 .
0/
1,
b100 .
1/
0,
b101 .
0/
1,
b110 .
1/
b111 .
0/
b1000 .
b1001 .
1/
0,
b1010 .
b1011 .
b1100 .
b1101 .
0/
b1110 .
1,
b1111 .
b10000 .
1%
b1111001010100 $
#11000
b1011 (
b110001000011010 !
b1111001011010001 "
b1111001011010001 *
b110001000011010 )
b101010011101011 1
b1111001011010001 0
0,
b0 .
1/
b1 .
b10 .
0/
b11 .
1/
b100 .
0/
1,
b101 .
1/
0,
b110 .
b111 .
b1000 .
0/
b1001 .
1,
b1010 .
1/
0,
b1011 .
0/
b1100 .
1/
b1101 .
0/
1,
b1110 .
1/
b1111 .
0/
b10000 .
02
13
b101010011101011 $
#12000
b1100 (
b11010011111 !
b1100110111101100 "
1#
1+
b1100110111101100 *
b11010011111 )
b11100010110011 1
b11001000010100 0
0,
b0 .
1/
b1 .
b10 .
0/
1,
b11 .
b100 .
1/
b101 .
0,
b110 .
0/
b111 .
1/
b1000 .
0/
b1001 .
1,
b1010 .
b1011 .
1/
0,
b1100 .
b1101 .
b1110 .
0/
b1111 .
b10000 .
0%
b11100010110011 $
#12100
14
#13000
b1101 (
b1000100101000 !
b1100011111011011 "
b1100011111011011 *
b1000100101000 )
b100100101001101 1
b11100000100101 0
b0 .
1/
b1 .
0/
b10 .
1/
b11 .
b100 .
0/
b101 .
1,
b110 .
1/
0,
b111 .
0/
b1000 .
1/
b1001 .
0/
b1010 .
b1011 .
1/
b1100 .
0/
1,
b1101 .
b1110 .
1/
0,
b1111 .
0/
b10000 .
b100100101001101 $
#14000
b1110 (
b101110111100101 !
b1110101110000 "
0#
0+
b1110101110000 *
b101110111100101 )
b111101101010101 1
b1110101110000 0
b0 .
1/
b1 .
0/
b10 .
1/
b11 .
0/
b100 .
1/
b101 .
0/
1,
b110 .
1/
b111 .
0/
b1000 .
1/
b1001 .
0,
b1010 .
0/
1,
b1011 .
1/
b1100 .
b1101 .
0,
b1110 .
b1111 .
0/
b10000 .
03
b111101101010101 $
#15000
b1111 (
b10111000 !
b10100100100111 "
b10100100100111 *
b10111000 )
b10100111011111 1
b10100100100111 0
b0 .
1/
b1 .
b10 .
b11 .
b100 .
b101 .
0/
1,
b110 .
1/
0,
b111 .
b1000 .
b1001 .
0/
b1010 .
b1011 .
1/
b1100 .
0/
b1101 .
1/
b1110 .
0/
b1111 .
b10000 .
b10100111011111 $
#16000
b10000 (
b100001111001011 !
b1010111100001110 "
b1010111100001110 *
b100001111001011 )
b1111001011011001 1
b1010111100001110 0
b0 .
1/
b1 .
0/
1,
b10 .
b11 .
1/
b100 .
0,
b101 .
0/
b110 .
1/
b111 .
b1000 .
0/
1,
b1001 .
1/
b1010 .
0/
b1011 .
b1100 .
1/
0,
b1101 .
b1110 .
b1111 .
b10000 .
13
b1111001011011001 $
#16100
04
#17000
b10001 (
b100110111 !
b1011110111011010 "
1#
1+
b1011110111011010 *
b100110111 )
b100001101011101 1
b100001000100110 0
b0 .
b1 .
0/
1,
b10 .
1/
b11 .
0,
b100 .
b101 .
0/
1,
b110 .
1/
0,
b111 .
0/
b1000 .
1/
b1001 .
b1010 .
0/
b1011 .
b1100 .
b1101 .
b1110 .
1/
b1111 .
0/
b10000 .
b100001101011101 $
#17100
14
#18000
b10010 (
b1100111001010011 !
b110010101001011 "
0#
0+
b110010101001011 *
b1100111001010011 )
b11001110011110 1
b110010101001011 0
b0 .
1,
b1 .
1/
b10 .
0,
b11 .
b100 .
b101 .
0/
b110 .
1,
b111 .
1/
0,
b1000 .
b1001 .
b1010 .
0/
1,
b1011 .
b1100 .
1/
0,
b1101 .
b1110 .
0/
1,
b1111 .
b10000 .
12
03
1%
b11001110011110 $
#18100
04
#19000
b10011 (
b1010001010101001 !
b111010101111 "
1#
1+
b111010101111 *
b1010001010101001 )
b1001001111111010 1
b1111000101010001 0
0,
b0 .
1,
b1 .
1/
0,
b10 .
0/
b11 .
1/
b100 .
b101 .
b110 .
b111 .
b1000 .
b1001 .
b1010 .
0/
b1011 .
b1100 .
1/
b1101 .
0/
1,
b1110 .
b1111 .
1/
b10000 .
b1001001111111010 $
#19100
14
#20000
b10100 (
b1011001010100011 !
b1010111100010101 "
0#
0+
b1010111100010101 *
b1011001010100011 )
b110000110111000 1
b1010111100010101 0
0,
b0 .
0/
1,
b1 .
b10 .
b11 .
1/
0,
b100 .
b101 .
b110 .
0/
b111 .
1/
b1000 .
b1001 .
0/
1,
b1010 .
b1011 .
b1100 .
b1101 .
1/
b1110 .
0,
b1111 .
0/
1,
b10000 .
13
b110000110111000 $
#20100
1-
1&
#21000
b10101 (
b1010111100000101 !
b1111000011001000 "
1#
1+
b1111000011001000 *
b1010111100000101 )
b1011111000111101 1
b111100111000 0
0,
b0 .
1/
b1 .
0/
b10 .
1/
b11 .
b100 .
b101 .
b110 .
0/
b111 .
b1000 .
1,
b1001 .
1/
b1010 .
b1011 .
b1100 .
0,
b1101 .
b1110 .
0/
b1111 .
1/
b10000 .
0%
b1011111000111101 $
#21100
04
0-
0&
#22000
b10110 (
b1010100111101100 !
b1111011111001011 "
0#
0+
b1111011111001011 *
b1010100111101100 )
b1010000110110111 1
b1111011111001011 0
b0 .
b1 .
b10 .
b11 .
0/
1,
b100 .
1/
0,
b101 .
b110 .
0/
1,
b111 .
1/
b1000 .
b1001 .
0/
b1010 .
b1011 .
b1100 .
b1101 .
1/
b1110 .
0/
b1111 .
1/
b10000 .
1%
b1010000110110111 $
#22100
14
#23000
b10111 (
b1111100111111101 !
b1100010011111101 "
1#
1+
b1100010011111101 *
b1111100111111101 )
b11010100000000 1
b11101100000011 0
0,
b0 .
0/
1,
b1 .
b10 .
b11 .
b100 .
b101 .
b110 .
b111 .
b1000 .
1/
b1001 .
0/
b1010 .
1/
0,
b1011 .
0/
1,
b1100 .
1/
b1101 .
b1110 .
0/
b1111 .
b10000 .
b11010100000000 $
#23100
04
#24000
b11000 (
b1000000000001111 !
b1010010100011011 "
b1010010100011011 *
b1000000000001111 )
b1101101011110100 1
b101101011100101 0
0,
b0 .
1,
b1 .
b10 .
1/
b11 .
0/
b100 .
1/
0,
b101 .
b110 .
b111 .
b1000 .
0/
b1001 .
1/
b1010 .
0/
b1011 .
1/
b1100 .
b1101 .
0/
b1110 .
1/
b1111 .
b10000 .
0%
b1101101011110100 $
#25000
b11001 (
b1111011110010011 !
b110000010011001 "
b110000010011001 *
b1111011110010011 )
b1001011011111010 1
b1001111101100111 0
b0 .
0/
1,
b1 .
1/
b10 .
0/
b11 .
1/
0,
b100 .
b101 .
b110 .
b111 .
b1000 .
0/
1,
b1001 .
1/
b1010 .
b1011 .
0/
b1100 .
1/
b1101 .
0/
b1110 .
b1111 .
1/
b10000 .
03
1%
b1001011011111010 $
#25100
14
#26000
b11010 (
b100100110110011 !
b1110010011011110 "
b1110010011011110 *
b100100110110011 )
b110010011010101 1
b1101100100010 0
0,
b0 .
b1 .
0/
1,
b10 .
1/
0,
b11 .
0/
b100 .
1/
b101 .
0/
1,
b110 .
1/
0,
b111 .
b1000 .
0/
1,
b1001 .
b1010 .
1/
0,
b1011 .
0/
1,
b1100 .
b1101 .
1/
0,
b1110 .
b1111 .
0/
b10000 .
02
13
0%
b110010011010101 $
#27000
b11011 (
b111001110100010 !
b1000011111001111 "
b1000011111001111 *
b111001110100010 )
b1110101111010011 1
b111100000110001 0
b0 .
1/
b1 .
b10 .
0/
b11 .
b100 .
1/
b101 .
0/
1,
b110 .
1/
0,
b111 .
b1000 .
b1001 .
b1010 .
0/
b1011 .
1/
b1100 .
0/
1,
b1101 .
1/
b1110 .
b1111 .
0,
b10000 .
b1110101111010011 $
#27100
1-
1&
#28000
b11100 (
b10011111011100 !
b111001001111101 "
0#
0+
b111001001111101 *
b10011111011100 )
b1001101001011001 1
b111001001111101 0
b0 .
b1 .
0/
b10 .
1,
b11 .
1/
b100 .
b101 .
0/
b110 .
1/
b111 .
0/
b1000 .
b1001 .
1/
b1010 .
0/
b1011 .
1/
0,
b1100 .
b1101 .
0/
1,
b1110 .
b1111 .
1/
0,
b10000 .
03
b1001101001011001 $
#29000
b11101 (
b101110001010000 !
b1000111000100 "
b1000111000100 *
b101110001010000 )
b110111000010100 1
b1000111000100 0
b0 .
0/
b1 .
b10 .
1/
b11 .
0/
b100 .
1/
b101 .
0/
b110 .
1,
b111 .
b1000 .
b1001 .
1/
0,
b1010 .
b1011 .
b1100 .
0/
1,
b1101 .
1/
0,
b1110 .
b1111 .
0/
b10000 .
b110111000010100 $
#29100
0-
0&
#30000
b11110 (
b111000011111000 !
b1000110000111110 "
1#
1+
b1000110000111110 *
b111000011111000 )
b1110010010111010 1
b111001111000010 0
b0 .
b1 .
1/
b10 .
0/
b11 .
1/
b100 .
b101 .
b110 .
0/
1,
b111 .
1/
b1000 .
0/
b1001 .
b1010 .
1/
0,
b1011 .
0/
b1100 .
1,
b1101 .
1/
b1110 .
b1111 .
0,
b10000 .
13
b1110010010111010 $
#30100
1-
1&
#31000
b11111 (
b1001001101101110 !
b111001000110111 "
0#
0+
b111001000110111 *
b1001001101101110 )
b10110100101 1
b111001000110111 0
b0 .
b1 .
0/
1,
b10 .
1/
b11 .
0/
b100 .
b101 .
1/
b110 .
0/
b111 .
1/
0,
b1000 .
b1001 .
0/
1,
b1010 .
1/
0,
b1011 .
0/
b1100 .
1,
b1101 .
b1110 .
b1111 .
b10000 .
12
03
1%
b10110100101 $
#31100
04
0-
0&
#32000
b100000 (
b1111100010111110 !
b101001111001001 "
1#
1+
b101001111001001 *
b1111100010111110 )
b1010010011110101 1
b1010110000110111 0
0,
b0 .
1/
b1 .
0/
1,
b10 .
1/
b11 .
0/
b100 .
1/
b101 .
b110 .
0,
b111 .
b1000 .
0/
b1001 .
b1010 .
1/
b1011 .
0/
1,
b1100 .
b1101 .
1/
b1110 .
0/
b1111 .
1/
b10000 .
b1010010011110101 $
#32100
14
#33000
b100001 (
b110000001000001 !
b1000010111001010 "
0#
0+
b1000010111001010 *
b110000001000001 )
b1110011000001011 1
b1000010111001010 0
0,
b0 .
b1 .
b10 .
0/
b11 .
1/
b100 .
0/
b101 .
b110 .
1,
b111 .
b1000 .
b1001 .
1/
0,
b1010 .
b1011 .
0/
b1100 .
b1101 .
1/
b1110 .
b1111 .
b10000 .
02
13
0%
b1110011000001011 $
#33100
04
#34000
b100010 (
b111011100101000 !
b101101101100111 "
b101101101100111 *
b111011100101000 )
b1101001010001111 1
b101101101100111 0
b0 .
b1 .
b10 .
b11 .
b100 .
0/
b101 .
1,
b110 .
b111 .
1/
0,
b1000 .
0/
1,
b1001 .
1/
b1010 .
0/
b1011 .
b1100 .
1/
b1101 .
0/
b1110 .
1/
b1111 .
0,
b10000 .
03
b1101001010001111 $
#34100
14
1-
1&
#35000
b100011 (
b11010001101000 !
b1100010010001001 "
b1100010010001001 *
b11010001101000 )
b1111100011110001 1
b1100010010001001 0
b0 .
b1 .
0/
b10 .
b11 .
1,
b100 .
1/
0,
b101 .
b110 .
b111 .
b1000 .
0/
b1001 .
b1010 .
1,
b1011 .
1/
0,
b1100 .
b1101 .
b1110 .
b1111 .
b10000 .
13
b1111100011110001 $
#35100
04
0-
0&
#36000
b100100 (
b1000101011111110 !
b1011010101010010 "
b1011010101010010 *
b1000101011111110 )
b100000001010000 1
b1011010101010010 0
b0 .
0/
b1 .
1,
b10 .
b11 .
b100 .
1/
b101 .
0/
b110 .
1/
b111 .
0/
b1000 .
b1001 .
b1010 .
b1011 .
b1100 .
b1101 .
b1110 .
1/
0,
b1111 .
0/
1,
b10000 .
12
1%
b100000001010000 $
#36100
14
1-
1&
#37000
b100101 (
b1100100100111111 !
b1101101110110110 "
1#
1+
b1101101110110110 *
b1100100100111111 )
b1110110110001001 1
b10010001001010 0
0,
b0 .
1/
b1 .
0/
1,
b10 .
b11 .
1/
b100 .
0/
b101 .
b110 .
b111 .
1/
0,
b1000 .
b1001 .
0/
b1010 .
1/
b1011 .
b1100 .
0/
b1101 .
1/
b1110 .
b1111 .
b10000 .
0%
b1110110110001001 $
#37100
04
0-
0&
#38000
b100110 (
b1100101110000000 !
b1101010011100011 "
0#
0+
b1101010011100011 *
b1100101110000000 )
b1010000001100011 1
b1101010011100011 0
b0 .
b1 .
b10 .
0/
b11 .
b100 .
b101 .
1/
b110 .
b111 .
0/
1,
b1000 .
b1001 .
b1010 .
b1011 .
b1100 .
b1101 .
1/
0,
b1110 .
0/
1,
b1111 .
1/
b10000 .
1%
b1010000001100011 $
#38100
14
#39000
b100111 (
b1001100011100001 !
b1001001111101001 "
b1001001111101001 *
b1001100011100001 )
b10110011001010 1
b1001001111101001 0
0,
b0 .
0/
1,
b1 .
1/
0,
b10 .
0/
b11 .
1/
b100 .
0/
b101 .
1,
b110 .
1/
b111 .
b1000 .
0/
b1001 .
b1010 .
1/
0,
b1011 .
b1100 .
0/
1,
b1101 .
1/
0,
b1110 .
0/
b1111 .
1,
b10000 .
b10110011001010 $
#39100
1-
1&
#40000
b101000 (
b1110110010101101 !
b1101110011101011 "
b1101110011101011 *
b1110110010101101 )
b1100100110011000 1
b1101110011101011 0
0,
b0 .
1,
b1 .
b10 .
b11 .
1/
b100 .
0,
b101 .
0/
1,
b110 .
b111 .
1/
b1000 .
0,
b1001 .
0/
b1010 .
1,
b1011 .
1/
b1100 .
0/
b1101 .
b1110 .
1/
b1111 .
b10000 .
b1100100110011000 $
#40100
0-
0&
#41000
b101001 (
b1011010011010001 !
b101111111111000 "
b101111111111000 *
b1011010011010001 )
b1010011001001 1
b101111111111000 0
0,
b0 .
b1 .
0/
b10 .
b11 .
1/
b100 .
0/
1,
b101 .
b110 .
1/
b111 .
b1000 .
0/
b1001 .
b1010 .
1/
b1011 .
0/
b1100 .
1/
b1101 .
0/
b1110 .
b1111 .
b10000 .
03
b1010011001001 $
#41100
04
#42000
b101010 (
b100101100111011 !
b1010111010001000 "
1#
1+
b1010111010001000 *
b100101100111011 )
b1001110010110011 1
b101000101111000 0
0,
b0 .
1/
b1 .
b10 .
0/
b11 .
1,
b100 .
1/
b101 .
b110 .
0/
b111 .
1/
0,
b1000 .
0/
1,
b1001 .
b1010 .
1/
0,
b1011 .
b1100 .
b1101 .
0/
b1110 .
1,
b1111 .
1/
0,
b10000 .
02
13
0%
b1001110010110011 $
#42100
14
1-
1&
#43000
b101011 (
b1000010101101110 !
b111110000001001 "
b111110000001001 *
b1000010101101110 )
b100101100101 1
b1000001111110111 0
b0 .
b1 .
0/
1,
b10 .
1/
b11 .
0/
b100 .
b101 .
1/
b110 .
b111 .
0/
b1000 .
1/
b1001 .
0/
b1010 .
b1011 .
1/
0,
b1100 .
0/
b1101 .
b1110 .
b1111 .
1,
b10000 .
12
03
1%
b100101100101 $
#44000
b101100 (
b111101000101001 !
b100010111000 "
b100010111000 *
b111101000101001 )
b111000101110001 1
b1111011101001000 0
0,
b0 .
1/
b1 .
0/
b10 .
b11 .
1,
b100 .
1/
0,
b101 .
b110 .
b111 .
0/
b1000 .
1/
b1001 .
0/
1,
b1010 .
b1011 .
b1100 .
1/
b1101 .
b1110 .
b1111 .
0/
b10000 .
02
b111000101110001 $
#44100
04
0-
0&
#45000
b101101 (
b110110101000000 !
b110101010110111 "
0#
0+
b110101010110111 *
b110110101000000 )
b1101011111110111 1
b110101010110111 0
0,
b0 .
1/
b1 .
b10 .
b11 .
0/
b100 .
1/
b101 .
b110 .
b111 .
b1000 .
b1001 .
b1010 .
b1011 .
0/
1,
b1100 .
1/
0,
b1101 .
0/
1,
b1110 .
1/
b1111 .
0,
b10000 .
0%
b1101011111110111 $
#45100
14
1-
1&
#46000
b101110 (
b100100011110011 !
b101100101101011 "
b101100101101011 *
b100100011110011 )
b1010001001011110 1
b101100101101011 0
b0 .
0/
1,
b1 .
1/
b10 .
0,
b11 .
b100 .
b101 .
0/
1,
b110 .
1/
b111 .
0/
b1000 .
b1001 .
1/
0,
b1010 .
0/
b1011 .
1,
b1100 .
b1101 .
1/
0,
b1110 .
0/
1,
b1111 .
1/
0,
b10000 .
b1010001001011110 $
#47000
b101111 (
b1101010111101010 !
b1011001000110010 "
b1011001000110010 *
b1101010111101010 )
b1000100000011100 1
b1011001000110010 0
b0 .
0/
b1 .
1,
b10 .
1/
0,
b11 .
b100 .
b101 .
0/
1,
b110 .
b111 .
b1000 .
b1001 .
b1010 .
b1011 .
1/
0,
b1100 .
0/
1,
b1101 .
b1110 .
b1111 .
1/
b10000 .
12
13
1%
b1000100000011100 $
#47100
0-
0&
#48000
b110000 (
b101000101010000 !
b1011010001101101 "
b1011010001101101 *
b101000101010000 )
b10110111101 1
b1011010001101101 0
0,
b0 .
b1 .
0/
b10 .
1/
b11 .
b100 .
b101 .
b110 .
0/
1,
b111 .
1/
0,
b1000 .
b1001 .
0/
b1010 .
1/
b1011 .
0/
b1100 .
1,
b1101 .
b1110 .
b1111 .
b10000 .
02
b10110111101 $
#48100
04
#49000
b110001 (
b1100110001111110 !
b110011011100110 "
b110011011100110 *
b1100110001111110 )
b11001101100100 1
b110011011100110 0
0,
b0 .
b1 .
1,
b10 .
1/
b11 .
0/
b100 .
b101 .
1/
b110 .
b111 .
0/
b1000 .
1/
0,
b1001 .
b1010 .
0/
1,
b1011 .
b1100 .
1/
0,
b1101 .
b1110 .
0/
1,
b1111 .
b10000 .
12
03
b11001101100100 $
#50000
b110010 (
b11110111111010 !
b11100000011 "
b11100000011 *
b11110111111010 )
b100010011111101 1
b11100000011 0
0,
b0 .
1/
b1 .
0/
1,
b10 .
1/
0,
b11 .
b100 .
b101 .
b110 .
b111 .
b1000 .
0/
1,
b1001 .
b1010 .
1/
b1011 .
0/
b1100 .
b1101 .
b1110 .
1/
0,
b1111 .
0/
b10000 .
02
0%
b100010011111101 $
#50100
14
#51000
b110011 (
b1101000001011001 !
b11011001111010 "
b11011001111010 *
b1101000001011001 )
b11011010011 1
b11011001111010 0
b0 .
1/
b1 .
b10 .
0/
b11 .
1,
b100 .
1/
b101 .
0/
b110 .
1/
b111 .
0,
b1000 .
0/
b1001 .
1/
b1010 .
b1011 .
0/
b1100 .
1,
b1101 .
b1110 .
b1111 .
b10000 .
12
1%
b11011010011 $
#51100
04
#52000
b110100 (
b1010011100100111 !
b1110110111111101 "
1#
1+
b1110110111111101 *
b1010011100100111 )
b1011100100101010 1
b1001000000011 0
0,
b0 .
1,
b1 .
1/
b10 .
0/
b11 .
1/
0,
b100 .
0/
b101 .
1/
b110 .
0/
b111 .
b1000 .
1/
b1001 .
0/
1,
b1010 .
b1011 .
1/
0,
b1100 .
b1101 .
b1110 .
0/
b1111 .
1/
b10000 .
13
0%
b1011100100101010 $
#53000
b110101 (
b110011010011010 !
b101000000110101 "
b101000000110101 *
b110011010011010 )
b1011001100101 1
b1010111111001011 0
b0 .
b1 .
0/
1,
b10 .
1/
0,
b11 .
0/
1,
b100 .
b101 .
1/
0,
b110 .
b111 .
0/
1,
b1000 .
b1001 .
1/
b1010 .
b1011 .
0/
b1100 .
1/
0,
b1101 .
0/
1,
b1110 .
b1111 .
b10000 .
02
03
1%
b1011001100101 $
#54000
b110110 (
b1000000011000011 !
b1111101100101001 "
0#
0+
b1111101100101001 *
b1000000011000011 )
b111101111101100 1
b1111101100101001 0
0,
b0 .
1,
b1 .
b10 .
1/
0,
b11 .
b100 .
0/
b101 .
1/
b110 .
b111 .
b1000 .
b1001 .
b1010 .
0/
b1011 .
1/
b1100 .
b1101 .
b1110 .
b1111 .
0/
1,
b10000 .
12
13
b111101111101100 $
#54100
14
1-
1&
#55000
b110111 (
b10000111001110 !
b1000001000001111 "
1#
1+
b1000001000001111 *
b10000111001110 )
b1001111110111111 1
b111110111110001 0
0,
b0 .
1/
b1 .
b10 .
b11 .
b100 .
b101 .
b110 .
0/
1,
b111 .
1/
b1000 .
b1001 .
0,
b1010 .
b1011 .
b1100 .
b1101 .
0/
1,
b1110 .
b1111 .
1/
0,
b10000 .
02
0%
b1001111110111111 $
#56000
b111000 (
b11010101000000 !
b100110010000011 "
b100110010000011 *
b11010101000000 )
b1110100010111101 1
b1011001101111101 0
b0 .
b1 .
0/
b10 .
1/
b11 .
b100 .
b101 .
b110 .
0/
1,
b111 .
1/
0,
b1000 .
0/
1,
b1001 .
b1010 .
b1011 .
1/
0,
b1100 .
0/
1,
b1101 .
1/
b1110 .
0,
b1111 .
b10000 .
03
b1110100010111101 $
#56100
04
0-
0&
#57000
b111001 (
b1101000011111111 !
b1111110111010100 "
0#
0+
b1111110111010100 *
b1101000011111111 )
b1100111011010011 1
b1111110111010100 0
b0 .
b1 .
b10 .
0/
1,
b11 .
b100 .
1/
b101 .
0/
b110 .
1/
b111 .
b1000 .
0/
b1001 .
1/
0,
b1010 .
b1011 .
b1100 .
0/
1,
b1101 .
b1110 .
1/
b1111 .
b10000 .
12
13
1%
b1100111011010011 $
#57100
14
#58000
b111010 (
b10000000000110 !
b1010001110111110 "
b1010001110111110 *
b10000000000110 )
b1100001111000100 1
b1010001110111110 0
0,
b0 .
0/
b1 .
1,
b10 .
1/
b11 .
0/
b100 .
b101 .
b110 .
1/
0,
b111 .
b1000 .
b1001 .
b1010 .
0/
b1011 .
b1100 .
b1101 .
1,
b1110 .
1/
0,
b1111 .
b10000 .
02
0%
b1100001111000100 $
#58100
04
