npl_cpu/instruction_set_model.v
/* ==========================
 *   Model of RISC without pipeline.
 *   risc.v
 *
 *  Useful for instruction set simulation.
 *  Three main tasks - fetch, execute, write.
 */
module instruction_set_model ;
/* 
 * Declarations, functions , and tasks
 */
// Declare parameters
parameter  CYCLE=10 ;               // Cycle Time
parameter  WIDTH=32 ;   // Width of data paths
parameter  ADDRSIZE = 12 ;  // Size of address field
parameter  MEMSIZE = (1<<ADDRSIZE); // Size of memory
parameter  MAXREGS = 16 ;  // Maximum # of registers
parameter  SBITS = 5 ;                // Status register bits
// Declare Registers and Memory

reg [WIDTH-1:0] MEM[0:MEMSIZE-1],    //  MEMORY
         RFILE[0:MAXREGS-1],   // Register File
    ir,                                      // Instruction Register
    src1, src2 ;                       // Alu operation registers
reg[WIDTH:0]  result ;     // ALU result register
reg[SBITS-1:0]  psr;          // Processor Status Register
reg[ADDRSIZE-1:0] pc ;    // Program counter
reg               dir;                   // rotate direction
reg               reset;               // System Reset
integer           i;                    // useful for interactive debugging

// General definitions

`define TRUE 1
`define FALSE 0 

`define DEBUG_ON  debug = 1
`define DEBUG_OFF debug = 0

// Define Instruction fields

`define OPCODE ir[31:28]
`define SRC  ir[23:12]
`define DST   ir[11:0]
`define SRCTYPE ir[27] // source type, 0=reg (mem for LD), 1=imm
`define DSTTYPE ir[26] // destination type, 0=reg, 1=imm
`define CCODE   ir[27:24]
`define SRCNT   ir[23:12] // Shift/rotate count -= left, +=right

// Operand Types

`define REGTYPE 0
`define IMMTYPE 1
 // Define opcodes for each instruction

`define NOP      4'b0000
`define BRA      4'b0001
`define LD       4'b0010
`define STR      4'b0011
`define ADD      4'b0100
`define MUL      4'b0101
`define CMP      4'b0110
`define SHF      4'b0111
`define ROT      4'b1000
`define HLT      4'b1001

// Define Condition Code fields
`define CARRY  psr[0]
`define EVEN   psr[1]
`define PARITY psr[2]
`define ZERO   psr[3]
`define NEG    psr[4]

// Define Condition Codes
`define CCC 1   // Result has carry
`define CCE 2   // Result is even
`define CCP 3   // Result is odd parity
`define CCZ 4   // Result is Zero
`define CCN 5   // Result is Negative
`define CCA 0   // Always

`define RIGHT  0 // Rotate/Shift Right
`define LEFT   1 // Rotate/Shift Left

// Function for ALU operands and result

function [WIDTH-1:0] getsrc;
input [WIDTH-1:0] in;
begin
   if (`SRCTYPE == `REGTYPE) getsrc = RFILE[`SRC] ;
   else getsrc = `SRC ;   // immediate type
end
endfunction

function [WIDTH-1:0] getdst;
input [WIDTH-1:0] in;
begin
   if (`DSTTYPE == `REGTYPE) begin
      getdst = RFILE[`DST];
  end
  else begin // immediate type
    $display("Error:Immediate data can't be destination. ");
   end
end
endfunction

// Functions / tasks for Condition Codes

function checkcond; //Returns 1 if condition code is set .
input [4:0] ccode;
begin
   case (ccode)
     `CCC : checkcond =  `CARRY ;
     `CCE : checkcond =  `EVEN ;
     `CCP : checkcond =  `PARITY ;
     `CCZ : checkcond =  `ZERO ;
     `CCN : chedkcond =  `NEG ;
     `CCA : checkcond =  1; 
endcase
end
endfunction
task clearcondcode ; // Reset condition codes in PSR
begin
   psr = 0;
end
endtask

task setcondcode ; // Compute the condition codes and set PSR
input [WIDTH:0] res; //33 bit result register
begin
   `CARRY  = res[WIDTH];
   `EVEN   = ~res[0];
   `PARITY =  ^res ;
   `ZERO   = ~(|res) ;
   `NEG    = res[WIDTH-1];
end
endtask

// Main Tasks - fetch, execute, write_result
task fetch ;   // Fetch the instruction and increment PC.
begin
  ir = MEM[pc] ;
  pc = pc + 1 ;
end 
endtask
task execute ; // Decode and execute the instruction.
begin
case(`OPCODE)
  `NOP : ;
  `BRA : if (checkcond( `CCODE)  == 1) pc = `DST;
  `LD :  begin  
             clearcondcode ;
           if (`SRCTYPE) RFILE[`DST] = `SRC ;
        else RFILE[`DST]=MEM[`SRC] ;
            setcondcode({1'bo,RFILE[`DST]}) ;
               end
  `STR : begin
             clearcondcode    
              if (`SRCTYPE) MEM[`DST] = `SRC;
              else MEM[`DST] = RFILE[`SRC] ;
                 if (`SRCTYPE) setcondcode({21'b0,`SRC})
                   else setcondcode ({1'b0,RFILE[`SRC]});
               end
  `ADD :  begin
                  clearcondcode ;
                  src1 = getsrc(ir);
                  src2 = getdst(ir);
                  result = src1 + src2;
                  setcondcode(result);
              end

    
   

    `MUL : begin
                   clearcondcode ;
                   src1 = getsrc(ir) ;
                   src2 = getdst(ir) ;
                   result = src1 * src2 ;
                   setcondcode(result) ;
                end
    `CMP : begin
                   clearcondcode ;
                   src1 = getsrc(ir) ;
                   result = ~src1 ;
                   setcondcode (result) ;
               end
    `SHF : begin
                   clearcondcode ;
                   src1 = getsrc(ir) ;
                   src2 = getdst(ir) ;
                   i = src1[ADDRSIZE-1:0] ;
                   result = (i>=0) ? (src2 >> i) : (src2 << -i) ;
                   setcondcode(result);
               end
    
 `ROT : begin
               clearcondcode ;
               src1 = getsrc(ir) ;
               src2 = getdst(ir) ;
               dir = (src1[ADDRSIZE-1] >=0 ? `RIGHT : `LEFT ;
               i = ( src1[ADDRSIZE-1] >=0)? src1 : -src1[ADDRSIZE-1:0] ;
             while (i > 0) begin
      if (dir == `RIGHT) begin
        result = src2 >> 1 ;
        result[WIDTH-1] = src2 [0] ;
     end
     else begin
        result = src2 << 1 ;
        result[0] =src2[WIDTH-1] ;
       end
       i= i - 1 ;
       src2 = result ;
             end //end of while
             setcondcode(result);
           end
   `HLT : begin
                $display("Halt ... ");
                $stop ;
              end
   default : $display ("Error : Illegal Opcode . " );
endcase
end
endtask

     
// Write the result in register file or memory.

task write_result ;
begin
   if ((`OPCODE >= `ADD) && (`OPCODE < `HLT)) begin
      if(`DSTTYPE == `REGTYPE) RFILE[`DST] = result ; 
      else MEM[`DST] = result ;
   end
end
endtask 

// Debugging help

task apply_reset ;
begin
   reset = 1;
   #CYCLE
   reset = 0;
   pc = 0;
end
endtask


task disprm ;
input rm ;
input [ADDRSIZE-1:0] adr1, adr2 ;
begin
   if (rm == `REGTYPE) begin
       while (adr2 >= adr1)
         begin
               $display("REGFILE[%d] = %d\n ",adr1,RFILE[adr1]);
               adr1 = adr1 +1;
         end
   end

   else begin
         while (adr2 >= adr1) begin  
              $display("MEM[%d]=%d\n ",adr1,MEM[adr1]);
              adr1= adr1 + 1;
         end
   end
end
endtask

// Initial and always blocks

initial begin : prog_load
     $readmemb("sisc.prog ",MEM);
     $monitor("%d %d %h %h %h ",
     $time,pc,RFILE[0], RFILE[1]; RFILE[2]) ;
     apply_reset ;
end

always begin : main_process
    if (!reset) begin
       #CYCLE fetch ;
       #CYCLE execute ;
       #CYCLE write_result ;
    end
    else #CYCLE ;
 end
 endmodule

npl_cpu/d.vcd
$date
	Thu Nov 21 01:18:58 2019
$end
$version
	Icarus Verilog
$end
$timescale
	1s
$end
$scope module instruction_set_model $end
$var reg 1 ! dir $end
$var reg 32 " ir [31:0] $end
$var reg 12 # pc [11:0] $end
$var reg 5 $ psr [4:0] $end
$var reg 1 % reset $end
$var reg 33 & result [32:0] $end
$var reg 32 ' src1 [31:0] $end
$var reg 32 ( src2 [31:0] $end
$var integer 32 ) i [31:0] $end
$scope function checkcond $end
$var reg 5 * ccode [4:0] $end
$var reg 1 + checkcond $end
$upscope $end
$scope function getdst $end
$var reg 32 , getdst [31:0] $end
$var reg 32 - in [31:0] $end
$upscope $end
$scope function getsrc $end
$var reg 32 . getsrc [31:0] $end
$var reg 32 / in [31:0] $end
$upscope $end
$scope begin main_process $end
$upscope $end
$scope begin prog_load $end
$upscope $end
$scope task apply_reset $end
$upscope $end
$scope task clearcondcode $end
$upscope $end
$scope task disprm $end
$var reg 12 0 adr1 [11:0] $end
$var reg 12 1 adr2 [11:0] $end
$var reg 1 2 rm $end
$upscope $end
$scope task execute $end
$upscope $end
$scope task fetch $end
$upscope $end
$scope task setcondcode $end
$var reg 33 3 res [32:0] $end
$upscope $end
$scope task write_result $end
$upscope $end
$upscope $end
$enddefinitions $end
#0
$dumpvars
bx 3
x2
bx 1
bx 0
bx /
bx .
bx -
bx ,
x+
bx *
bx )
bx (
bx '
bx &
1%
bx $
bx #
bx "
x!
$end
#10
b0 #
0%
#20
b1 #
b0 "
#50
b10 #
b101000000000010100000000000000 "
#60
b10100 3
b10 $
#80
b11 #
b100000000000000001000000000001 "
#90
b101000000000010100000000000000 3
b10 $
#110
b100 #
b110000000000000001000000010100 "
#120
b10 $
#140
b101 #
b1000000000000000000000000000001 "
#150
b101000000000010100000000010100 3
b101000000000010100000000010100 &
b101000000000010100000000000000 (
b101000000000010100000000000000 ,
b1000000000000000000000000000001 -
b10100 '
b10100 .
b1000000000000000000000000000001 /
b10 $
#170
b110 #
b1001000000000110010000000000001 "
#180
b101000000000010100000001000110 3
b101000000000010100000001000110 &
b101000000000010100000000010100 (
b101000000000010100000000010100 ,
b1001000000000110010000000000001 -
b110010 '
b110010 .
b1001000000000110010000000000001 /
b110 $
#200
b111 #
b1011000000000110010000000000001 "
#210
b111010000001111101000110110101100 3
b111010000001111101000110110101100 &
b101000000000010100000001000110 (
b101000000000010100000001000110 ,
b1011000000000110010000000000001 -
b1011000000000110010000000000001 /
b10111 $
#230
b1000 #
b1100000000000000011000000000001 "
#240
b1xxxxxxxxxxxxxxxxxxxxxxxxxxxxxxxx 3
b1xxxxxxxxxxxxxxxxxxxxxxxxxxxxxxxx &
bx '
bx .
b1100000000000000011000000000001 /
bx0xx1 $
#260
b1001 #
b1110000000000000100000000000001 "
#270
bx 3
bx &
b0xxxxxxxxxxxx )
bx (
bx ,
b1110000000000000100000000000001 -
b1110000000000000100000000000001 /
bx $
#290
b1010 #
b10000000000000000100000000000001 "
#300
bx )
b10000000000000000100000000000001 -
b10000000000000000100000000000001 /
bx $
#320
b1011 #
b10010000000000000000000000000000 "
