fulladder/fulladder.v
module fulladder (input a,b,c_in,output sum,c_out);
wire s1,c1,c2;
xor(s1,a,b);
xor(sum,s1,c_in);
and(c1,a,b);
and(c2,s1,c_in);
xor(c_out,c1,c2);
endmodule

adder/fulladder/Ntest_bench.v
`include "fulladder.v"
`timescale 1 ns / 1 ps
module test_bench;
reg a;
reg b;
reg c;
wire s;
wire co;
fulladder FA (a,b,c,s,co);
initial
begin
$display("=========This is a test bench of FULL ADDER=========");
$monitor($time," || a= %b | b= %b | c= %b | s= %b | os= %b",a,b,c,s,co);
a=1'b0;
b=1'b0;
c=1'b0;
#5 a=1'b0;
b=1'b0;
c=1'b1;
  #5 a=1'b0;
b=1'b1;
c=1'b0;
  #5 a=1'b1;
b=1'b0;
c=1'b0;
  #5 a=1'b0;
b=1'b1;
c=1'b1;
  #5 a=1'b1;
b=1'b1;
c=1'b0;
  #5 a=1'b1;
b=1'b0;
c=1'b1;
  #5 a=1'b1;
b=1'b1;
c=1'b1;
#5 $finish;
end
//====================chart========================
//for all abc -> output S/C
//000->0/0
//001->1/0
//011->0/1
//111->1/1
//a|b|c/S-c
//000/0-0
//001/1-0
//010/1-0
//100/1-0
//011/0-1
//110/0-1
//101/0-1
//111/1-1
//============all we need to test==================
//always #50 begin
//if
//initial
//begin
//$dumpfile("fulladder.vcd");
//$dumpvars;
//end
endmodule

adder/fulladder/fulladder.vcd
$date
	Sat Oct 26 00:31:33 2019
$end
$version
	Icarus Verilog
$end
$timescale
	1ps
$end
$scope module test_bench $end
$var wire 1 ! s $end
$var wire 1 " co $end
$var reg 1 # a $end
$var reg 1 $ b $end
$var reg 1 % c $end
$scope module FA $end
$var wire 1 # a $end
$var wire 1 $ b $end
$var wire 1 & c1 $end
$var wire 1 ' c2 $end
$var wire 1 % c_in $end
$var wire 1 " c_out $end
$var wire 1 ( s1 $end
$var wire 1 ! sum $end
$upscope $end
$upscope $end
$enddefinitions $end
#0
$dumpvars
0(
0'
0&
0%
0$
0#
0"
0!
$end
#5000
1!
1%
#10000
1(
0%
1$
#15000
0$
1#
#20000
1"
0!
1'
1%
1$
0#
#25000
0'
0(
1&
0%
1#
#30000
1'
1(
0&
1%
0$
#35000
1!
0'
1"
0(
1&
1$
