before_mounth10/hw1and2/adder/addsub4/fulladder.v
module fulladder (input a, b, c_in, output sum, c_out);
wire s1, c1, c2;

xor g1(s1, a, b);
xor g2(sum, s1, c_in);
and g3(c1, a,b);
and g4(c2, s1, c_in) ;
xor g5(c_out, c2, c1) ;

endmodule

adder/fourBitAdder/fourBitAdder.v
`timescale 1 ns /1 ps
`include "fulladder.v"
module fourBitAdder(
	c_in,a,b,//in
	sum,c_out//out
);
//=============================================
//NOTAM:
//do not write:
//
//module fourBitAdder(
//	input c_in,a,b,
//	output sum,c_out
//);
//
//input [3:0] a,b;
//...~
//
//==> repeat announcement :: u can't do "input" on smae varib. two times
//<!will cause error>
//
//(2019.10.7)
//
//============================================= 
input [3:0] a,b;
input c_in;
output [3:0] sum;
output c_out;
wire f0Cout,f1Cout,f2Cout;
fulladder f0 (
.a(a[0]),
.b(b[0]),
.c_in(c_in),
.sum(sum[0]),
.c_out(f0Cout)
);
	fulladder f1 (
.a(a[1]),
.b(b[1]),
.c_in(f0Cout),
.sum(sum[1]),
.c_out(f1Cout)
);
	fulladder f2 (
.a(a[2]),
.b(b[2]),
.c_in(f1Cout),
.sum(sum[2]),
.c_out(f2Cout)
);
	fulladder f3 (
.a(a[3]),
.b(b[3]),
.c_in(f2Cout),
.sum(sum[3]),
.c_out(C_out)
);

endmodule

adder/fourBitAdder/test_bench_4bit.v
`include "fourBitAdder.v"
`timescale 1 ns / 1 ps
module test_bench_4bit;
reg [3:0] a,b;//in
reg c_in;//in
wire [3:0] sum;//out
wire c_out;//out
fourBitAdder ad4 (c_in,a,b,sum,c_out);
initial
begin : first_init
$display("=========This is a test bench of 4 bit ADDER=========");
$monitor($time," || a= %d | b= %d | c= %b | s= %d | OC= %b | (ERR:%d)",a,b,c_in,sum,c_out,error_code);
a=4'd0;
b=4'd0;
c_in=1'b0;
end// : first_init
integer error_code=1;

initial
begin : main_test
		integer i;
	for (i=0;i<16;i=i+1)
	begin : for_loop_for_a_big
	integer k;
	for (k=0;k<16;k=k+1)
	begin : F_loop_b_small

	#5 b=b+4'd1;
	if ((sum+c_out*16)==(i+k))
	error_code=error_code*1;
	else
	error_code=error_code*0;

	end// : F_loop_b_small
	
	a=a+4'd1;

	end// : for_loop_for_a_big
#5 if(error_code==0)
$display("ERROR!");
else
$display("OK!");
#5 $finish;
end// : main_test

//=================================================
//NOTAM:
//if u name a begin-end block with ":" mark behind "begin"
//do not put the same stuff behind "end" -> will cuz ERROR
//=================================================

initial
begin : out_wave
$dumpfile("fourBitAdder.vcd");
$dumpvars;
end// : out_wave
endmodule

before_mounth10/hw1and2/adder/fourBitAdder/fourBitAdder.vcd
$date
    Oct  7, 2019  23:07:09
$end
$version
    TOOL:	ncsim	15.20-s039
$end
$timescale
    1 ps
$end

$scope module test_bench_4bit $end
$var reg       4 !    a [3:0] $end
$var reg       4 "    b [3:0] $end
$var reg       1 #    c_in  $end
$var wire      1 $    sum [3] $end
$var wire      1 %    sum [2] $end
$var wire      1 &    sum [1] $end
$var wire      1 '    sum [0] $end
$var wire      1 (    c_out  $end
$var integer  32 )    error_code  $end

$scope module ad4 $end
$var wire      1 *    a [3] $end
$var wire      1 +    a [2] $end
$var wire      1 ,    a [1] $end
$var wire      1 -    a [0] $end
$var wire      1 .    b [3] $end
$var wire      1 /    b [2] $end
$var wire      1 0    b [1] $end
$var wire      1 1    b [0] $end
$var wire      1 2    c_in  $end
$var wire      1 $    sum [3] $end
$var wire      1 %    sum [2] $end
$var wire      1 &    sum [1] $end
$var wire      1 '    sum [0] $end
$var wire      1 (    c_out  $end
$var wire      1 3    f0Cout  $end
$var wire      1 4    f1Cout  $end
$var wire      1 5    f2Cout  $end

$scope module f0 $end
$var wire      1 -    a  $end
$var wire      1 1    b  $end
$var wire      1 2    c_in  $end
$var wire      1 '    sum  $end
$var wire      1 3    c_out  $end
$var wire      1 6    s1  $end
$var wire      1 7    c1  $end
$var wire      1 8    c2  $end
$upscope $end


$scope module f1 $end
$var wire      1 ,    a  $end
$var wire      1 0    b  $end
$var wire      1 3    c_in  $end
$var wire      1 &    sum  $end
$var wire      1 4    c_out  $end
$var wire      1 9    s1  $end
$var wire      1 :    c1  $end
$var wire      1 ;    c2  $end
$upscope $end


$scope module f2 $end
$var wire      1 +    a  $end
$var wire      1 /    b  $end
$var wire      1 4    c_in  $end
$var wire      1 %    sum  $end
$var wire      1 5    c_out  $end
$var wire      1 <    s1  $end
$var wire      1 =    c1  $end
$var wire      1 >    c2  $end
$upscope $end


$scope module f3 $end
$var wire      1 *    a  $end
$var wire      1 .    b  $end
$var wire      1 5    c_in  $end
$var wire      1 $    sum  $end
$var wire      1 (    c_out  $end
$var wire      1 ?    s1  $end
$var wire      1 @    c1  $end
$var wire      1 A    c2  $end
$upscope $end

$upscope $end


$scope begin main_test $end
$var integer  32 B    i  $end

$scope begin for_loop_for_a_big $end
$var integer  32 C    k  $end
$upscope $end

$upscope $end

$upscope $end

$enddefinitions $end
$dumpvars
b0 !
b0 "
0#
0$
0%
0&
0'
0(
b1 )
0*
0+
0,
0-
0.
0/
00
01
02
03
04
05
06
07
08
09
0:
0;
0<
0=
0>
0?
0@
0A
b0 B
b0 C
$end
#5000
b1 "
b1 C
11
16
1'
#10000
b10 "
b10 C
10
01
06
19
1&
0'
#15000
b11 "
b11 C
11
16
1'
#20000
b100 "
b100 C
1/
00
01
06
09
1<
1%
0&
0'
#25000
b101 "
b101 C
11
16
1'
#30000
b110 "
b110 C
10
01
06
19
1&
0'
#35000
b111 "
b111 C
11
16
1'
#40000
b1000 "
b1000 C
1.
0/
00
01
06
09
0<
1?
1$
0%
0&
0'
#45000
b1001 "
b1001 C
11
16
1'
#50000
b1010 "
b1010 C
10
01
06
19
1&
0'
#55000
b1011 "
b1011 C
11
16
1'
#60000
b1100 "
b1100 C
1/
00
01
06
09
1<
1%
0&
0'
#65000
b1101 "
b1101 C
11
16
1'
#70000
b1110 "
b1110 C
10
01
06
19
1&
0'
#75000
b1111 "
b1111 C
11
16
1'
#80000
b0 "
b10000 C
b1 !
b1 B
b0 C
1-
0.
0/
00
01
09
0<
0?
0$
0%
0&
#85000
b1 "
b1 C
11
06
17
13
1&
0'
#90000
b10 "
b10 C
10
01
16
07
03
19
1'
#95000
b11 "
b11 C
11
06
17
13
0&
1;
14
0'
1%
#100000
b100 "
b100 C
1/
00
01
16
07
03
09
0;
04
1<
1'
#105000
b101 "
b101 C
11
06
17
13
1&
0'
#110000
b110 "
b110 C
10
01
16
07
03
19
1'
#115000
b111 "
b111 C
11
06
17
13
0&
1;
14
0'
0%
1>
15
1$
#120000
b1000 "
b1000 C
1.
0/
00
01
16
07
03
09
0;
04
0<
0>
05
1?
1'
#125000
b1001 "
b1001 C
11
06
17
13
1&
0'
#130000
b1010 "
b1010 C
10
01
16
07
03
19
1'
#135000
b1011 "
b1011 C
11
06
17
13
0&
1;
14
0'
1%
#140000
b1100 "
b1100 C
1/
00
01
16
07
03
09
0;
04
1<
1'
#145000
b1101 "
b1101 C
11
06
17
13
1&
0'
#150000
b1110 "
b1110 C
10
01
16
07
03
19
1'
#155000
b1111 "
b1111 C
11
06
17
13
0&
1;
14
0'
0%
1>
15
0$
1A
1(
#160000
b0 "
b10000 C
b10 !
b10 B
b0 C
1,
0-
0.
0/
00
01
0<
0>
05
0?
0A
0(
07
03
0;
04
1&
#165000
b1 "
b1 C
11
16
1'
#170000
b10 "
b10 C
10
01
06
09
1:
14
1%
0&
0'
#175000
b11 "
b11 C
11
16
1'
#180000
b100 "
b100 C
1/
00
01
06
19
0:
04
1<
1&
0'
#185000
b101 "
b101 C
11
16
1'
#190000
b110 "
b110 C
10
01
06
09
1:
14
0%
1>
15
0&
0'
1$
#195000
b111 "
b111 C
11
16
1'
#200000
b1000 "
b1000 C
1.
0/
00
01
06
19
0:
04
0<
0>
05
1?
1&
0'
#205000
b1001 "
b1001 C
11
16
1'
#210000
b1010 "
b1010 C
10
01
06
09
1:
14
1%
0&
0'
#215000
b1011 "
b1011 C
11
16
1'
#220000
b1100 "
b1100 C
1/
00
01
06
19
0:
04
1<
1&
0'
#225000
b1101 "
b1101 C
11
16
1'
#230000
b1110 "
b1110 C
10
01
06
09
1:
14
0%
1>
15
0&
0'
0$
1A
1(
#235000
b1111 "
b1111 C
11
16
1'
#240000
b0 "
b10000 C
b11 !
b11 B
b0 C
1-
0.
0/
00
01
19
0:
04
0<
0>
05
0?
0A
0(
1&
#245000
b1 "
b1 C
11
06
17
13
0&
1;
14
0'
1%
#250000
b10 "
b10 C
10
01
16
07
03
09
0;
1:
1'
#255000
b11 "
b11 C
11
06
17
13
1&
0'
#260000
b100 "
b100 C
1/
00
01
16
07
03
19
0:
04
1<
1'
#265000
b101 "
b101 C
11
06
17
13
0&
1;
14
0'
0%
1>
15
1$
#270000
b110 "
b110 C
10
01
16
07
03
09
0;
1:
1'
#275000
b111 "
b111 C
11
06
17
13
1&
0'
#280000
b1000 "
b1000 C
1.
0/
00
01
16
07
03
19
0:
04
0<
0>
05
1?
1'
#285000
b1001 "
b1001 C
11
06
17
13
0&
1;
14
0'
1%
#290000
b1010 "
b1010 C
10
01
16
07
03
09
0;
1:
1'
#295000
b1011 "
b1011 C
11
06
17
13
1&
0'
#300000
b1100 "
b1100 C
1/
00
01
16
07
03
19
0:
04
1<
1'
#305000
b1101 "
b1101 C
11
06
17
13
0&
1;
14
0'
0%
1>
15
0$
1A
1(
#310000
b1110 "
b1110 C
10
01
16
07
03
09
0;
1:
1'
#315000
b1111 "
b1111 C
11
06
17
13
1&
0'
#320000
b0 "
b10000 C
b100 !
b100 B
b0 C
1+
0,
0-
0.
0/
00
01
0?
0A
0(
07
03
0:
04
0>
05
1%
0&
#325000
b1 "
b1 C
11
16
1'
#330000
b10 "
b10 C
10
01
06
19
1&
0'
#335000
b11 "
b11 C
11
16
1'
#340000
b100 "
b100 C
1/
00
01
06
09
0<
1=
15
1$
0%
0&
0'
#345000
b101 "
b101 C
11
16
1'
#350000
b110 "
b110 C
10
01
06
19
1&
0'
#355000
b111 "
b111 C
11
16
1'
#360000
b1000 "
b1000 C
1.
0/
00
01
06
09
1<
0=
05
1?
1%
0&
0'
#365000
b1001 "
b1001 C
11
16
1'
#370000
b1010 "
b1010 C
10
01
06
19
1&
0'
#375000
b1011 "
b1011 C
11
16
1'
#380000
b1100 "
b1100 C
1/
00
01
06
09
0<
1=
15
0$
1A
1(
0%
0&
0'
#385000
b1101 "
b1101 C
11
16
1'
#390000
b1110 "
b1110 C
10
01
06
19
1&
0'
#395000
b1111 "
b1111 C
11
16
1'
#400000
b0 "
b10000 C
b101 !
b101 B
b0 C
1-
0.
0/
00
01
09
1<
0=
05
0?
0A
0(
1%
0&
#405000
b1 "
b1 C
11
06
17
13
1&
0'
#410000
b10 "
b10 C
10
01
16
07
03
19
1'
#415000
b11 "
b11 C
11
06
17
13
0&
1;
14
0'
0%
1>
15
1$
#420000
b100 "
b100 C
1/
00
01
16
07
03
09
0;
04
0<
0>
1=
1'
#425000
b101 "
b101 C
11
06
17
13
1&
0'
#430000
b110 "
b110 C
10
01
16
07
03
19
1'
#435000
b111 "
b111 C
11
06
17
13
0&
1;
14
0'
1%
#440000
b1000 "
b1000 C
1.
0/
00
01
16
07
03
09
0;
04
1<
0=
05
1?
1'
#445000
b1001 "
b1001 C
11
06
17
13
1&
0'
#450000
b1010 "
b1010 C
10
01
16
07
03
19
1'
#455000
b1011 "
b1011 C
11
06
17
13
0&
1;
14
0'
0%
1>
15
0$
1A
1(
#460000
b1100 "
b1100 C
1/
00
01
16
07
03
09
0;
04
0<
0>
1=
1'
#465000
b1101 "
b1101 C
11
06
17
13
1&
0'
#470000
b1110 "
b1110 C
10
01
16
07
03
19
1'
#475000
b1111 "
b1111 C
11
06
17
13
0&
1;
14
0'
1%
#480000
b0 "
b10000 C
b110 !
b110 B
b0 C
1,
0-
0.
0/
00
01
1<
0>
0=
0?
0A
0(
07
03
0;
04
05
1&
#485000
b1 "
b1 C
11
16
1'
#490000
b10 "
b10 C
10
01
06
09
1:
14
0%
1>
15
0&
0'
1$
#495000
b11 "
b11 C
11
16
1'
#500000
b100 "
b100 C
1/
00
01
06
19
0:
04
0<
0>
1=
1&
0'
#505000
b101 "
b101 C
11
16
1'
#510000
b110 "
b110 C
10
01
06
09
1:
14
1%
0&
0'
#515000
b111 "
b111 C
11
16
1'
#520000
b1000 "
b1000 C
1.
0/
00
01
06
19
0:
04
1<
0=
05
1?
1&
0'
#525000
b1001 "
b1001 C
11
16
1'
#530000
b1010 "
b1010 C
10
01
06
09
1:
14
0%
1>
15
0&
0'
0$
1A
1(
#535000
b1011 "
b1011 C
11
16
1'
#540000
b1100 "
b1100 C
1/
00
01
06
19
0:
04
0<
0>
1=
1&
0'
#545000
b1101 "
b1101 C
11
16
1'
#550000
b1110 "
b1110 C
10
01
06
09
1:
14
1%
0&
0'
#555000
b1111 "
b1111 C
11
16
1'
#560000
b0 "
b10000 C
b111 !
b111 B
b0 C
1-
0.
0/
00
01
19
0:
04
1<
0=
05
0?
0A
0(
1&
#565000
b1 "
b1 C
11
06
17
13
0&
1;
14
0'
0%
1>
15
1$
#570000
b10 "
b10 C
10
01
16
07
03
09
0;
1:
1'
#575000
b11 "
b11 C
11
06
17
13
1&
0'
#580000
b100 "
b100 C
1/
00
01
16
07
03
19
0:
04
0<
0>
1=
1'
#585000
b101 "
b101 C
11
06
17
13
0&
1;
14
0'
1%
#590000
b110 "
b110 C
10
01
16
07
03
09
0;
1:
1'
#595000
b111 "
b111 C
11
06
17
13
1&
0'
#600000
b1000 "
b1000 C
1.
0/
00
01
16
07
03
19
0:
04
1<
0=
05
1?
1'
#605000
b1001 "
b1001 C
11
06
17
13
0&
1;
14
0'
0%
1>
15
0$
1A
1(
#610000
b1010 "
b1010 C
10
01
16
07
03
09
0;
1:
1'
#615000
b1011 "
b1011 C
11
06
17
13
1&
0'
#620000
b1100 "
b1100 C
1/
00
01
16
07
03
19
0:
04
0<
0>
1=
1'
#625000
b1101 "
b1101 C
11
06
17
13
0&
1;
14
0'
1%
#630000
b1110 "
b1110 C
10
01
16
07
03
09
0;
1:
1'
#635000
b1111 "
b1111 C
11
06
17
13
1&
0'
#640000
b0 "
b10000 C
b1000 !
b1000 B
b0 C
1*
0+
0,
0-
0.
0/
00
01
07
03
0:
04
0=
05
0A
0(
1$
0%
0&
#645000
b1 "
b1 C
11
16
1'
#650000
b10 "
b10 C
10
01
06
19
1&
0'
#655000
b11 "
b11 C
11
16
1'
#660000
b100 "
b100 C
1/
00
01
06
09
1<
1%
0&
0'
#665000
b101 "
b101 C
11
16
1'
#670000
b110 "
b110 C
10
01
06
19
1&
0'
#675000
b111 "
b111 C
11
16
1'
#680000
b1000 "
b1000 C
1.
0/
00
01
06
09
0<
0?
1@
1(
0$
0%
0&
0'
#685000
b1001 "
b1001 C
11
16
1'
#690000
b1010 "
b1010 C
10
01
06
19
1&
0'
#695000
b1011 "
b1011 C
11
16
1'
#700000
b1100 "
b1100 C
1/
00
01
06
09
1<
1%
0&
0'
#705000
b1101 "
b1101 C
11
16
1'
#710000
b1110 "
b1110 C
10
01
06
19
1&
0'
#715000
b1111 "
b1111 C
11
16
1'
#720000
b0 "
b10000 C
b1001 !
b1001 B
b0 C
1-
0.
0/
00
01
09
0<
1?
0@
0(
1$
0%
0&
#725000
b1 "
b1 C
11
06
17
13
1&
0'
#730000
b10 "
b10 C
10
01
16
07
03
19
1'
#735000
b11 "
b11 C
11
06
17
13
0&
1;
14
0'
1%
#740000
b100 "
b100 C
1/
00
01
16
07
03
09
0;
04
1<
1'
#745000
b101 "
b101 C
11
06
17
13
1&
0'
#750000
b110 "
b110 C
10
01
16
07
03
19
1'
#755000
b111 "
b111 C
11
06
17
13
0&
1;
14
0'
0%
1>
15
0$
1A
1(
#760000
b1000 "
b1000 C
1.
0/
00
01
16
07
03
09
0;
04
0<
0>
05
0?
0A
1@
1'
#765000
b1001 "
b1001 C
11
06
17
13
1&
0'
#770000
b1010 "
b1010 C
10
01
16
07
03
19
1'
#775000
b1011 "
b1011 C
11
06
17
13
0&
1;
14
0'
1%
#780000
b1100 "
b1100 C
1/
00
01
16
07
03
09
0;
04
1<
1'
#785000
b1101 "
b1101 C
11
06
17
13
1&
0'
#790000
b1110 "
b1110 C
10
01
16
07
03
19
1'
#795000
b1111 "
b1111 C
11
06
17
13
0&
1;
14
0'
0%
1>
15
1$
#800000
b0 "
b10000 C
b1010 !
b1010 B
b0 C
1,
0-
0.
0/
00
01
0<
0>
05
1?
0@
0(
07
03
0;
04
1&
#805000
b1 "
b1 C
11
16
1'
#810000
b10 "
b10 C
10
01
06
09
1:
14
1%
0&
0'
#815000
b11 "
b11 C
11
16
1'
#820000
b100 "
b100 C
1/
00
01
06
19
0:
04
1<
1&
0'
#825000
b101 "
b101 C
11
16
1'
#830000
b110 "
b110 C
10
01
06
09
1:
14
0%
1>
15
0&
0'
0$
1A
1(
#835000
b111 "
b111 C
11
16
1'
#840000
b1000 "
b1000 C
1.
0/
00
01
06
19
0:
04
0<
0>
05
0?
0A
1@
1&
0'
#845000
b1001 "
b1001 C
11
16
1'
#850000
b1010 "
b1010 C
10
01
06
09
1:
14
1%
0&
0'
#855000
b1011 "
b1011 C
11
16
1'
#860000
b1100 "
b1100 C
1/
00
01
06
19
0:
04
1<
1&
0'
#865000
b1101 "
b1101 C
11
16
1'
#870000
b1110 "
b1110 C
10
01
06
09
1:
14
0%
1>
15
0&
0'
1$
#875000
b1111 "
b1111 C
11
16
1'
#880000
b0 "
b10000 C
b1011 !
b1011 B
b0 C
1-
0.
0/
00
01
19
0:
04
0<
0>
05
1?
0@
0(
1&
#885000
b1 "
b1 C
11
06
17
13
0&
1;
14
0'
1%
#890000
b10 "
b10 C
10
01
16
07
03
09
0;
1:
1'
#895000
b11 "
b11 C
11
06
17
13
1&
0'
#900000
b100 "
b100 C
1/
00
01
16
07
03
19
0:
04
1<
1'
#905000
b101 "
b101 C
11
06
17
13
0&
1;
14
0'
0%
1>
15
0$
1A
1(
#910000
b110 "
b110 C
10
01
16
07
03
09
0;
1:
1'
#915000
b111 "
b111 C
11
06
17
13
1&
0'
#920000
b1000 "
b1000 C
1.
0/
00
01
16
07
03
19
0:
04
0<
0>
05
0?
0A
1@
1'
#925000
b1001 "
b1001 C
11
06
17
13
0&
1;
14
0'
1%
#930000
b1010 "
b1010 C
10
01
16
07
03
09
0;
1:
1'
#935000
b1011 "
b1011 C
11
06
17
13
1&
0'
#940000
b1100 "
b1100 C
1/
00
01
16
07
03
19
0:
04
1<
1'
#945000
b1101 "
b1101 C
11
06
17
13
0&
1;
14
0'
0%
1>
15
1$
#950000
b1110 "
b1110 C
10
01
16
07
03
09
0;
1:
1'
#955000
b1111 "
b1111 C
11
06
17
13
1&
0'
#960000
b0 "
b10000 C
b1100 !
b1100 B
b0 C
1+
0,
0-
0.
0/
00
01
1?
0A
0@
07
03
0:
04
0>
05
0(
1%
0&
#965000
b1 "
b1 C
11
16
1'
#970000
b10 "
b10 C
10
01
06
19
1&
0'
#975000
b11 "
b11 C
11
16
1'
#980000
b100 "
b100 C
1/
00
01
06
09
0<
1=
15
0$
1A
1(
0%
0&
0'
#985000
b101 "
b101 C
11
16
1'
#990000
b110 "
b110 C
10
01
06
19
1&
0'
#995000
b111 "
b111 C
11
16
1'
#1000000
b1000 "
b1000 C
1.
0/
00
01
06
09
1<
0=
05
0?
0A
1@
1%
0&
0'
#1005000
b1001 "
b1001 C
11
16
1'
#1010000
b1010 "
b1010 C
10
01
06
19
1&
0'
#1015000
b1011 "
b1011 C
11
16
1'
#1020000
b1100 "
b1100 C
1/
00
01
06
09
0<
1=
15
1$
0%
0&
0'
#1025000
b1101 "
b1101 C
11
16
1'
#1030000
b1110 "
b1110 C
10
01
06
19
1&
0'
#1035000
b1111 "
b1111 C
11
16
1'
#1040000
b0 "
b10000 C
b1101 !
b1101 B
b0 C
1-
0.
0/
00
01
09
1<
0=
05
1?
0@
0(
1%
0&
#1045000
b1 "
b1 C
11
06
17
13
1&
0'
#1050000
b10 "
b10 C
10
01
16
07
03
19
1'
#1055000
b11 "
b11 C
11
06
17
13
0&
1;
14
0'
0%
1>
15
0$
1A
1(
#1060000
b100 "
b100 C
1/
00
01
16
07
03
09
0;
04
0<
0>
1=
1'
#1065000
b101 "
b101 C
11
06
17
13
1&
0'
#1070000
b110 "
b110 C
10
01
16
07
03
19
1'
#1075000
b111 "
b111 C
11
06
17
13
0&
1;
14
0'
1%
#1080000
b1000 "
b1000 C
1.
0/
00
01
16
07
03
09
0;
04
1<
0=
05
0?
0A
1@
1'
#1085000
b1001 "
b1001 C
11
06
17
13
1&
0'
#1090000
b1010 "
b1010 C
10
01
16
07
03
19
1'
#1095000
b1011 "
b1011 C
11
06
17
13
0&
1;
14
0'
0%
1>
15
1$
#1100000
b1100 "
b1100 C
1/
00
01
16
07
03
09
0;
04
0<
0>
1=
1'
#1105000
b1101 "
b1101 C
11
06
17
13
1&
0'
#1110000
b1110 "
b1110 C
10
01
16
07
03
19
1'
#1115000
b1111 "
b1111 C
11
06
17
13
0&
1;
14
0'
1%
#1120000
b0 "
b10000 C
b1110 !
b1110 B
b0 C
1,
0-
0.
0/
00
01
1<
0>
0=
1?
0A
0@
07
03
0;
04
05
1&
0(
#1125000
b1 "
b1 C
11
16
1'
#1130000
b10 "
b10 C
10
01
06
09
1:
14
0%
1>
15
0&
0'
0$
1A
1(
#1135000
b11 "
b11 C
11
16
1'
#1140000
b100 "
b100 C
1/
00
01
06
19
0:
04
0<
0>
1=
1&
0'
#1145000
b101 "
b101 C
11
16
1'
#1150000
b110 "
b110 C
10
01
06
09
1:
14
1%
0&
0'
#1155000
b111 "
b111 C
11
16
1'
#1160000
b1000 "
b1000 C
1.
0/
00
01
06
19
0:
04
1<
0=
05
0?
0A
1@
1&
0'
#1165000
b1001 "
b1001 C
11
16
1'
#1170000
b1010 "
b1010 C
10
01
06
09
1:
14
0%
1>
15
0&
0'
1$
#1175000
b1011 "
b1011 C
11
16
1'
#1180000
b1100 "
b1100 C
1/
00
01
06
19
0:
04
0<
0>
1=
1&
0'
#1185000
b1101 "
b1101 C
11
16
1'
#1190000
b1110 "
b1110 C
10
01
06
09
1:
14
1%
0&
0'
#1195000
b1111 "
b1111 C
11
16
1'
#1200000
b0 "
b10000 C
b1111 !
b1111 B
b0 C
1-
0.
0/
00
01
19
0:
04
1<
0=
05
1?
0@
0(
1&
#1205000
b1 "
b1 C
11
06
17
13
0&
1;
14
0'
0%
1>
15
0$
1A
1(
#1210000
b10 "
b10 C
10
01
16
07
03
09
0;
1:
1'
#1215000
b11 "
b11 C
11
06
17
13
1&
0'
#1220000
b100 "
b100 C
1/
00
01
16
07
03
19
0:
04
0<
0>
1=
1'
#1225000
b101 "
b101 C
11
06
17
13
0&
1;
14
0'
1%
#1230000
b110 "
b110 C
10
01
16
07
03
09
0;
1:
1'
#1235000
b111 "
b111 C
11
06
17
13
1&
0'
#1240000
b1000 "
b1000 C
1.
0/
00
01
16
07
03
19
0:
04
1<
0=
05
0?
0A
1@
1'
#1245000
b1001 "
b1001 C
11
06
17
13
0&
1;
14
0'
0%
1>
15
1$
#1250000
b1010 "
b1010 C
10
01
16
07
03
09
0;
1:
1'
#1255000
b1011 "
b1011 C
11
06
17
13
1&
0'
#1260000
b1100 "
b1100 C
1/
00
01
16
07
03
19
0:
04
0<
0>
1=
1'
#1265000
b1101 "
b1101 C
11
06
17
13
0&
1;
14
0'
1%
#1270000
b1110 "
b1110 C
10
01
16
07
03
09
0;
1:
1'
#1275000
b1111 "
b1111 C
11
06
17
13
1&
0'
#1280000
b0 "
b10000 C
b0 !
b10000 B
0*
0+
0,
0-
0.
0/
00
01
07
03
0:
04
0=
05
0@
0(
0$
0%
0&
