synchronous_ctr/behavioral/synchronous_ctr_b.v
module synchronous_ctr_b(
input clk,
input ct,/*control | '0' -> '+' |  '1' -> '-'*/
input cn,/*count*/
input rst,
output [5:0] op
);

reg [5:0] rop;
assign op=rop;

always@(posedge clk or posedge rst)
begin
rop=(rst==1)?5'd0:(cn==1)?(ct==0)?(rop==5'd20)?5'd20:(rop+cn):(rop==5'd0)?5'd0:rop-cn:rop;
end

endmodule

synchronous_ctr/behavioral/testbench.v
`timescale 1ns/1ps
`include "synchronous_ctr_b.v"
module testbench;

reg ct,clk,cn,rst;
wire [5:0] op;

synchronous_ctr_b scb(clk,ct,cn,rst,op);

integer i,j;

initial begin
rst = 0;
clk = 0;
cn = 0;
ct = 0;
end

initial begin
$monitor("Time= %d | op= %d",$time,op);
end

always #10 begin
clk=~clk;
end

//raw test
/*
initial #5 begin
rst = 1;
#10 rst =0;
#10 cn=1;
#10 cn=0;
#10 cn=1;
#10 cn=0;
#10 $finish;
end
*/

initial begin
# 5 rst=1;
#10 rst =0;
for(j=0;j<2;j=j+1)
begin
	for(i=0;i<42;i=i+1)
	begin
		#10 cn=~cn;
	end
	ct=1;
	for(i=0;i<42;i=i+1)
	begin
		#10 cn=~cn;
	end
	ct=~ct;
end
//#10 $finish;
end

initial begin
#1000 rst=1;
#10 rst = 0;
#190 rst = 1;
#10 rst =0;
end

initial #1985 begin
for(j=0;j<50;j=j+1)
begin
//+4
#15 ct=0;
#15 for(i=0;i<8;i=i+1)
begin
#10 cn=~cn;
end
//-2
#10 ct=1;
#10 for(i=0;i<4;i=i+1)
begin
#10 cn=~cn;
end
//+8
#10 ct=0;
#10 for(i=0;i<16;i=i+1)
begin
#10 cn=~cn;
end
//-6
#10 ct=1;
#10 for(i=0;i<11;i=i+1)
begin
#10 cn=~cn;
end
end
#10 $finish;
end

initial begin
$dumpfile("scb.vcd");
$dumpvars;
end

endmodule

synchronous_ctr/behavioral/scb.vcd
$date
    Oct 15, 2019  22:25:41
$end
$version
    TOOL:	ncsim	15.20-s039
$end
$timescale
    1 ps
$end

$scope module testbench $end
$var reg       1 !    ct  $end
$var reg       1 "    clk  $end
$var reg       1 #    cn  $end
$var reg       1 $    rst  $end
$var wire      6 %    op [5:0] $end
$var integer  32 &    i  $end
$var integer  32 '    j  $end

$scope module scb $end
$var wire      1 (    clk  $end
$var wire      1 )    ct  $end
$var wire      1 *    cn  $end
$var wire      1 +    rst  $end
$var wire      6 %    op [5:0] $end
$var reg       6 ,    rop [5:0] $end
$upscope $end

$upscope $end

$enddefinitions $end
$dumpvars
0!
0"
0#
0$
bx %
bx &
bx '
0(
0)
0*
0+
bx ,
$end
#5000
1$
1+
b0 ,
b0 %
#10000
1"
1(
#15000
0$
b0 '
b0 &
0+
#20000
0"
0(
#25000
1#
b1 &
1*
#30000
1"
1(
b1 ,
b1 %
#35000
0#
b10 &
0*
#40000
0"
0(
#45000
1#
b11 &
1*
#50000
1"
1(
b10 ,
b10 %
#55000
0#
b100 &
0*
#60000
0"
0(
#65000
1#
b101 &
1*
#70000
1"
1(
b11 ,
b11 %
#75000
0#
b110 &
0*
#80000
0"
0(
#85000
1#
b111 &
1*
#90000
1"
1(
b100 ,
b100 %
#95000
0#
b1000 &
0*
#100000
0"
0(
#105000
1#
b1001 &
1*
#110000
1"
1(
b101 ,
b101 %
#115000
0#
b1010 &
0*
#120000
0"
0(
#125000
1#
b1011 &
1*
#130000
1"
1(
b110 ,
b110 %
#135000
0#
b1100 &
0*
#140000
0"
0(
#145000
1#
b1101 &
1*
#150000
1"
1(
b111 ,
b111 %
#155000
0#
b1110 &
0*
#160000
0"
0(
#165000
1#
b1111 &
1*
#170000
1"
1(
b1000 ,
b1000 %
#175000
0#
b10000 &
0*
#180000
0"
0(
#185000
1#
b10001 &
1*
#190000
1"
1(
b1001 ,
b1001 %
#195000
0#
b10010 &
0*
#200000
0"
0(
#205000
1#
b10011 &
1*
#210000
1"
1(
b1010 ,
b1010 %
#215000
0#
b10100 &
0*
#220000
0"
0(
#225000
1#
b10101 &
1*
#230000
1"
1(
b1011 ,
b1011 %
#235000
0#
b10110 &
0*
#240000
0"
0(
#245000
1#
b10111 &
1*
#250000
1"
1(
b1100 ,
b1100 %
#255000
0#
b11000 &
0*
#260000
0"
0(
#265000
1#
b11001 &
1*
#270000
1"
1(
b1101 ,
b1101 %
#275000
0#
b11010 &
0*
#280000
0"
0(
#285000
1#
b11011 &
1*
#290000
1"
1(
b1110 ,
b1110 %
#295000
0#
b11100 &
0*
#300000
0"
0(
#305000
1#
b11101 &
1*
#310000
1"
1(
b1111 ,
b1111 %
#315000
0#
b11110 &
0*
#320000
0"
0(
#325000
1#
b11111 &
1*
#330000
1"
1(
b10000 ,
b10000 %
#335000
0#
b100000 &
0*
#340000
0"
0(
#345000
1#
b100001 &
1*
#350000
1"
1(
b10001 ,
b10001 %
#355000
0#
b100010 &
0*
#360000
0"
0(
#365000
1#
b100011 &
1*
#370000
1"
1(
b10010 ,
b10010 %
#375000
0#
b100100 &
0*
#380000
0"
0(
#385000
1#
b100101 &
1*
#390000
1"
1(
b10011 ,
b10011 %
#395000
0#
b100110 &
0*
#400000
0"
0(
#405000
1#
b100111 &
1*
#410000
1"
1(
b10100 ,
b10100 %
#415000
0#
b101000 &
0*
#420000
0"
0(
#425000
1#
b101001 &
1*
#430000
1"
1(
#435000
0#
b101010 &
1!
b0 &
1)
0*
#440000
0"
0(
#445000
1#
b1 &
1*
#450000
1"
1(
b10011 ,
b10011 %
#455000
0#
b10 &
0*
#460000
0"
0(
#465000
1#
b11 &
1*
#470000
1"
1(
b10010 ,
b10010 %
#475000
0#
b100 &
0*
#480000
0"
0(
#485000
1#
b101 &
1*
#490000
1"
1(
b10001 ,
b10001 %
#495000
0#
b110 &
0*
#500000
0"
0(
#505000
1#
b111 &
1*
#510000
1"
1(
b10000 ,
b10000 %
#515000
0#
b1000 &
0*
#520000
0"
0(
#525000
1#
b1001 &
1*
#530000
1"
1(
b1111 ,
b1111 %
#535000
0#
b1010 &
0*
#540000
0"
0(
#545000
1#
b1011 &
1*
#550000
1"
1(
b1110 ,
b1110 %
#555000
0#
b1100 &
0*
#560000
0"
0(
#565000
1#
b1101 &
1*
#570000
1"
1(
b1101 ,
b1101 %
#575000
0#
b1110 &
0*
#580000
0"
0(
#585000
1#
b1111 &
1*
#590000
1"
1(
b1100 ,
b1100 %
#595000
0#
b10000 &
0*
#600000
0"
0(
#605000
1#
b10001 &
1*
#610000
1"
1(
b1011 ,
b1011 %
#615000
0#
b10010 &
0*
#620000
0"
0(
#625000
1#
b10011 &
1*
#630000
1"
1(
b1010 ,
b1010 %
#635000
0#
b10100 &
0*
#640000
0"
0(
#645000
1#
b10101 &
1*
#650000
1"
1(
b1001 ,
b1001 %
#655000
0#
b10110 &
0*
#660000
0"
0(
#665000
1#
b10111 &
1*
#670000
1"
1(
b1000 ,
b1000 %
#675000
0#
b11000 &
0*
#680000
0"
0(
#685000
1#
b11001 &
1*
#690000
1"
1(
b111 ,
b111 %
#695000
0#
b11010 &
0*
#700000
0"
0(
#705000
1#
b11011 &
1*
#710000
1"
1(
b110 ,
b110 %
#715000
0#
b11100 &
0*
#720000
0"
0(
#725000
1#
b11101 &
1*
#730000
1"
1(
b101 ,
b101 %
#735000
0#
b11110 &
0*
#740000
0"
0(
#745000
1#
b11111 &
1*
#750000
1"
1(
b100 ,
b100 %
#755000
0#
b100000 &
0*
#760000
0"
0(
#765000
1#
b100001 &
1*
#770000
1"
1(
b11 ,
b11 %
#775000
0#
b100010 &
0*
#780000
0"
0(
#785000
1#
b100011 &
1*
#790000
1"
1(
b10 ,
b10 %
#795000
0#
b100100 &
0*
#800000
0"
0(
#805000
1#
b100101 &
1*
#810000
1"
1(
b1 ,
b1 %
#815000
0#
b100110 &
0*
#820000
0"
0(
#825000
1#
b100111 &
1*
#830000
1"
1(
b0 ,
b0 %
#835000
0#
b101000 &
0*
#840000
0"
0(
#845000
1#
b101001 &
1*
#850000
1"
1(
#855000
0#
b101010 &
0!
b1 '
b0 &
0)
0*
#860000
0"
0(
#865000
1#
b1 &
1*
#870000
1"
1(
b1 ,
b1 %
#875000
0#
b10 &
0*
#880000
0"
0(
#885000
1#
b11 &
1*
#890000
1"
1(
b10 ,
b10 %
#895000
0#
b100 &
0*
#900000
0"
0(
#905000
1#
b101 &
1*
#910000
1"
1(
b11 ,
b11 %
#915000
0#
b110 &
0*
#920000
0"
0(
#925000
1#
b111 &
1*
#930000
1"
1(
b100 ,
b100 %
#935000
0#
b1000 &
0*
#940000
0"
0(
#945000
1#
b1001 &
1*
#950000
1"
1(
b101 ,
b101 %
#955000
0#
b1010 &
0*
#960000
0"
0(
#965000
1#
b1011 &
1*
#970000
1"
1(
b110 ,
b110 %
#975000
0#
b1100 &
0*
#980000
0"
0(
#985000
1#
b1101 &
1*
#990000
1"
1(
b111 ,
b111 %
#995000
0#
b1110 &
0*
#1000000
1$
0"
0(
1+
b0 ,
b0 %
#1005000
1#
b1111 &
1*
#1010000
0$
1"
1(
0+
b1 ,
b1 %
#1015000
0#
b10000 &
0*
#1020000
0"
0(
#1025000
1#
b10001 &
1*
#1030000
1"
1(
b10 ,
b10 %
#1035000
0#
b10010 &
0*
#1040000
0"
0(
#1045000
1#
b10011 &
1*
#1050000
1"
1(
b11 ,
b11 %
#1055000
0#
b10100 &
0*
#1060000
0"
0(
#1065000
1#
b10101 &
1*
#1070000
1"
1(
b100 ,
b100 %
#1075000
0#
b10110 &
0*
#1080000
0"
0(
#1085000
1#
b10111 &
1*
#1090000
1"
1(
b101 ,
b101 %
#1095000
0#
b11000 &
0*
#1100000
0"
0(
#1105000
1#
b11001 &
1*
#1110000
1"
1(
b110 ,
b110 %
#1115000
0#
b11010 &
0*
#1120000
0"
0(
#1125000
1#
b11011 &
1*
#1130000
1"
1(
b111 ,
b111 %
#1135000
0#
b11100 &
0*
#1140000
0"
0(
#1145000
1#
b11101 &
1*
#1150000
1"
1(
b1000 ,
b1000 %
#1155000
0#
b11110 &
0*
#1160000
0"
0(
#1165000
1#
b11111 &
1*
#1170000
1"
1(
b1001 ,
b1001 %
#1175000
0#
b100000 &
0*
#1180000
0"
0(
#1185000
1#
b100001 &
1*
#1190000
1"
1(
b1010 ,
b1010 %
#1195000
0#
b100010 &
0*
#1200000
1$
0"
0(
1+
b0 ,
b0 %
#1205000
1#
b100011 &
1*
#1210000
0$
1"
1(
0+
b1 ,
b1 %
#1215000
0#
b100100 &
0*
#1220000
0"
0(
#1225000
1#
b100101 &
1*
#1230000
1"
1(
b10 ,
b10 %
#1235000
0#
b100110 &
0*
#1240000
0"
0(
#1245000
1#
b100111 &
1*
#1250000
1"
1(
b11 ,
b11 %
#1255000
0#
b101000 &
0*
#1260000
0"
0(
#1265000
1#
b101001 &
1*
#1270000
1"
1(
b100 ,
b100 %
#1275000
0#
b101010 &
1!
b0 &
1)
0*
#1280000
0"
0(
#1285000
1#
b1 &
1*
#1290000
1"
1(
b11 ,
b11 %
#1295000
0#
b10 &
0*
#1300000
0"
0(
#1305000
1#
b11 &
1*
#1310000
1"
1(
b10 ,
b10 %
#1315000
0#
b100 &
0*
#1320000
0"
0(
#1325000
1#
b101 &
1*
#1330000
1"
1(
b1 ,
b1 %
#1335000
0#
b110 &
0*
#1340000
0"
0(
#1345000
1#
b111 &
1*
#1350000
1"
1(
b0 ,
b0 %
#1355000
0#
b1000 &
0*
#1360000
0"
0(
#1365000
1#
b1001 &
1*
#1370000
1"
1(
#1375000
0#
b1010 &
0*
#1380000
0"
0(
#1385000
1#
b1011 &
1*
#1390000
1"
1(
#1395000
0#
b1100 &
0*
#1400000
0"
0(
#1405000
1#
b1101 &
1*
#1410000
1"
1(
#1415000
0#
b1110 &
0*
#1420000
0"
0(
#1425000
1#
b1111 &
1*
#1430000
1"
1(
#1435000
0#
b10000 &
0*
#1440000
0"
0(
#1445000
1#
b10001 &
1*
#1450000
1"
1(
#1455000
0#
b10010 &
0*
#1460000
0"
0(
#1465000
1#
b10011 &
1*
#1470000
1"
1(
#1475000
0#
b10100 &
0*
#1480000
0"
0(
#1485000
1#
b10101 &
1*
#1490000
1"
1(
#1495000
0#
b10110 &
0*
#1500000
0"
0(
#1505000
1#
b10111 &
1*
#1510000
1"
1(
#1515000
0#
b11000 &
0*
#1520000
0"
0(
#1525000
1#
b11001 &
1*
#1530000
1"
1(
#1535000
0#
b11010 &
0*
#1540000
0"
0(
#1545000
1#
b11011 &
1*
#1550000
1"
1(
#1555000
0#
b11100 &
0*
#1560000
0"
0(
#1565000
1#
b11101 &
1*
#1570000
1"
1(
#1575000
0#
b11110 &
0*
#1580000
0"
0(
#1585000
1#
b11111 &
1*
#1590000
1"
1(
#1595000
0#
b100000 &
0*
#1600000
0"
0(
#1605000
1#
b100001 &
1*
#1610000
1"
1(
#1615000
0#
b100010 &
0*
#1620000
0"
0(
#1625000
1#
b100011 &
1*
#1630000
1"
1(
#1635000
0#
b100100 &
0*
#1640000
0"
0(
#1645000
1#
b100101 &
1*
#1650000
1"
1(
#1655000
0#
b100110 &
0*
#1660000
0"
0(
#1665000
1#
b100111 &
1*
#1670000
1"
1(
#1675000
0#
b101000 &
0*
#1680000
0"
0(
#1685000
1#
b101001 &
1*
#1690000
1"
1(
#1695000
0#
b101010 &
0!
b10 '
0)
0*
#1700000
0"
0(
#1710000
1"
1(
#1720000
0"
0(
#1730000
1"
1(
#1740000
0"
0(
#1750000
1"
1(
#1760000
0"
0(
#1770000
1"
1(
#1780000
0"
0(
#1790000
1"
1(
#1800000
0"
0(
#1810000
1"
1(
#1820000
0"
0(
#1830000
1"
1(
#1840000
0"
0(
#1850000
1"
1(
#1860000
0"
0(
#1870000
1"
1(
#1880000
0"
0(
#1890000
1"
1(
#1900000
0"
0(
#1910000
1"
1(
#1920000
0"
0(
#1930000
1"
1(
#1940000
0"
0(
#1950000
1"
1(
#1960000
0"
0(
#1970000
1"
1(
#1980000
0"
0(
#1985000
b0 '
#1990000
1"
1(
#2000000
0"
0(
#2010000
1"
1(
#2015000
b0 &
#2020000
0"
0(
#2025000
1#
b1 &
1*
#2030000
1"
1(
b1 ,
b1 %
#2035000
0#
b10 &
0*
#2040000
0"
0(
#2045000
1#
b11 &
1*
#2050000
1"
1(
b10 ,
b10 %
#2055000
0#
b100 &
0*
#2060000
0"
0(
#2065000
1#
b101 &
1*
#2070000
1"
1(
b11 ,
b11 %
#2075000
0#
b110 &
0*
#2080000
0"
0(
#2085000
1#
b111 &
1*
#2090000
1"
1(
b100 ,
b100 %
#2095000
0#
b1000 &
0*
#2100000
0"
0(
#2105000
1!
1)
#2110000
1"
1(
#2115000
b0 &
#2120000
0"
0(
#2125000
1#
b1 &
1*
#2130000
1"
1(
b11 ,
b11 %
#2135000
0#
b10 &
0*
#2140000
0"
0(
#2145000
1#
b11 &
1*
#2150000
1"
1(
b10 ,
b10 %
#2155000
0#
b100 &
0*
#2160000
0"
0(
#2165000
0!
0)
#2170000
1"
1(
#2175000
b0 &
#2180000
0"
0(
#2185000
1#
b1 &
1*
#2190000
1"
1(
b11 ,
b11 %
#2195000
0#
b10 &
0*
#2200000
0"
0(
#2205000
1#
b11 &
1*
#2210000
1"
1(
b100 ,
b100 %
#2215000
0#
b100 &
0*
#2220000
0"
0(
#2225000
1#
b101 &
1*
#2230000
1"
1(
b101 ,
b101 %
#2235000
0#
b110 &
0*
#2240000
0"
0(
#2245000
1#
b111 &
1*
#2250000
1"
1(
b110 ,
b110 %
#2255000
0#
b1000 &
0*
#2260000
0"
0(
#2265000
1#
b1001 &
1*
#2270000
1"
1(
b111 ,
b111 %
#2275000
0#
b1010 &
0*
#2280000
0"
0(
#2285000
1#
b1011 &
1*
#2290000
1"
1(
b1000 ,
b1000 %
#2295000
0#
b1100 &
0*
#2300000
0"
0(
#2305000
1#
b1101 &
1*
#2310000
1"
1(
b1001 ,
b1001 %
#2315000
0#
b1110 &
0*
#2320000
0"
0(
#2325000
1#
b1111 &
1*
#2330000
1"
1(
b1010 ,
b1010 %
#2335000
0#
b10000 &
0*
#2340000
0"
0(
#2345000
1!
1)
#2350000
1"
1(
#2355000
b0 &
#2360000
0"
0(
#2365000
1#
b1 &
1*
#2370000
1"
1(
b1001 ,
b1001 %
#2375000
0#
b10 &
0*
#2380000
0"
0(
#2385000
1#
b11 &
1*
#2390000
1"
1(
b1000 ,
b1000 %
#2395000
0#
b100 &
0*
#2400000
0"
0(
#2405000
1#
b101 &
1*
#2410000
1"
1(
b111 ,
b111 %
#2415000
0#
b110 &
0*
#2420000
0"
0(
#2425000
1#
b111 &
1*
#2430000
1"
1(
b110 ,
b110 %
#2435000
0#
b1000 &
0*
#2440000
0"
0(
#2445000
1#
b1001 &
1*
#2450000
1"
1(
b101 ,
b101 %
#2455000
0#
b1010 &
0*
#2460000
0"
0(
#2465000
1#
b1011 &
b1 '
1*
#2470000
1"
1(
b100 ,
b100 %
#2480000
0!
0"
0(
0)
#2490000
1"
1(
b101 ,
b101 %
#2495000
b0 &
#2500000
0"
0(
#2505000
0#
b1 &
0*
#2510000
1"
1(
#2515000
1#
b10 &
1*
#2520000
0"
0(
#2525000
0#
b11 &
0*
#2530000
1"
1(
#2535000
1#
b100 &
1*
#2540000
0"
0(
#2545000
0#
b101 &
0*
#2550000
1"
1(
#2555000
1#
b110 &
1*
#2560000
0"
0(
#2565000
0#
b111 &
0*
#2570000
1"
1(
#2575000
1#
b1000 &
1*
#2580000
0"
0(
#2585000
1!
1)
#2590000
1"
1(
b100 ,
b100 %
#2595000
b0 &
#2600000
0"
0(
#2605000
0#
b1 &
0*
#2610000
1"
1(
#2615000
1#
b10 &
1*
#2620000
0"
0(
#2625000
0#
b11 &
0*
#2630000
1"
1(
#2635000
1#
b100 &
1*
#2640000
0"
0(
#2645000
0!
0)
#2650000
1"
1(
b101 ,
b101 %
#2655000
b0 &
#2660000
0"
0(
#2665000
0#
b1 &
0*
#2670000
1"
1(
#2675000
1#
b10 &
1*
#2680000
0"
0(
#2685000
0#
b11 &
0*
#2690000
1"
1(
#2695000
1#
b100 &
1*
#2700000
0"
0(
#2705000
0#
b101 &
0*
#2710000
1"
1(
#2715000
1#
b110 &
1*
#2720000
0"
0(
#2725000
0#
b111 &
0*
#2730000
1"
1(
#2735000
1#
b1000 &
1*
#2740000
0"
0(
#2745000
0#
b1001 &
0*
#2750000
1"
1(
#2755000
1#
b1010 &
1*
#2760000
0"
0(
#2765000
0#
b1011 &
0*
#2770000
1"
1(
#2775000
1#
b1100 &
1*
#2780000
0"
0(
#2785000
0#
b1101 &
0*
#2790000
1"
1(
#2795000
1#
b1110 &
1*
#2800000
0"
0(
#2805000
0#
b1111 &
0*
#2810000
1"
1(
#2815000
1#
b10000 &
1*
#2820000
0"
0(
#2825000
1!
1)
#2830000
1"
1(
b100 ,
b100 %
#2835000
b0 &
#2840000
0"
0(
#2845000
0#
b1 &
0*
#2850000
1"
1(
#2855000
1#
b10 &
1*
#2860000
0"
0(
#2865000
0#
b11 &
0*
#2870000
1"
1(
#2875000
1#
b100 &
1*
#2880000
0"
0(
#2885000
0#
b101 &
0*
#2890000
1"
1(
#2895000
1#
b110 &
1*
#2900000
0"
0(
#2905000
0#
b111 &
0*
#2910000
1"
1(
#2915000
1#
b1000 &
1*
#2920000
0"
0(
#2925000
0#
b1001 &
0*
#2930000
1"
1(
#2935000
1#
b1010 &
1*
#2940000
0"
0(
#2945000
0#
b1011 &
b10 '
0*
#2950000
1"
1(
#2960000
0!
0"
0(
0)
#2970000
1"
1(
#2975000
b0 &
#2980000
0"
0(
#2985000
1#
b1 &
1*
#2990000
1"
1(
b101 ,
b101 %
#2995000
0#
b10 &
0*
#3000000
0"
0(
#3005000
1#
b11 &
1*
#3010000
1"
1(
b110 ,
b110 %
#3015000
0#
b100 &
0*
#3020000
0"
0(
#3025000
1#
b101 &
1*
#3030000
1"
1(
b111 ,
b111 %
#3035000
0#
b110 &
0*
#3040000
0"
0(
#3045000
1#
b111 &
1*
#3050000
1"
1(
b1000 ,
b1000 %
#3055000
0#
b1000 &
0*
#3060000
0"
0(
#3065000
1!
1)
#3070000
1"
1(
#3075000
b0 &
#3080000
0"
0(
#3085000
1#
b1 &
1*
#3090000
1"
1(
b111 ,
b111 %
#3095000
0#
b10 &
0*
#3100000
0"
0(
#3105000
1#
b11 &
1*
#3110000
1"
1(
b110 ,
b110 %
#3115000
0#
b100 &
0*
#3120000
0"
0(
#3125000
0!
0)
#3130000
1"
1(
#3135000
b0 &
#3140000
0"
0(
#3145000
1#
b1 &
1*
#3150000
1"
1(
b111 ,
b111 %
#3155000
0#
b10 &
0*
#3160000
0"
0(
#3165000
1#
b11 &
1*
#3170000
1"
1(
b1000 ,
b1000 %
#3175000
0#
b100 &
0*
#3180000
0"
0(
#3185000
1#
b101 &
1*
#3190000
1"
1(
b1001 ,
b1001 %
#3195000
0#
b110 &
0*
#3200000
0"
0(
#3205000
1#
b111 &
1*
#3210000
1"
1(
b1010 ,
b1010 %
#3215000
0#
b1000 &
0*
#3220000
0"
0(
#3225000
1#
b1001 &
1*
#3230000
1"
1(
b1011 ,
b1011 %
#3235000
0#
b1010 &
0*
#3240000
0"
0(
#3245000
1#
b1011 &
1*
#3250000
1"
1(
b1100 ,
b1100 %
#3255000
0#
b1100 &
0*
#3260000
0"
0(
#3265000
1#
b1101 &
1*
#3270000
1"
1(
b1101 ,
b1101 %
#3275000
0#
b1110 &
0*
#3280000
0"
0(
#3285000
1#
b1111 &
1*
#3290000
1"
1(
b1110 ,
b1110 %
#3295000
0#
b10000 &
0*
#3300000
0"
0(
#3305000
1!
1)
#3310000
1"
1(
#3315000
b0 &
#3320000
0"
0(
#3325000
1#
b1 &
1*
#3330000
1"
1(
b1101 ,
b1101 %
#3335000
0#
b10 &
0*
#3340000
0"
0(
#3345000
1#
b11 &
1*
#3350000
1"
1(
b1100 ,
b1100 %
#3355000
0#
b100 &
0*
#3360000
0"
0(
#3365000
1#
b101 &
1*
#3370000
1"
1(
b1011 ,
b1011 %
#3375000
0#
b110 &
0*
#3380000
0"
0(
#3385000
1#
b111 &
1*
#3390000
1"
1(
b1010 ,
b1010 %
#3395000
0#
b1000 &
0*
#3400000
0"
0(
#3405000
1#
b1001 &
1*
#3410000
1"
1(
b1001 ,
b1001 %
#3415000
0#
b1010 &
0*
#3420000
0"
0(
#3425000
1#
b1011 &
b11 '
1*
#3430000
1"
1(
b1000 ,
b1000 %
#3440000
0!
0"
0(
0)
#3450000
1"
1(
b1001 ,
b1001 %
#3455000
b0 &
#3460000
0"
0(
#3465000
0#
b1 &
0*
#3470000
1"
1(
#3475000
1#
b10 &
1*
#3480000
0"
0(
#3485000
0#
b11 &
0*
#3490000
1"
1(
#3495000
1#
b100 &
1*
#3500000
0"
0(
#3505000
0#
b101 &
0*
#3510000
1"
1(
#3515000
1#
b110 &
1*
#3520000
0"
0(
#3525000
0#
b111 &
0*
#3530000
1"
1(
#3535000
1#
b1000 &
1*
#3540000
0"
0(
#3545000
1!
1)
#3550000
1"
1(
b1000 ,
b1000 %
#3555000
b0 &
#3560000
0"
0(
#3565000
0#
b1 &
0*
#3570000
1"
1(
#3575000
1#
b10 &
1*
#3580000
0"
0(
#3585000
0#
b11 &
0*
#3590000
1"
1(
#3595000
1#
b100 &
1*
#3600000
0"
0(
#3605000
0!
0)
#3610000
1"
1(
b1001 ,
b1001 %
#3615000
b0 &
#3620000
0"
0(
#3625000
0#
b1 &
0*
#3630000
1"
1(
#3635000
1#
b10 &
1*
#3640000
0"
0(
#3645000
0#
b11 &
0*
#3650000
1"
1(
#3655000
1#
b100 &
1*
#3660000
0"
0(
#3665000
0#
b101 &
0*
#3670000
1"
1(
#3675000
1#
b110 &
1*
#3680000
0"
0(
#3685000
0#
b111 &
0*
#3690000
1"
1(
#3695000
1#
b1000 &
1*
#3700000
0"
0(
#3705000
0#
b1001 &
0*
#3710000
1"
1(
#3715000
1#
b1010 &
1*
#3720000
0"
0(
#3725000
0#
b1011 &
0*
#3730000
1"
1(
#3735000
1#
b1100 &
1*
#3740000
0"
0(
#3745000
0#
b1101 &
0*
#3750000
1"
1(
#3755000
1#
b1110 &
1*
#3760000
0"
0(
#3765000
0#
b1111 &
0*
#3770000
1"
1(
#3775000
1#
b10000 &
1*
#3780000
0"
0(
#3785000
1!
1)
#3790000
1"
1(
b1000 ,
b1000 %
#3795000
b0 &
#3800000
0"
0(
#3805000
0#
b1 &
0*
#3810000
1"
1(
#3815000
1#
b10 &
1*
#3820000
0"
0(
#3825000
0#
b11 &
0*
#3830000
1"
1(
#3835000
1#
b100 &
1*
#3840000
0"
0(
#3845000
0#
b101 &
0*
#3850000
1"
1(
#3855000
1#
b110 &
1*
#3860000
0"
0(
#3865000
0#
b111 &
0*
#3870000
1"
1(
#3875000
1#
b1000 &
1*
#3880000
0"
0(
#3885000
0#
b1001 &
0*
#3890000
1"
1(
#3895000
1#
b1010 &
1*
#3900000
0"
0(
#3905000
0#
b1011 &
b100 '
0*
#3910000
1"
1(
#3920000
0!
0"
0(
0)
#3930000
1"
1(
#3935000
b0 &
#3940000
0"
0(
#3945000
1#
b1 &
1*
#3950000
1"
1(
b1001 ,
b1001 %
#3955000
0#
b10 &
0*
#3960000
0"
0(
#3965000
1#
b11 &
1*
#3970000
1"
1(
b1010 ,
b1010 %
#3975000
0#
b100 &
0*
#3980000
0"
0(
#3985000
1#
b101 &
1*
#3990000
1"
1(
b1011 ,
b1011 %
#3995000
0#
b110 &
0*
#4000000
0"
0(
#4005000
1#
b111 &
1*
#4010000
1"
1(
b1100 ,
b1100 %
#4015000
0#
b1000 &
0*
#4020000
0"
0(
#4025000
1!
1)
#4030000
1"
1(
#4035000
b0 &
#4040000
0"
0(
#4045000
1#
b1 &
1*
#4050000
1"
1(
b1011 ,
b1011 %
#4055000
0#
b10 &
0*
#4060000
0"
0(
#4065000
1#
b11 &
1*
#4070000
1"
1(
b1010 ,
b1010 %
#4075000
0#
b100 &
0*
#4080000
0"
0(
#4085000
0!
0)
#4090000
1"
1(
#4095000
b0 &
#4100000
0"
0(
#4105000
1#
b1 &
1*
#4110000
1"
1(
b1011 ,
b1011 %
#4115000
0#
b10 &
0*
#4120000
0"
0(
#4125000
1#
b11 &
1*
#4130000
1"
1(
b1100 ,
b1100 %
#4135000
0#
b100 &
0*
#4140000
0"
0(
#4145000
1#
b101 &
1*
#4150000
1"
1(
b1101 ,
b1101 %
#4155000
0#
b110 &
0*
#4160000
0"
0(
#4165000
1#
b111 &
1*
#4170000
1"
1(
b1110 ,
b1110 %
#4175000
0#
b1000 &
0*
#4180000
0"
0(
#4185000
1#
b1001 &
1*
#4190000
1"
1(
b1111 ,
b1111 %
#4195000
0#
b1010 &
0*
#4200000
0"
0(
#4205000
1#
b1011 &
1*
#4210000
1"
1(
b10000 ,
b10000 %
#4215000
0#
b1100 &
0*
#4220000
0"
0(
#4225000
1#
b1101 &
1*
#4230000
1"
1(
b10001 ,
b10001 %
#4235000
0#
b1110 &
0*
#4240000
0"
0(
#4245000
1#
b1111 &
1*
#4250000
1"
1(
b10010 ,
b10010 %
#4255000
0#
b10000 &
0*
#4260000
0"
0(
#4265000
1!
1)
#4270000
1"
1(
#4275000
b0 &
#4280000
0"
0(
#4285000
1#
b1 &
1*
#4290000
1"
1(
b10001 ,
b10001 %
#4295000
0#
b10 &
0*
#4300000
0"
0(
#4305000
1#
b11 &
1*
#4310000
1"
1(
b10000 ,
b10000 %
#4315000
0#
b100 &
0*
#4320000
0"
0(
#4325000
1#
b101 &
1*
#4330000
1"
1(
b1111 ,
b1111 %
#4335000
0#
b110 &
0*
#4340000
0"
0(
#4345000
1#
b111 &
1*
#4350000
1"
1(
b1110 ,
b1110 %
#4355000
0#
b1000 &
0*
#4360000
0"
0(
#4365000
1#
b1001 &
1*
#4370000
1"
1(
b1101 ,
b1101 %
#4375000
0#
b1010 &
0*
#4380000
0"
0(
#4385000
1#
b1011 &
b101 '
1*
#4390000
1"
1(
b1100 ,
b1100 %
#4400000
0!
0"
0(
0)
#4410000
1"
1(
b1101 ,
b1101 %
#4415000
b0 &
#4420000
0"
0(
#4425000
0#
b1 &
0*
#4430000
1"
1(
#4435000
1#
b10 &
1*
#4440000
0"
0(
#4445000
0#
b11 &
0*
#4450000
1"
1(
#4455000
1#
b100 &
1*
#4460000
0"
0(
#4465000
0#
b101 &
0*
#4470000
1"
1(
#4475000
1#
b110 &
1*
#4480000
0"
0(
#4485000
0#
b111 &
0*
#4490000
1"
1(
#4495000
1#
b1000 &
1*
#4500000
0"
0(
#4505000
1!
1)
#4510000
1"
1(
b1100 ,
b1100 %
#4515000
b0 &
#4520000
0"
0(
#4525000
0#
b1 &
0*
#4530000
1"
1(
#4535000
1#
b10 &
1*
#4540000
0"
0(
#4545000
0#
b11 &
0*
#4550000
1"
1(
#4555000
1#
b100 &
1*
#4560000
0"
0(
#4565000
0!
0)
#4570000
1"
1(
b1101 ,
b1101 %
#4575000
b0 &
#4580000
0"
0(
#4585000
0#
b1 &
0*
#4590000
1"
1(
#4595000
1#
b10 &
1*
#4600000
0"
0(
#4605000
0#
b11 &
0*
#4610000
1"
1(
#4615000
1#
b100 &
1*
#4620000
0"
0(
#4625000
0#
b101 &
0*
#4630000
1"
1(
#4635000
1#
b110 &
1*
#4640000
0"
0(
#4645000
0#
b111 &
0*
#4650000
1"
1(
#4655000
1#
b1000 &
1*
#4660000
0"
0(
#4665000
0#
b1001 &
0*
#4670000
1"
1(
#4675000
1#
b1010 &
1*
#4680000
0"
0(
#4685000
0#
b1011 &
0*
#4690000
1"
1(
#4695000
1#
b1100 &
1*
#4700000
0"
0(
